Workbook

Sheet Monthly Activity Log
A1: BA Team – Monthly Activity Log
A2: 📋 Fill in one row per activity. All yellow-highlighted columns are mandatory. Select values from the dropdown lists where provided.
A3: # | B3: Month | C3: Team Member | D3: Department / Module | E3: Ticket / Ref No. | F3: Project / Activity Name | G3: Description of Work | H3: Client | I3: Category | J3: Priority | K3: Status | L3: Notes / Blockers
A4: 1 | B4: April | C4: Shennaz | D4: SAP SD | F4: Aviation Surcharge (ZAVS) | G4: Configured and tested ZAVS pricing condition in QAS. Investigated condition determination and access sequence behaviour. Prepared emergency change documentation and UAT support. | H4: PetroSA | I4: Project | J4: High | K4: Completed
A5: 2 | B5: April | C5: Shennaz | D5: SAP MM | F5: Contract Expiry Control | G5: Investigated contract expiry controls for PO/SES processing. Performed QAS testing and documented findings for ABAP team. | H5: PetroSA | I5: Incident/Bug Fix | J5: Low | K5: Completed
A6: 3 | B6: April | C6: Shennaz | D6: SAP FI | F6: Ghana Company Code Project | G6: Reviewed chart of accounts mapping, account groups, number ranges and company code configuration requirements. | H6: PetroSA Ghana | I6: Project | J6: Medium | K6: In Progress
A7: 4 | B7: April | C7: Shennaz | D7: SAP FI/TRM | F7: Treasury Corrections | G7: Assisted with TBB1/TPM10 treasury postings and correction process analysis. | H7: PetroSA | I7: User Support | J7: Low | K7: Completed
A8: 5 | B8: April | C8: Shennaz | D8: SAP SD | F8: Credit Exposure Investigation | G8: Analysed customer credit exposure update issue and RVKRED77 behaviour. | H8: PetroSA | I8: Incident/Bug Fix | J8: Low | K8: Completed
A9: 6 | B9: April | C9: Shennaz | D9: SAP Travel | F9: Travel Management Support | G9: Resolved trip and expense claim issues and provided user support. | H9: SANPC | I9: Incident/Bug Fix | J9: Low | K9: Completed
A10: 7 | B10: April | C10: Shennaz | D10: SAP FI | F10: Period-End Support | G10: Supported period-end activities including balance carry-forward and account investigations. | H10: PetroSA | I10: Incident/Bug Fix | J10: Low | K10: Completed
A11: 8 | B11: April | C11: Shennaz | D11: SAP MM | F11: PO Output Notifications | G11: Assisted in Investigated workflow and email notification issues for purchase orders. | H11: PetroSA | I11: Incident/Bug Fix | J11: Low | K11: Completed
A12: 9 | B12: April | C12: Nyameka | D12: HR/Payroll | E12: 69585655 | F12: Payslips- October 2025 | G12: Incorrect for SFF due to SARS Bi-Annual. SARS Payment is not aligned to Sage for SANPC. | H12: SANPC | I12: Admin/Config | J12: Low | K12: In Progress
A13: 10 | B13: April | C13: Nyameka | D13: HR/Payroll | E13: 69585765 | F13: July Backpay line vs Backpay Overtime line | G13: July Backpay Line to be aligned and removed from Overtime in August 2025 payroll. | H13: SANPC | I13: Admin/Config | J13: Low | K13: In Progress
A14: 11 | B14: April | C14: Nyameka | D14: HR/Payroll | E14: 69585703 | F14: EMP 201 Payments Sep to Nov | G14: Payment does not reconcile due to item on Line 5. | H14: SANPC | I14: Admin/Config | J14: Low | K14: In Progress
A15: 12 | B15: April | C15: Nyameka | D15: HR/Payroll | E15: 69585655 | F15: October 2025 Payslip Discrepancy | G15: The SARS payment reflected in the October 2025 payslips is not aligned with Sage records for SANPC. | H15: SANPC | I15: Admin/Config | J15: Low | K15: In Progress
A16: 13 | B16: April | C16: Nyameka | D16: HR/Payroll | E16: 71880714 | F16: Run Time error | G16: Run time error investigation. | H16: SANPC | I16: Incident/Bug Fix | J16: Low | K16: In Progress
A17: 14 | B17: April | C17: Nyameka | D17: SAP HR | F17: PetroSA Solidarity Premium Update | G17: PetroSA Solidarity Premium Update. | H17: PetroSA | I17: Admin/Config | J17: Low | K17: Completed
A18: 15 | B18: April | C18: Nyameka | D18: SAP HR | F18: PetroSA Mortgage Premium Update | G18: PetroSA Mortgage Premium Update. | H18: PetroSA | I18: Admin/Config | J18: Low | K18: Completed
A19: 16 | B19: April | C19: Nyameka | D19: SAP HR | F19: PetroSA COID Premium Update | G19: PetroSA COID Premium Update. | H19: PetroSA | I19: Admin/Config | J19: Low | K19: Completed
A20: 17 | B20: April | C20: Lindiwe | D20: IT | E20: 77317642 | F20: Signing Hub | G20: Signing hub access. | H20: SANPC | I20: Incident/Bug Fix | J20: Low | K20: Completed
A21: 18 | B21: April | C21: Lindiwe | D21: IT | E21: 76861404 | F21: BPM - Password Resets | G21: Resetting all BPM/ACCPAC passwords for the users that are using the system. | H21: SANPC | I21: User Support | J21: Low | K21: Completed
A22: 19 | B22: April | C22: Lindiwe | D22: IT | E22: Emails | F22: BPM - Business Connect Loading | G22: Loading Business connect, MPLS, Network points, Sage Support PO GRV. | H22: SANPC | I22: User Support | J22: Low | K22: Completed
A23: 20 | B23: April | C23: Lindiwe | D23: Finance | E23: Emails | F23: BPM - RCP Investigation | G23: Check where the RCPs are stuck. | H23: SANPC/SFF | I23: Incident/Bug Fix | J23: Low | K23: Completed
A24: 21 | B24: April | C24: Lindiwe | D24: IT | E24: Emails | F24: BPM - Req Allocation | G24: Allocating the Reqs to correct approvers. | H24: SANPC | I24: User Support | J24: Low | K24: Completed
A25: 22 | B25: April | C25: Lindiwe | D25: IT | E25: Emails | F25: BPM - Transaction Re-allocation | G25: Re-allocate transactions to Sechaba for approval. | H25: SANPC | I25: User Support | J25: Low | K25: Completed
A26: 23 | B26: April | C26: Lindiwe | D26: IT | E26: Emails | F26: BPM - Scope of Work Loading | G26: Loading Scope of work for UPS, VMware licenses and Dell laptop Charges. | H26: SANPC | I26: User Support | J26: Low | K26: Completed
A27: 24 | B27: April | C27: Lindiwe | D27: IT | E27: 77314897 | F27: QBCON Installation | G27: Installation of QBCON-Plant Maintenance Icon on laptop. | H27: SANPC | I27: User Support | J27: Low | K27: Completed
A28: 25 | B28: April | C28: Lindiwe | D28: IT | E28: Emails | F28: BPM - Discard Reqs/POs | G28: Discarding all the Reqs Or POs as per the user's Request. | H28: SANPC | I28: User Support | J28: Low | K28: Completed
A29: 26 | B29: April | C29: Lindiwe | D29: IT | E29: Emails | F29: BPM - Grant Access | G29: Granting Access to BPM for Wayne, Comfort Bunting and Azarias. | H29: SANPC | I29: Incident/Bug Fix | J29: Low | K29: Completed
A30: 27 | B30: April | C30: Lindiwe | D30: IT | E30: Emails | F30: Signing Hub - Grant Access | G30: Granting Access to Signing hub for Wayne, Comfort Bunting and Azarias. | H30: SANPC | I30: Incident/Bug Fix | J30: Low | K30: Completed
A31: 28 | B31: May | C31: T A Willems | D31: IT | F31: ISS Upgrade - QAS Server Testing | G31: Encountered issues relating to TempDB and server connectivity. Resolved with assistance from Infrastructure Team. | H31: PetroSA | I31: Project | J31: Medium | K31: Completed
A32: 29 | B32: May | C32: T A Willems | D32: IT | E32: Problem:145411 | F32: IIS Tampering - EDI Application Recovery | G32: Investigated IIS Tampering which resulted in EDI Business Application being unavailable for more than 24 hours. Resolved and provided input to Incident Report. | H32: PetroSA | I32: Incident/Bug Fix | J32: High | K32: Completed
A33: 30 | B33: May | C33: T A Willems | D33: SAP HR | E33: CRQ: 77012428 | F33: Compensation Statement - Alternate Solution | G33: Developed, tested with End Users and released. Deployed via emergency Change to allow SAP Team more time to investigate long term solution. | H33: PetroSA | I33: Project | J33: High | K33: Completed
A34: 31 | B34: May | C34: T A Willems | D34: IT | F34: BBEE ESD Stakeholder Database Solution | G34: Initial session conducted with Business Users to understand requirements. Further deliberation required to determine direction. | H34: PetroSA/SANPC | I34: User Support | J34: Low | K34: Pending
A35: 32 | B35: May | C35: T A Willems | D35: IT | E35: 52710601 | F35: Procurement Email Tender Mailbox Replacement | G35: Requirement complete, planning complete, currently in development. Ongoing feedback sessions with Business Users. Planned finalisation Mid-June. | H35: PetroSA/SANPC | I35: Project | J35: Medium | K35: In Progress
A36: 33 | B36: May | C36: T A Willems | D36: IT | F36: ISS Upgrade - Procurement Public Website Update | G36: Development complete, awaiting time from Project Team to confirm SQL Databases/Tables/Views before finalising and sending to CCB for Go Live. | H36: PetroSA | I36: Project | J36: Medium | K36: In Progress
A37: 34 | B37: May | C37: T A Willems | D37: IT | F37: ISS Production - SQL 2022 Cluster Build | G37: Specifications agreed with Infrastructure, Project Team and Vendor. SQL Server 2022 Cluster build started. To be finalised next week. | H37: PetroSA | I37: Project | J37: Medium | K37: In Progress
A38: 35 | B38: May | C38: T A Willems | D38: IT | F38: AG Audit Ad-Hoc Support | G38: Ongoing ad-hoc requests for AG Audit queries for Security and Business Applications Team. | H38: PetroSA | I38: User Support | J38: Low | K38: In Progress
A39: 36 | B39: May | C39: T A Willems | D39: IT | F39: Customer Online Application Relaunch | G39: Requirements sent to Business Users. Redesigned two business applications based on End User feedback. Currently in development. Next session 3 June. | H39: PetroSA | I39: Project | J39: Medium | K39: In Progress
A40: 37 | B40: May | C40: T A Willems | D40: IT | E40: Problem: 133172 | F40: ESS Problem Investigation | G40: Issues point to Meraki implemented during SD-WAN. Next step: get assistance from Infrastructure Team and MTN. Issue isolated to remote site access Web Applications in Parow. | H40: PetroSA | I40: Project | J40: Low | K40: In Progress
A41: 38 | B41: May | C41: T A Willems | D41: IT | F41: Mentoring: Phase 1 | G41: Drafted and discussed plan with Mentee and shared with Line Manager. | H41: SANPC | I41: Mentoring | J41: Low | K41: In Progress
A42: 39 | B42: May | C42: T A Willems | D42: IT | F42: Apply Screensavers for the Month | G42: 3 Screensavers applied for the month. | H42: PetroSA | I42: Other | J42: Low | K42: Completed
A43: 40 | B43: May | C43: T A Willems | D43: IT | E43: 74568700 | F43: SharePoint Well Data Site Investigation | G43: Investigated claimed disappearance of folders. Created Stream Search Views for NVU Team. Resolved issues with Python programs created by NVU Team. | H43: PetroSA | I43: Project | J43: Low | K43: In Progress
A44: 41 | B44: May | C44: Mphatheleni Matidze | D44: Business Application | E44: 78078099 | F44: Restore CEF Website | G44: Service was temporarily down due to storage limit reached. | H44: Legacy/CEF | I44: Other | J44: High | K44: Completed
A45: 42 | B45: May | C45: Mphatheleni Matidze | D45: Business Application | E45: 77168702 | F45: CSI - Web Pages and Contact Form Creation | G45: Create a CSI overview, Contact, Services Pages. | H45: SANPC | I45: Project | J45: Low | K45: Completed
A46: 43 | B46: May | C46: Mphatheleni Matidze | D46: Business Application | E46: 75627621 | F46: Configure/Develop Document Management System | G46: Configure/Develop Document Management System with Reviewers Workflow Using React, SharePoint and Power Automate. | H46: SANPC | I46: Project | J46: Medium | K46: In Progress
A47: 44 | B47: May | C47: Mphatheleni Matidze | D47: Business Application | E47: 77148063 | F47: Procurement Shared Drive | G47: Create a SharePoint Drive for PetroSA and SANPC to collaborate and share resources. | H47: SANPC | I47: Project | J47: Low | K47: Completed
A48: 45 | B48: May | C48: Mphatheleni Matidze | D48: Business Application | E48: 78079869 | F48: Risk Management System | G48: Assist in development and testing of the Enterprise Risk Management System. | H48: SANPC | I48: Project | J48: Medium | K48: In Progress
A49: 46 | B49: May | C49: Mphatheleni Matidze | D49: Business Application | E49: 78080759 | F49: Update and Redeploy CEF Internal Mobile App | G49: The CEF Mobile App required significant updates to accommodate new functional requirements, security enhancements, and updated technology libraries. | H49: Legacy/CEF | I49: Project | J49: Low | K49: In Progress
A50: 47 | B50: May | C50: Mphatheleni Matidze | D50: Business Application | F50: SANPC Letterhead Update on Intranet | G50: Updated the SANPC letterhead on the Intranet. | H50: SANPC | I50: Admin/Config | J50: Low | K50: Completed
A51: 48 | B51: May | C51: Shennaz | D51: SAP SD | F51: Pricing Condition Fix | G51: Implemented and tested pricing access sequence changes to resolve incorrect pricing determination. | H51: PetroSA | I51: Project | J51: Low | K51: Completed
A52: 49 | B52: May | C52: Shennaz | D52: SAP MM | F52: Contract Expiry Enhancement Analysis | G52: Continued analysis of expired contract processing and SES creation behaviour. Coordinated with ABAP and business teams. | H52: PetroSA | I52: Reporting | J52: Low | K52: In Progress
A53: 50 | B53: May | C53: Shennaz | D53: SAP FI | F53: Ghana Company Code Configuration | G53: Prepared COA upload structure and reviewed configuration readiness for new company code. | H53: PetroSA Ghana | I53: Admin/Config | J53: Low | K53: In Progress
A54: 51 | B54: May | C54: Shennaz | D54: SAP MM | F54: STO / Workflow Notifications | G54: Investigated notification issues impacting STO and PO related workflows. | H54: PetroSA | I54: Incident/Bug Fix | J54: Low | K54: Completed
A55: 52 | B55: May | C55: Shennaz | D55: SAP FI | F55: Foreign Currency Vendor Clearing | G55: Analysed and supported vendor clearing and reconciliation requirements. | H55: PetroSA | I55: User Support | J55: Low | K55: Completed
A56: 53 | B56: May | C56: Shennaz | D56: SAP PS | F56: Project Commitments Analysis | G56: Investigated PR/PO commitment reporting and project system behaviour. | H56: PetroSA | I56: Project | J56: Medium | K56: Completed
A57: 54 | B57: May | C57: Shennaz | D57: SAP FI/CO | F57: Reporting & Queries | G57: Developed and analysed SAP queries and reports for finance and procurement users. | H57: PetroSA | I57: Project | J57: Medium | K57: In Progress
A58: 55 | B58: May | C58: Shennaz | D58: SAP Support | F58: General SAP Support | G58: Provided incident resolution, user support, testing, documentation and change management activities. | H58: PetroSA/SANPC | I58: Incident/Bug Fix | J58: Low | K58: Completed
A59: 56 | B59: May | C59: Nyameka | D59: HR/Payroll | E59: 69585655 | F59: October 2025 Payslip Discrepancy | G59: The SARS payment reflected in the October 2025 payslips is not aligned with Sage records for SANPC. | H59: SANPC | I59: Admin/Config | J59: Low | K59: Completed
A60: 57 | B60: May | C60: Nyameka | D60: HR/Payroll | E60: 76920689 | F60: Shift Roster Configuration on Sage (Saldanha) | G60: Enablement of the shift roster functionality for the Saldanha site on Sage. | H60: SANPC | I60: Admin/Config | J60: Low | K60: In Progress
A61: 58 | B61: May | C61: Nyameka | D61: HR/Payroll | E61: 76921191 | F61: Shift Roster Leave Miscalculation | G61: Shift Roster Leave Miscalculating leave days on Sage. | H61: SANPC | I61: Admin/Config | J61: Low | K61: In Progress
A62: 59 | B62: May | C62: Nyameka | D62: HR/Payroll | E62: 77901568 | F62: COID Earnings Setup | G62: When processing a COID report for Dept of Labour, the report only processes employees' earnings for three months not the full year. | H62: SANPC | I62: Admin/Config | J62: Low | K62: In Progress
A63: 60 | B63: May | C63: Nyameka | D63: HR/Payroll | E63: 76920962 | F63: SARS Submission Support | G63: Assist with SARS Recon. | H63: SANPC | I63: User Support | J63: Low | K63: Completed
A64: 61 | B64: May | C64: Nyameka | D64: HR/Payroll | E64: 69585655 | F64: Payslips - October 2025 (SARS) | G64: Incorrect for SFF due to SARS Bi-Annual. SARS Payment is not aligned to Sage for SANPC. | H64: SANPC | I64: Admin/Config | J64: Low | K64: Completed
A65: 62 | B65: May | C65: Nyameka | D65: HR/Payroll | E65: 69585765 | F65: July Backpay vs Backpay Overtime | G65: July Backpay Line to be aligned and removed from Overtime in August 2025 payroll. | H65: SANPC | I65: Admin/Config | J65: Low | K65: Completed
A66: 63 | B66: May | C66: Nyameka | D66: HR/Payroll | E66: 69585703 | F66: EMP 201 Payments Sep to Nov | G66: Payment does not reconcile due to item on Line 5. | H66: SANPC | I66: Admin/Config | J66: Low | K66: Completed
A67: 64 | B67: May | C67: Nyameka | D67: IT | E67: 77459225 | F67: IMS Analytical Report Access | G67: Quality department cannot access the IMS Analytical reports via both LAN and VPN. | H67: PetroSA | I67: Incident/Bug Fix | J67: Low | K67: Completed
A68: 65 | B68: May | C68: Nyameka | D68: IT | E68: 77226834 | F68: IMS Reports Issue | G68: IMS tool is not pulling out the analytical reports properly. Incident numbers appearing under title. | H68: PetroSA | I68: Incident/Bug Fix | J68: Low | K68: In Progress
A69: 66 | B69: May | C69: Nyameka | D69: IT | E69: 76797458 | F69: Cannot Connect to SAP (Wi-Fi) | G69: User unable to connect to SAP via Wi-Fi intermittently. | H69: PetroSA | I69: User Support | J69: Low | K69: Completed
A70: 67 | B70: May | C70: Nyameka | D70: IT | E70: 77626961 | F70: Struggle to Access IMS on SAP | G70: Path to IMS does not open. Stops at launch NWBC. | H70: PetroSA | I70: Project | J70: High | K70: In Progress
... A72: 69 | B72: May | C72: Nyameka | D72: IT | E72: 77464517 | F72: SAP Login Error (Role/Auth) | G72: Can log into SAP but experiencing errors. | H72: PetroSA | I72: Incident/Bug Fix | J72: Low | K72: In Progress
A73: 70 | B73: May | C73: Nyameka | D73: SAP HR | F73: Termination of SANPC Employees from PetroSA Structure | G73: Termination of SANPC Employees from PetroSA Structure. | H73: PetroSA | I73: Other | J73: Low | K73: In Progress
A74: 71 | B74: May | C74: Nyameka | D74: SAP HR | F74: PetroSA PayScale Update | G74: PetroSA PayScale Update. | H74: PetroSA | I74: Admin/Config | J74: Low | K74: In Progress
A75: 72 | B75: May | C75: Nyameka | D75: SAP HR | F75: PetroSA CEPPAWU Premium Update | G75: PetroSA CEPPAWU Premium Update. | H75: PetroSA | I75: Admin/Config | J75: Low | K75: In Progress
A76: 73 | B76: May | C76: Nyameka | D76: SAP HR | F76: FA Platform Shift Roster | G76: FA Platform Shift roster configuration. | H76: PetroSA | I76: Admin/Config | J76: Low | K76: Completed
A77: 74 | B77: May | C77: Lindiwe | D77: IT | E77: 77317642 | F77: Signing Hub | G77: Signing hub access. | H77: SANPC | I77: Incident/Bug Fix | J77: Low | K77: Completed
A78: 75 | B78: May | C78: Lindiwe | D78: IT | E78: 76861404 | F78: BPM - Password Resets | G78: Resetting all BPM/ACCPAC passwords for the users that are using the system. | H78: SANPC | I78: User Support | J78: Low | K78: Completed
A79: 76 | B79: May | C79: Lindiwe | D79: IT | E79: Emails | F79: BPM - Business Connect Loading | G79: Loading Business connect, MPLS, Network points, Sage Support PO GRV. | H79: SANPC | I79: User Support | J79: Low | K79: Completed
A80: 77 | B80: May | C80: Lindiwe | D80: Finance | E80: Emails | F80: BPM - RCP Investigation | G80: Check where the RCPs are stuck. | H80: SANPC/SFF | I80: Incident/Bug Fix | J80: Low | K80: Completed
A81: 78 | B81: May | C81: Lindiwe | D81: IT | E81: Emails | F81: BPM - Req Allocation | G81: Allocating the Reqs to correct approvers. | H81: SANPC | I81: User Support | J81: Low | K81: Completed
A82: 79 | B82: May | C82: Lindiwe | D82: IT | E82: Emails | F82: BPM - Transaction Re-allocation | G82: Re-allocate transactions to Sechaba for approval. | H82: SANPC | I82: User Support | J82: Low | K82: Completed
A83: 80 | B83: May | C83: Lindiwe | D83: IT | E83: Emails | F83: BPM - Scope of Work Loading | G83: Loading Scope of work for UPS, VMware licenses and Dell laptop Charges. | H83: SANPC | I83: User Support | J83: Low | K83: Completed
A84: 81 | B84: May | C84: Lindiwe | D84: IT | E84: 77314897 | F84: QBCON Installation | G84: Installation of QBCON-Plant Maintenance Icon on laptop. | H84: SANPC | I84: User Support | J84: Low | K84: Completed
A85: 82 | B85: May | C85: Lindiwe | D85: IT | E85: Emails | F85: BPM - Discard Reqs/POs | G85: Discarding all the Reqs Or POs as per the user's Request. | H85: SANPC | I85: User Support | J85: Low | K85: Completed
A86: 83 | B86: May | C86: Lindiwe | D86: IT | E86: Emails | F86: BPM - Grant Access | G86: Granting Access to BPM for Wayne, Comfort Bunting and Azarias. | H86: SANPC | I86: Incident/Bug Fix | J86: Low | K86: Completed
A87: 84 | B87: May | C87: Lindiwe | D87: IT | E87: Emails | F87: Signing Hub - Grant Access | G87: Granting Access to Signing hub for Wayne, Comfort Bunting and Azarias. | H87: SANPC | I87: Incident/Bug Fix | J87: Low | K87: Completed
A88: =IF(C88<>"",COUNTA($C$4:C88),"")
A89: =IF(C89<>"",COUNTA($C$4:C89),"")
A90: =IF(C90<>"",COUNTA($C$4:C90),"")
A91: =IF(C91<>"",COUNTA($C$4:C91),"")
A92: =IF(C92<>"",COUNTA($C$4:C92),"")
A93: =IF(C93<>"",COUNTA($C$4:C93),"")
A94: =IF(C94<>"",COUNTA($C$4:C94),"")
A95: =IF(C95<>"",COUNTA($C$4:C95),"")
A96: =IF(C96<>"",COUNTA($C$4:C96),"")
A97: =IF(C97<>"",COUNTA($C$4:C97),"")
A98: =IF(C98<>"",COUNTA($C$4:C98),"")
A99: =IF(C99<>"",COUNTA($C$4:C99),"")
... A103: =IF(C103<>"",COUNTA($C$4:C103),"")

Sheet Summary Dashboard
A1: BA Team – Monthly Summary Dashboard
A2: 📊 All figures update automatically when the Monthly Activity Log is populated. Use the Month filter in B4 to view a specific month.
A4: Filter: Month | B4: All
A6: Total Activities | C6: Completed | E6: In Progress | G6: Pending | I6: % Completed | K6: Active Members
A7: =IF($B$4="All",COUNTIF('Monthly Activity Log'!C$4:C$200,"<>"),COUNTIFS('Monthly Activity Log'!B$4:B$200,$B$4,'Monthly Activity Log'!C$4:C$200,"<>")) | C7: =IF($B$4="All",COUNTIF('Monthly Activity Log'!K$4:K$200,"Completed"),COUNTIFS('Monthly Activity Log'!B$4:B$200,$B$4,'Monthly Activity Log'!K$4:K$200,"Completed")) | E7: =IF($B$4="All",COUNTIF('Monthly Activity Log'!K$4:K$200,"In Progress"),COUNTIFS('Monthly Activity Log'!B$4:B$200,$B$4,'Monthly Activity Log'!K$4:K$200,"In Progress")) | G7: =IF($B$4="All",COUNTIF('Monthly Activity Log'!K$4:K$200,"Pending"),COUNTIFS('Monthly Activity Log'!B$4:B$200,$B$4,'Monthly Activity Log'!K$4:K$200,"Pending")) | I7: =IFERROR(C7/A7,0) | K7: =IF(IF($B$4="All",COUNTIF('Monthly Activity Log'!C$4:C$200,"Shennaz"),COUNTIFS('Monthly Activity Log'!B$4:B$200,$B$4,'Monthly Activity Log'!C$4:C$200,"Shennaz"))>0,1,0)+IF(IF($B$4="All",COUNTIF('Monthly Activity Log'!C$4:C$200,"Nyameka"),COUNTIFS('Monthly Activity Log'!B$4:B$200,$B$4,'Monthly Activity Log'!C$4:C$200,"Nyameka"))>0,1,0)+IF(IF($B$4="All",COUNTIF('Monthly Activity Log'!C$4:C$200,"Lindiwe"),COUNTIFS('Monthly Activity Log'!B$4:B$200,$B$4,'Monthly Activity Log'!C$4:C$200,"Lindiwe"))>0,1,0)+IF(IF($B$4="All",COUNTIF('Monthly Activity Log'!C$4:C$200,"T A Willems"),COUNTIFS('Monthly Activity Log'!B$4:B$200,$B$4,'Monthly Activity Log'!C$4:C$200,"T A Willems"))>0,1,0)+IF(IF($B$4="All",COUNTIF('Monthly Activity Log'!C$4:C$200,"Mphatheleni Matidze"),COUNTIFS('Monthly Activity Log'!B$4:B$200,$B$4,'Monthly Activity Log'!C$4:C$200,"Mphatheleni Matidze"))>0,1,0)
A10: ACTIVITIES PER TEAM MEMBER
A11: Team Member | B11: Total | C11: Completed | D11: In Progress | E11: Pending | F11: % Done
A12: Shennaz | B12: =IF($B$4="All",COUNTIF('Monthly Activity Log'!C$4:C$200,"Shennaz"),COUNTIFS('Monthly Activity Log'!B$4:B$200,$B$4,'Monthly Activity Log'!C$4:C$200,"Shennaz")) | C12: =IF($B$4="All",COUNTIFS('Monthly Activity Log'!C$4:C$200,"Shennaz",'Monthly Activity Log'!K$4:K$200,"Completed"),COUNTIFS('Monthly Activity Log'!B$4:B$200,$B$4,'Monthly Activity Log'!C$4:C$200,"Shennaz",'Monthly Activity Log'!K$4:K$200,"Completed")) | D12: =IF($B$4="All",COUNTIFS('Monthly Activity Log'!C$4:C$200,"Shennaz",'Monthly Activity Log'!K$4:K$200,"In Progress"),COUNTIFS('Monthly Activity Log'!B$4:B$200,$B$4,'Monthly Activity Log'!C$4:C$200,"Shennaz",'Monthly Activity Log'!K$4:K$200,"In Progress")) | E12: =IF($B$4="All",COUNTIFS('Monthly Activity Log'!C$4:C$200,"Shennaz",'Monthly Activity Log'!K$4:K$200,"Pending"),COUNTIFS('Monthly Activity Log'!B$4:B$200,$B$4,'Monthly Activity Log'!C$4:C$200,"Shennaz",'Monthly Activity Log'!K$4:K$200,"Pending")) | F12: =IFERROR(C12/B12,0)
A13: Nyameka | B13: =IF($B$4="All",COUNTIF('Monthly Activity Log'!C$4:C$200,"Nyameka"),COUNTIFS('Monthly Activity Log'!B$4:B$200,$B$4,'Monthly Activity Log'!C$4:C$200,"Nyameka")) | C13: =IF($B$4="All",COUNTIFS('Monthly Activity Log'!C$4:C$200,"Nyameka",'Monthly Activity Log'!K$4:K$200,"Completed"),COUNTIFS('Monthly Activity Log'!B$4:B$200,$B$4,'Monthly Activity Log'!C$4:C$200,"Nyameka",'Monthly Activity Log'!K$4:K$200,"Completed")) | D13: =IF($B$4="All",COUNTIFS('Monthly Activity Log'!C$4:C$200,"Nyameka",'Monthly Activity Log'!K$4:K$200,"In Progress"),COUNTIFS('Monthly Activity Log'!B$4:B$200,$B$4,'Monthly Activity Log'!C$4:C$200,"Nyameka",'Monthly Activity Log'!K$4:K$200,"In Progress")) | E13: =IF($B$4="All",COUNTIFS('Monthly Activity Log'!C$4:C$200,"Nyameka",'Monthly Activity Log'!K$4:K$200,"Pending"),COUNTIFS('Monthly Activity Log'!B$4:B$200,$B$4,'Monthly Activity Log'!C$4:C$200,"Nyameka",'Monthly Activity Log'!K$4:K$200,"Pending")) | F13: =IFERROR(C13/B13,0)
A14: Lindiwe | B14: =IF($B$4="All",COUNTIF('Monthly Activity Log'!C$4:C$200,"Lindiwe"),COUNTIFS('Monthly Activity Log'!B$4:B$200,$B$4,'Monthly Activity Log'!C$4:C$200,"Lindiwe")) | C14: =IF($B$4="All",COUNTIFS('Monthly Activity Log'!C$4:C$200,"Lindiwe",'Monthly Activity Log'!K$4:K$200,"Completed"),COUNTIFS('Monthly Activity Log'!B$4:B$200,$B$4,'Monthly Activity Log'!C$4:C$200,"Lindiwe",'Monthly Activity Log'!K$4:K$200,"Completed")) | D14: =IF($B$4="All",COUNTIFS('Monthly Activity Log'!C$4:C$200,"Lindiwe",'Monthly Activity Log'!K$4:K$200,"In Progress"),COUNTIFS('Monthly Activity Log'!B$4:B$200,$B$4,'Monthly Activity Log'!C$4:C$200,"Lindiwe",'Monthly Activity Log'!K$4:K$200,"In Progress")) | E14: =IF($B$4="All",COUNTIFS('Monthly Activity Log'!C$4:C$200,"Lindiwe",'Monthly Activity Log'!K$4:K$200,"Pending"),COUNTIFS('Monthly Activity Log'!B$4:B$200,$B$4,'Monthly Activity Log'!C$4:C$200,"Lindiwe",'Monthly Activity Log'!K$4:K$200,"Pending")) | F14: =IFERROR(C14/B14,0)
A15: T A Willems | B15: =IF($B$4="All",COUNTIF('Monthly Activity Log'!C$4:C$200,"T A Willems"),COUNTIFS('Monthly Activity Log'!B$4:B$200,$B$4,'Monthly Activity Log'!C$4:C$200,"T A Willems")) | C15: =IF($B$4="All",COUNTIFS('Monthly Activity Log'!C$4:C$200,"T A Willems",'Monthly Activity Log'!K$4:K$200,"Completed"),COUNTIFS('Monthly Activity Log'!B$4:B$200,$B$4,'Monthly Activity Log'!C$4:C$200,"T A Willems",'Monthly Activity Log'!K$4:K$200,"Completed")) | D15: =IF($B$4="All",COUNTIFS('Monthly Activity Log'!C$4:C$200,"T A Willems",'Monthly Activity Log'!K$4:K$200,"In Progress"),COUNTIFS('Monthly Activity Log'!B$4:B$200,$B$4,'Monthly Activity Log'!C$4:C$200,"T A Willems",'Monthly Activity Log'!K$4:K$200,"In Progress")) | E15: =IF($B$4="All",COUNTIFS('Monthly Activity Log'!C$4:C$200,"T A Willems",'Monthly Activity Log'!K$4:K$200,"Pending"),COUNTIFS('Monthly Activity Log'!B$4:B$200,$B$4,'Monthly Activity Log'!C$4:C$200,"T A Willems",'Monthly Activity Log'!K$4:K$200,"Pending")) | F15: =IFERROR(C15/B15,0)
A16: Mphatheleni Matidze | B16: =IF($B$4="All",COUNTIF('Monthly Activity Log'!C$4:C$200,"Mphatheleni Matidze"),COUNTIFS('Monthly Activity Log'!B$4:B$200,$B$4,'Monthly Activity Log'!C$4:C$200,"Mphatheleni Matidze")) | C16: =IF($B$4="All",COUNTIFS('Monthly Activity Log'!C$4:C$200,"Mphatheleni Matidze",'Monthly Activity Log'!K$4:K$200,"Completed"),COUNTIFS('Monthly Activity Log'!B$4:B$200,$B$4,'Monthly Activity Log'!C$4:C$200,"Mphatheleni Matidze",'Monthly Activity Log'!K$4:K$200,"Completed")) | D16: =IF($B$4="All",COUNTIFS('Monthly Activity Log'!C$4:C$200,"Mphatheleni Matidze",'Monthly Activity Log'!K$4:K$200,"In Progress"),COUNTIFS('Monthly Activity Log'!B$4:B$200,$B$4,'Monthly Activity Log'!C$4:C$200,"Mphatheleni Matidze",'Monthly Activity Log'!K$4:K$200,"In Progress")) | E16: =IF($B$4="All",COUNTIFS('Monthly Activity Log'!C$4:C$200,"Mphatheleni Matidze",'Monthly Activity Log'!K$4:K$200,"Pending"),COUNTIFS('Monthly Activity Log'!B$4:B$200,$B$4,'Monthly Activity Log'!C$4:C$200,"Mphatheleni Matidze",'Monthly Activity Log'!K$4:K$200,"Pending")) | F16: =IFERROR(C16/B16,0)
A17: TOTAL | B17: =SUM(B12:B16) | C17: =SUM(C12:C16) | D17: =SUM(D12:D16) | E17: =SUM(E12:E16) | F17: =IFERROR(C17/B17,0)
A19: ACTIVITIES BY CATEGORY | H19: ACTIVITIES BY CLIENT
A20: Category | B20: Count | C20: % of Total | H20: Client | I20: Count | J20: % of Total
A21: Project | B21: =IF($B$4="All",COUNTIF('Monthly Activity Log'!I$4:I$200,"Project"),COUNTIFS('Monthly Activity Log'!B$4:B$200,$B$4,'Monthly Activity Log'!I$4:I$200,"Project")) | C21: =IFERROR(B21/A7,0) | H21: SANPC | I21: =IF($B$4="All",COUNTIF('Monthly Activity Log'!H$4:H$200,"SANPC"),COUNTIFS('Monthly Activity Log'!B$4:B$200,$B$4,'Monthly Activity Log'!H$4:H$200,"SANPC")) | J21: =IFERROR(I21/A7,0)
A22: Incident/Bug Fix | B22: =IF($B$4="All",COUNTIF('Monthly Activity Log'!I$4:I$200,"Incident/Bug Fix"),COUNTIFS('Monthly Activity Log'!B$4:B$200,$B$4,'Monthly Activity Log'!I$4:I$200,"Incident/Bug Fix")) | C22: =IFERROR(B22/A7,0) | H22: PetroSA | I22: =IF($B$4="All",COUNTIF('Monthly Activity Log'!H$4:H$200,"PetroSA"),COUNTIFS('Monthly Activity Log'!B$4:B$200,$B$4,'Monthly Activity Log'!H$4:H$200,"PetroSA")) | J22: =IFERROR(I22/A7,0)
A23: Change Request | B23: =IF($B$4="All",COUNTIF('Monthly Activity Log'!I$4:I$200,"Change Request"),COUNTIFS('Monthly Activity Log'!B$4:B$200,$B$4,'Monthly Activity Log'!I$4:I$200,"Change Request")) | C23: =IFERROR(B23/A7,0) | H23: PetroSA Ghana | I23: =IF($B$4="All",COUNTIF('Monthly Activity Log'!H$4:H$200,"PetroSA Ghana"),COUNTIFS('Monthly Activity Log'!B$4:B$200,$B$4,'Monthly Activity Log'!H$4:H$200,"PetroSA Ghana")) | J23: =IFERROR(I23/A7,0)
A24: User Support | B24: =IF($B$4="All",COUNTIF('Monthly Activity Log'!I$4:I$200,"User Support"),COUNTIFS('Monthly Activity Log'!B$4:B$200,$B$4,'Monthly Activity Log'!I$4:I$200,"User Support")) | C24: =IFERROR(B24/A7,0) | H24: Legacy/CEF | I24: =IF($B$4="All",COUNTIF('Monthly Activity Log'!H$4:H$200,"Legacy/CEF"),COUNTIFS('Monthly Activity Log'!B$4:B$200,$B$4,'Monthly Activity Log'!H$4:H$200,"Legacy/CEF")) | J24: =IFERROR(I24/A7,0)
A25: Admin/Config | B25: =IF($B$4="All",COUNTIF('Monthly Activity Log'!I$4:I$200,"Admin/Config"),COUNTIFS('Monthly Activity Log'!B$4:B$200,$B$4,'Monthly Activity Log'!I$4:I$200,"Admin/Config")) | C25: =IFERROR(B25/A7,0) | H25: SANPC/SFF | I25: =IF($B$4="All",COUNTIF('Monthly Activity Log'!H$4:H$200,"SANPC/SFF"),COUNTIFS('Monthly Activity Log'!B$4:B$200,$B$4,'Monthly Activity Log'!H$4:H$200,"SANPC/SFF")) | J25: =IFERROR(I25/A7,0)
A26: Reporting | B26: =IF($B$4="All",COUNTIF('Monthly Activity Log'!I$4:I$200,"Reporting"),COUNTIFS('Monthly Activity Log'!B$4:B$200,$B$4,'Monthly Activity Log'!I$4:I$200,"Reporting")) | C26: =IFERROR(B26/A7,0) | H26: PetroSA/SANPC | I26: =IF($B$4="All",COUNTIF('Monthly Activity Log'!H$4:H$200,"PetroSA/SANPC"),COUNTIFS('Monthly Activity Log'!B$4:B$200,$B$4,'Monthly Activity Log'!H$4:H$200,"PetroSA/SANPC")) | J26: =IFERROR(I26/A7,0)
A27: Mentoring | B27: =IF($B$4="All",COUNTIF('Monthly Activity Log'!I$4:I$200,"Mentoring"),COUNTIFS('Monthly Activity Log'!B$4:B$200,$B$4,'Monthly Activity Log'!I$4:I$200,"Mentoring")) | C27: =IFERROR(B27/A7,0) | H27: Other | I27: =IF($B$4="All",COUNTIF('Monthly Activity Log'!H$4:H$200,"Other"),COUNTIFS('Monthly Activity Log'!B$4:B$200,$B$4,'Monthly Activity Log'!H$4:H$200,"Other")) | J27: =IFERROR(I27/A7,0)
A28: Other | B28: =IF($B$4="All",COUNTIF('Monthly Activity Log'!I$4:I$200,"Other"),COUNTIFS('Monthly Activity Log'!B$4:B$200,$B$4,'Monthly Activity Log'!I$4:I$200,"Other")) | C28: =IFERROR(B28/A7,0)

Sheet Team Member View
A1: BA Team – Team Member Workload View
A2: 👤 Select a team member in B3 to filter. Select 'All' to see the full team. Updates automatically from the Monthly Activity Log.
A3: Team Member: | B3: All | D3: Month: | E3: All
A4: # | B4: Month | C4: Team Member | D4: Dept/Module | E4: Ticket No. | F4: Activity Name | G4: Description | H4: Client | I4: Category | J4: Priority | K4: Status
A5: =IF(AND(('Monthly Activity Log'!C4<>""),(OR($B$3="All",'Monthly Activity Log'!C4=$B$3)),(OR($E$3="All",'Monthly Activity Log'!B4=$E$3))),ROW()-4,"") | B5: =IF(AND(('Monthly Activity Log'!C4<>""),(OR($B$3="All",'Monthly Activity Log'!C4=$B$3)),(OR($E$3="All",'Monthly Activity Log'!B4=$E$3))),'Monthly Activity Log'!B4,"") | C5: =IF(AND(('Monthly Activity Log'!C4<>""),(OR($B$3="All",'Monthly Activity Log'!C4=$B$3)),(OR($E$3="All",'Monthly Activity Log'!B4=$E$3))),'Monthly Activity Log'!C4,"") | D5: =IF(AND(('Monthly Activity Log'!C4<>""),(OR($B$3="All",'Monthly Activity Log'!C4=$B$3)),(OR($E$3="All",'Monthly Activity Log'!B4=$E$3))),'Monthly Activity Log'!D4,"") | E5: =IF(AND(('Monthly Activity Log'!C4<>""),(OR($B$3="All",'Monthly Activity Log'!C4=$B$3)),(OR($E$3="All",'Monthly Activity Log'!B4=$E$3))),'Monthly Activity Log'!E4,"") | F5: =IF(AND(('Monthly Activity Log'!C4<>""),(OR($B$3="All",'Monthly Activity Log'!C4=$B$3)),(OR($E$3="All",'Monthly Activity Log'!B4=$E$3))),'Monthly Activity Log'!F4,"") | G5: =IF(AND(('Monthly Activity Log'!C4<>""),(OR($B$3="All",'Monthly Activity Log'!C4=$B$3)),(OR($E$3="All",'Monthly Activity Log'!B4=$E$3))),'Monthly Activity Log'!G4,"") | H5: =IF(AND(('Monthly Activity Log'!C4<>""),(OR($B$3="All",'Monthly Activity Log'!C4=$B$3)),(OR($E$3="All",'Monthly Activity Log'!B4=$E$3))),'Monthly Activity Log'!H4,"") | I5: =IF(AND(('Monthly Activity Log'!C4<>""),(OR($B$3="All",'Monthly Activity Log'!C4=$B$3)),(OR($E$3="All",'Monthly Activity Log'!B4=$E$3))),'Monthly Activity Log'!I4,"") | J5: =IF(AND(('Monthly Activity Log'!C4<>""),(OR($B$3="All",'Monthly Activity Log'!C4=$B$3)),(OR($E$3="All",'Monthly Activity Log'!B4=$E$3))),'Monthly Activity Log'!J4,"") | K5: =IF(AND(('Monthly Activity Log'!C4<>""),(OR($B$3="All",'Monthly Activity Log'!C4=$B$3)),(OR($E$3="All",'Monthly Activity Log'!B4=$E$3))),'Monthly Activity Log'!K4,"")
A6: =IF(AND(('Monthly Activity Log'!C5<>""),(OR($B$3="All",'Monthly Activity Log'!C5=$B$3)),(OR($E$3="All",'Monthly Activity Log'!B5=$E$3))),ROW()-4,"") | B6: =IF(AND(('Monthly Activity Log'!C5<>""),(OR($B$3="All",'Monthly Activity Log'!C5=$B$3)),(OR($E$3="All",'Monthly Activity Log'!B5=$E$3))),'Monthly Activity Log'!B5,"") | C6: =IF(AND(('Monthly Activity Log'!C5<>""),(OR($B$3="All",'Monthly Activity Log'!C5=$B$3)),(OR($E$3="All",'Monthly Activity Log'!B5=$E$3))),'Monthly Activity Log'!C5,"") | D6: =IF(AND(('Monthly Activity Log'!C5<>""),(OR($B$3="All",'Monthly Activity Log'!C5=$B$3)),(OR($E$3="All",'Monthly Activity Log'!B5=$E$3))),'Monthly Activity Log'!D5,"") | E6: =IF(AND(('Monthly Activity Log'!C5<>""),(OR($B$3="All",'Monthly Activity Log'!C5=$B$3)),(OR($E$3="All",'Monthly Activity Log'!B5=$E$3))),'Monthly Activity Log'!E5,"") | F6: =IF(AND(('Monthly Activity Log'!C5<>""),(OR($B$3="All",'Monthly Activity Log'!C5=$B$3)),(OR($E$3="All",'Monthly Activity Log'!B5=$E$3))),'Monthly Activity Log'!F5,"") | G6: =IF(AND(('Monthly Activity Log'!C5<>""),(OR($B$3="All",'Monthly Activity Log'!C5=$B$3)),(OR($E$3="All",'Monthly Activity Log'!B5=$E$3))),'Monthly Activity Log'!G5,"") | H6: =IF(AND(('Monthly Activity Log'!C5<>""),(OR($B$3="All",'Monthly Activity Log'!C5=$B$3)),(OR($E$3="All",'Monthly Activity Log'!B5=$E$3))),'Monthly Activity Log'!H5,"") | I6: =IF(AND(('Monthly Activity Log'!C5<>""),(OR($B$3="All",'Monthly Activity Log'!C5=$B$3)),(OR($E$3="All",'Monthly Activity Log'!B5=$E$3))),'Monthly Activity Log'!I5,"") | J6: =IF(AND(('Monthly Activity Log'!C5<>""),(OR($B$3="All",'Monthly Activity Log'!C5=$B$3)),(OR($E$3="All",'Monthly Activity Log'!B5=$E$3))),'Monthly Activity Log'!J5,"") | K6: =IF(AND(('Monthly Activity Log'!C5<>""),(OR($B$3="All",'Monthly Activity Log'!C5=$B$3)),(OR($E$3="All",'Monthly Activity Log'!B5=$E$3))),'Monthly Activity Log'!K5,"")
A7: =IF(AND(('Monthly Activity Log'!C6<>""),(OR($B$3="All",'Monthly Activity Log'!C6=$B$3)),(OR($E$3="All",'Monthly Activity Log'!B6=$E$3))),ROW()-4,"") | B7: =IF(AND(('Monthly Activity Log'!C6<>""),(OR($B$3="All",'Monthly Activity Log'!C6=$B$3)),(OR($E$3="All",'Monthly Activity Log'!B6=$E$3))),'Monthly Activity Log'!B6,"") | C7: =IF(AND(('Monthly Activity Log'!C6<>""),(OR($B$3="All",'Monthly Activity Log'!C6=$B$3)),(OR($E$3="All",'Monthly Activity Log'!B6=$E$3))),'Monthly Activity Log'!C6,"") | D7: =IF(AND(('Monthly Activity Log'!C6<>""),(OR($B$3="All",'Monthly Activity Log'!C6=$B$3)),(OR($E$3="All",'Monthly Activity Log'!B6=$E$3))),'Monthly Activity Log'!D6,"") | E7: =IF(AND(('Monthly Activity Log'!C6<>""),(OR($B$3="All",'Monthly Activity Log'!C6=$B$3)),(OR($E$3="All",'Monthly Activity Log'!B6=$E$3))),'Monthly Activity Log'!E6,"") | F7: =IF(AND(('Monthly Activity Log'!C6<>""),(OR($B$3="All",'Monthly Activity Log'!C6=$B$3)),(OR($E$3="All",'Monthly Activity Log'!B6=$E$3))),'Monthly Activity Log'!F6,"") | G7: =IF(AND(('Monthly Activity Log'!C6<>""),(OR($B$3="All",'Monthly Activity Log'!C6=$B$3)),(OR($E$3="All",'Monthly Activity Log'!B6=$E$3))),'Monthly Activity Log'!G6,"") | H7: =IF(AND(('Monthly Activity Log'!C6<>""),(OR($B$3="All",'Monthly Activity Log'!C6=$B$3)),(OR($E$3="All",'Monthly Activity Log'!B6=$E$3))),'Monthly Activity Log'!H6,"") | I7: =IF(AND(('Monthly Activity Log'!C6<>""),(OR($B$3="All",'Monthly Activity Log'!C6=$B$3)),(OR($E$3="All",'Monthly Activity Log'!B6=$E$3))),'Monthly Activity Log'!I6,"") | J7: =IF(AND(('Monthly Activity Log'!C6<>""),(OR($B$3="All",'Monthly Activity Log'!C6=$B$3)),(OR($E$3="All",'Monthly Activity Log'!B6=$E$3))),'Monthly Activity Log'!J6,"") | K7: =IF(AND(('Monthly Activity Log'!C6<>""),(OR($B$3="All",'Monthly Activity Log'!C6=$B$3)),(OR($E$3="All",'Monthly Activity Log'!B6=$E$3))),'Monthly Activity Log'!K6,"")
A8: =IF(AND(('Monthly Activity Log'!C7<>""),(OR($B$3="All",'Monthly Activity Log'!C7=$B$3)),(OR($E$3="All",'Monthly Activity Log'!B7=$E$3))),ROW()-4,"") | B8: =IF(AND(('Monthly Activity Log'!C7<>""),(OR($B$3="All",'Monthly Activity Log'!C7=$B$3)),(OR($E$3="All",'Monthly Activity Log'!B7=$E$3))),'Monthly Activity Log'!B7,"") | C8: =IF(AND(('Monthly Activity Log'!C7<>""),(OR($B$3="All",'Monthly Activity Log'!C7=$B$3)),(OR($E$3="All",'Monthly Activity Log'!B7=$E$3))),'Monthly Activity Log'!C7,"") | D8: =IF(AND(('Monthly Activity Log'!C7<>""),(OR($B$3="All",'Monthly Activity Log'!C7=$B$3)),(OR($E$3="All",'Monthly Activity Log'!B7=$E$3))),'Monthly Activity Log'!D7,"") | E8: =IF(AND(('Monthly Activity Log'!C7<>""),(OR($B$3="All",'Monthly Activity Log'!C7=$B$3)),(OR($E$3="All",'Monthly Activity Log'!B7=$E$3))),'Monthly Activity Log'!E7,"") | F8: =IF(AND(('Monthly Activity Log'!C7<>""),(OR($B$3="All",'Monthly Activity Log'!C7=$B$3)),(OR($E$3="All",'Monthly Activity Log'!B7=$E$3))),'Monthly Activity Log'!F7,"") | G8: =IF(AND(('Monthly Activity Log'!C7<>""),(OR($B$3="All",'Monthly Activity Log'!C7=$B$3)),(OR($E$3="All",'Monthly Activity Log'!B7=$E$3))),'Monthly Activity Log'!G7,"") | H8: =IF(AND(('Monthly Activity Log'!C7<>""),(OR($B$3="All",'Monthly Activity Log'!C7=$B$3)),(OR($E$3="All",'Monthly Activity Log'!B7=$E$3))),'Monthly Activity Log'!H7,"") | I8: =IF(AND(('Monthly Activity Log'!C7<>""),(OR($B$3="All",'Monthly Activity Log'!C7=$B$3)),(OR($E$3="All",'Monthly Activity Log'!B7=$E$3))),'Monthly Activity Log'!I7,"") | J8: =IF(AND(('Monthly Activity Log'!C7<>""),(OR($B$3="All",'Monthly Activity Log'!C7=$B$3)),(OR($E$3="All",'Monthly Activity Log'!B7=$E$3))),'Monthly Activity Log'!J7,"") | K8: =IF(AND(('Monthly Activity Log'!C7<>""),(OR($B$3="All",'Monthly Activity Log'!C7=$B$3)),(OR($E$3="All",'Monthly Activity Log'!B7=$E$3))),'Monthly Activity Log'!K7,"")
A9: =IF(AND(('Monthly Activity Log'!C8<>""),(OR($B$3="All",'Monthly Activity Log'!C8=$B$3)),(OR($E$3="All",'Monthly Activity Log'!B8=$E$3))),ROW()-4,"") | B9: =IF(AND(('Monthly Activity Log'!C8<>""),(OR($B$3="All",'Monthly Activity Log'!C8=$B$3)),(OR($E$3="All",'Monthly Activity Log'!B8=$E$3))),'Monthly Activity Log'!B8,"") | C9: =IF(AND(('Monthly Activity Log'!C8<>""),(OR($B$3="All",'Monthly Activity Log'!C8=$B$3)),(OR($E$3="All",'Monthly Activity Log'!B8=$E$3))),'Monthly Activity Log'!C8,"") | D9: =IF(AND(('Monthly Activity Log'!C8<>""),(OR($B$3="All",'Monthly Activity Log'!C8=$B$3)),(OR($E$3="All",'Monthly Activity Log'!B8=$E$3))),'Monthly Activity Log'!D8,"") | E9: =IF(AND(('Monthly Activity Log'!C8<>""),(OR($B$3="All",'Monthly Activity Log'!C8=$B$3)),(OR($E$3="All",'Monthly Activity Log'!B8=$E$3))),'Monthly Activity Log'!E8,"") | F9: =IF(AND(('Monthly Activity Log'!C8<>""),(OR($B$3="All",'Monthly Activity Log'!C8=$B$3)),(OR($E$3="All",'Monthly Activity Log'!B8=$E$3))),'Monthly Activity Log'!F8,"") | G9: =IF(AND(('Monthly Activity Log'!C8<>""),(OR($B$3="All",'Monthly Activity Log'!C8=$B$3)),(OR($E$3="All",'Monthly Activity Log'!B8=$E$3))),'Monthly Activity Log'!G8,"") | H9: =IF(AND(('Monthly Activity Log'!C8<>""),(OR($B$3="All",'Monthly Activity Log'!C8=$B$3)),(OR($E$3="All",'Monthly Activity Log'!B8=$E$3))),'Monthly Activity Log'!H8,"") | I9: =IF(AND(('Monthly Activity Log'!C8<>""),(OR($B$3="All",'Monthly Activity Log'!C8=$B$3)),(OR($E$3="All",'Monthly Activity Log'!B8=$E$3))),'Monthly Activity Log'!I8,"") | J9: =IF(AND(('Monthly Activity Log'!C8<>""),(OR($B$3="All",'Monthly Activity Log'!C8=$B$3)),(OR($E$3="All",'Monthly Activity Log'!B8=$E$3))),'Monthly Activity Log'!J8,"") | K9: =IF(AND(('Monthly Activity Log'!C8<>""),(OR($B$3="All",'Monthly Activity Log'!C8=$B$3)),(OR($E$3="All",'Monthly Activity Log'!B8=$E$3))),'Monthly Activity Log'!K8,"")
A10: =IF(AND(('Monthly Activity Log'!C9<>""),(OR($B$3="All",'Monthly Activity Log'!C9=$B$3)),(OR($E$3="All",'Monthly Activity Log'!B9=$E$3))),ROW()-4,"") | B10: =IF(AND(('Monthly Activity Log'!C9<>""),(OR($B$3="All",'Monthly Activity Log'!C9=$B$3)),(OR($E$3="All",'Monthly Activity Log'!B9=$E$3))),'Monthly Activity Log'!B9,"") | C10: =IF(AND(('Monthly Activity Log'!C9<>""),(OR($B$3="All",'Monthly Activity Log'!C9=$B$3)),(OR($E$3="All",'Monthly Activity Log'!B9=$E$3))),'Monthly Activity Log'!C9,"") | D10: =IF(AND(('Monthly Activity Log'!C9<>""),(OR($B$3="All",'Monthly Activity Log'!C9=$B$3)),(OR($E$3="All",'Monthly Activity Log'!B9=$E$3))),'Monthly Activity Log'!D9,"") | E10: =IF(AND(('Monthly Activity Log'!C9<>""),(OR($B$3="All",'Monthly Activity Log'!C9=$B$3)),(OR($E$3="All",'Monthly Activity Log'!B9=$E$3))),'Monthly Activity Log'!E9,"") | F10: =IF(AND(('Monthly Activity Log'!C9<>""),(OR($B$3="All",'Monthly Activity Log'!C9=$B$3)),(OR($E$3="All",'Monthly Activity Log'!B9=$E$3))),'Monthly Activity Log'!F9,"") | G10: =IF(AND(('Monthly Activity Log'!C9<>""),(OR($B$3="All",'Monthly Activity Log'!C9=$B$3)),(OR($E$3="All",'Monthly Activity Log'!B9=$E$3))),'Monthly Activity Log'!G9,"") | H10: =IF(AND(('Monthly Activity Log'!C9<>""),(OR($B$3="All",'Monthly Activity Log'!C9=$B$3)),(OR($E$3="All",'Monthly Activity Log'!B9=$E$3))),'Monthly Activity Log'!H9,"") | I10: =IF(AND(('Monthly Activity Log'!C9<>""),(OR($B$3="All",'Monthly Activity Log'!C9=$B$3)),(OR($E$3="All",'Monthly Activity Log'!B9=$E$3))),'Monthly Activity Log'!I9,"") | J10: =IF(AND(('Monthly Activity Log'!C9<>""),(OR($B$3="All",'Monthly Activity Log'!C9=$B$3)),(OR($E$3="All",'Monthly Activity Log'!B9=$E$3))),'Monthly Activity Log'!J9,"") | K10: =IF(AND(('Monthly Activity Log'!C9<>""),(OR($B$3="All",'Monthly Activity Log'!C9=$B$3)),(OR($E$3="All",'Monthly Activity Log'!B9=$E$3))),'Monthly Activity Log'!K9,"")
A11: =IF(AND(('Monthly Activity Log'!C10<>""),(OR($B$3="All",'Monthly Activity Log'!C10=$B$3)),(OR($E$3="All",'Monthly Activity Log'!B10=$E$3))),ROW()-4,"") | B11: =IF(AND(('Monthly Activity Log'!C10<>""),(OR($B$3="All",'Monthly Activity Log'!C10=$B$3)),(OR($E$3="All",'Monthly Activity Log'!B10=$E$3))),'Monthly Activity Log'!B10,"") | C11: =IF(AND(('Monthly Activity Log'!C10<>""),(OR($B$3="All",'Monthly Activity Log'!C10=$B$3)),(OR($E$3="All",'Monthly Activity Log'!B10=$E$3))),'Monthly Activity Log'!C10,"") | D11: =IF(AND(('Monthly Activity Log'!C10<>""),(OR($B$3="All",'Monthly Activity Log'!C10=$B$3)),(OR($E$3="All",'Monthly Activity Log'!B10=$E$3))),'Monthly Activity Log'!D10,"") | E11: =IF(AND(('Monthly Activity Log'!C10<>""),(OR($B$3="All",'Monthly Activity Log'!C10=$B$3)),(OR($E$3="All",'Monthly Activity Log'!B10=$E$3))),'Monthly Activity Log'!E10,"") | F11: =IF(AND(('Monthly Activity Log'!C10<>""),(OR($B$3="All",'Monthly Activity Log'!C10=$B$3)),(OR($E$3="All",'Monthly Activity Log'!B10=$E$3))),'Monthly Activity Log'!F10,"") | G11: =IF(AND(('Monthly Activity Log'!C10<>""),(OR($B$3="All",'Monthly Activity Log'!C10=$B$3)),(OR($E$3="All",'Monthly Activity Log'!B10=$E$3))),'Monthly Activity Log'!G10,"") | H11: =IF(AND(('Monthly Activity Log'!C10<>""),(OR($B$3="All",'Monthly Activity Log'!C10=$B$3)),(OR($E$3="All",'Monthly Activity Log'!B10=$E$3))),'Monthly Activity Log'!H10,"") | I11: =IF(AND(('Monthly Activity Log'!C10<>""),(OR($B$3="All",'Monthly Activity Log'!C10=$B$3)),(OR($E$3="All",'Monthly Activity Log'!B10=$E$3))),'Monthly Activity Log'!I10,"") | J11: =IF(AND(('Monthly Activity Log'!C10<>""),(OR($B$3="All",'Monthly Activity Log'!C10=$B$3)),(OR($E$3="All",'Monthly Activity Log'!B10=$E$3))),'Monthly Activity Log'!J10,"") | K11: =IF(AND(('Monthly Activity Log'!C10<>""),(OR($B$3="All",'Monthly Activity Log'!C10=$B$3)),(OR($E$3="All",'Monthly Activity Log'!B10=$E$3))),'Monthly Activity Log'!K10,"")
A12: =IF(AND(('Monthly Activity Log'!C11<>""),(OR($B$3="All",'Monthly Activity Log'!C11=$B$3)),(OR($E$3="All",'Monthly Activity Log'!B11=$E$3))),ROW()-4,"") | B12: =IF(AND(('Monthly Activity Log'!C11<>""),(OR($B$3="All",'Monthly Activity Log'!C11=$B$3)),(OR($E$3="All",'Monthly Activity Log'!B11=$E$3))),'Monthly Activity Log'!B11,"") | C12: =IF(AND(('Monthly Activity Log'!C11<>""),(OR($B$3="All",'Monthly Activity Log'!C11=$B$3)),(OR($E$3="All",'Monthly Activity Log'!B11=$E$3))),'Monthly Activity Log'!C11,"") | D12: =IF(AND(('Monthly Activity Log'!C11<>""),(OR($B$3="All",'Monthly Activity Log'!C11=$B$3)),(OR($E$3="All",'Monthly Activity Log'!B11=$E$3))),'Monthly Activity Log'!D11,"") | E12: =IF(AND(('Monthly Activity Log'!C11<>""),(OR($B$3="All",'Monthly Activity Log'!C11=$B$3)),(OR($E$3="All",'Monthly Activity Log'!B11=$E$3))),'Monthly Activity Log'!E11,"") | F12: =IF(AND(('Monthly Activity Log'!C11<>""),(OR($B$3="All",'Monthly Activity Log'!C11=$B$3)),(OR($E$3="All",'Monthly Activity Log'!B11=$E$3))),'Monthly Activity Log'!F11,"") | G12: =IF(AND(('Monthly Activity Log'!C11<>""),(OR($B$3="All",'Monthly Activity Log'!C11=$B$3)),(OR($E$3="All",'Monthly Activity Log'!B11=$E$3))),'Monthly Activity Log'!G11,"") | H12: =IF(AND(('Monthly Activity Log'!C11<>""),(OR($B$3="All",'Monthly Activity Log'!C11=$B$3)),(OR($E$3="All",'Monthly Activity Log'!B11=$E$3))),'Monthly Activity Log'!H11,"") | I12: =IF(AND(('Monthly Activity Log'!C11<>""),(OR($B$3="All",'Monthly Activity Log'!C11=$B$3)),(OR($E$3="All",'Monthly Activity Log'!B11=$E$3))),'Monthly Activity Log'!I11,"") | J12: =IF(AND(('Monthly Activity Log'!C11<>""),(OR($B$3="All",'Monthly Activity Log'!C11=$B$3)),(OR($E$3="All",'Monthly Activity Log'!B11=$E$3))),'Monthly Activity Log'!J11,"") | K12: =IF(AND(('Monthly Activity Log'!C11<>""),(OR($B$3="All",'Monthly Activity Log'!C11=$B$3)),(OR($E$3="All",'Monthly Activity Log'!B11=$E$3))),'Monthly Activity Log'!K11,"")
A13: =IF(AND(('Monthly Activity Log'!C12<>""),(OR($B$3="All",'Monthly Activity Log'!C12=$B$3)),(OR($E$3="All",'Monthly Activity Log'!B12=$E$3))),ROW()-4,"") | B13: =IF(AND(('Monthly Activity Log'!C12<>""),(OR($B$3="All",'Monthly Activity Log'!C12=$B$3)),(OR($E$3="All",'Monthly Activity Log'!B12=$E$3))),'Monthly Activity Log'!B12,"") | C13: =IF(AND(('Monthly Activity Log'!C12<>""),(OR($B$3="All",'Monthly Activity Log'!C12=$B$3)),(OR($E$3="All",'Monthly Activity Log'!B12=$E$3))),'Monthly Activity Log'!C12,"") | D13: =IF(AND(('Monthly Activity Log'!C12<>""),(OR($B$3="All",'Monthly Activity Log'!C12=$B$3)),(OR($E$3="All",'Monthly Activity Log'!B12=$E$3))),'Monthly Activity Log'!D12,"") | E13: =IF(AND(('Monthly Activity Log'!C12<>""),(OR($B$3="All",'Monthly Activity Log'!C12=$B$3)),(OR($E$3="All",'Monthly Activity Log'!B12=$E$3))),'Monthly Activity Log'!E12,"") | F13: =IF(AND(('Monthly Activity Log'!C12<>""),(OR($B$3="All",'Monthly Activity Log'!C12=$B$3)),(OR($E$3="All",'Monthly Activity Log'!B12=$E$3))),'Monthly Activity Log'!F12,"") | G13: =IF(AND(('Monthly Activity Log'!C12<>""),(OR($B$3="All",'Monthly Activity Log'!C12=$B$3)),(OR($E$3="All",'Monthly Activity Log'!B12=$E$3))),'Monthly Activity Log'!G12,"") | H13: =IF(AND(('Monthly Activity Log'!C12<>""),(OR($B$3="All",'Monthly Activity Log'!C12=$B$3)),(OR($E$3="All",'Monthly Activity Log'!B12=$E$3))),'Monthly Activity Log'!H12,"") | I13: =IF(AND(('Monthly Activity Log'!C12<>""),(OR($B$3="All",'Monthly Activity Log'!C12=$B$3)),(OR($E$3="All",'Monthly Activity Log'!B12=$E$3))),'Monthly Activity Log'!I12,"") | J13: =IF(AND(('Monthly Activity Log'!C12<>""),(OR($B$3="All",'Monthly Activity Log'!C12=$B$3)),(OR($E$3="All",'Monthly Activity Log'!B12=$E$3))),'Monthly Activity Log'!J12,"") | K13: =IF(AND(('Monthly Activity Log'!C12<>""),(OR($B$3="All",'Monthly Activity Log'!C12=$B$3)),(OR($E$3="All",'Monthly Activity Log'!B12=$E$3))),'Monthly Activity Log'!K12,"")
A14: =IF(AND(('Monthly Activity Log'!C13<>""),(OR($B$3="All",'Monthly Activity Log'!C13=$B$3)),(OR($E$3="All",'Monthly Activity Log'!B13=$E$3))),ROW()-4,"") | B14: =IF(AND(('Monthly Activity Log'!C13<>""),(OR($B$3="All",'Monthly Activity Log'!C13=$B$3)),(OR($E$3="All",'Monthly Activity Log'!B13=$E$3))),'Monthly Activity Log'!B13,"") | C14: =IF(AND(('Monthly Activity Log'!C13<>""),(OR($B$3="All",'Monthly Activity Log'!C13=$B$3)),(OR($E$3="All",'Monthly Activity Log'!B13=$E$3))),'Monthly Activity Log'!C13,"") | D14: =IF(AND(('Monthly Activity Log'!C13<>""),(OR($B$3="All",'Monthly Activity Log'!C13=$B$3)),(OR($E$3="All",'Monthly Activity Log'!B13=$E$3))),'Monthly Activity Log'!D13,"") | E14: =IF(AND(('Monthly Activity Log'!C13<>""),(OR($B$3="All",'Monthly Activity Log'!C13=$B$3)),(OR($E$3="All",'Monthly Activity Log'!B13=$E$3))),'Monthly Activity Log'!E13,"") | F14: =IF(AND(('Monthly Activity Log'!C13<>""),(OR($B$3="All",'Monthly Activity Log'!C13=$B$3)),(OR($E$3="All",'Monthly Activity Log'!B13=$E$3))),'Monthly Activity Log'!F13,"") | G14: =IF(AND(('Monthly Activity Log'!C13<>""),(OR($B$3="All",'Monthly Activity Log'!C13=$B$3)),(OR($E$3="All",'Monthly Activity Log'!B13=$E$3))),'Monthly Activity Log'!G13,"") | H14: =IF(AND(('Monthly Activity Log'!C13<>""),(OR($B$3="All",'Monthly Activity Log'!C13=$B$3)),(OR($E$3="All",'Monthly Activity Log'!B13=$E$3))),'Monthly Activity Log'!H13,"") | I14: =IF(AND(('Monthly Activity Log'!C13<>""),(OR($B$3="All",'Monthly Activity Log'!C13=$B$3)),(OR($E$3="All",'Monthly Activity Log'!B13=$E$3))),'Monthly Activity Log'!I13,"") | J14: =IF(AND(('Monthly Activity Log'!C13<>""),(OR($B$3="All",'Monthly Activity Log'!C13=$B$3)),(OR($E$3="All",'Monthly Activity Log'!B13=$E$3))),'Monthly Activity Log'!J13,"") | K14: =IF(AND(('Monthly Activity Log'!C13<>""),(OR($B$3="All",'Monthly Activity Log'!C13=$B$3)),(OR($E$3="All",'Monthly Activity Log'!B13=$E$3))),'Monthly Activity Log'!K13,"")
A15: =IF(AND(('Monthly Activity Log'!C14<>""),(OR($B$3="All",'Monthly Activity Log'!C14=$B$3)),(OR($E$3="All",'Monthly Activity Log'!B14=$E$3))),ROW()-4,"") | B15: =IF(AND(('Monthly Activity Log'!C14<>""),(OR($B$3="All",'Monthly Activity Log'!C14=$B$3)),(OR($E$3="All",'Monthly Activity Log'!B14=$E$3))),'Monthly Activity Log'!B14,"") | C15: =IF(AND(('Monthly Activity Log'!C14<>""),(OR($B$3="All",'Monthly Activity Log'!C14=$B$3)),(OR($E$3="All",'Monthly Activity Log'!B14=$E$3))),'Monthly Activity Log'!C14,"") | D15: =IF(AND(('Monthly Activity Log'!C14<>""),(OR($B$3="All",'Monthly Activity Log'!C14=$B$3)),(OR($E$3="All",'Monthly Activity Log'!B14=$E$3))),'Monthly Activity Log'!D14,"") | E15: =IF(AND(('Monthly Activity Log'!C14<>""),(OR($B$3="All",'Monthly Activity Log'!C14=$B$3)),(OR($E$3="All",'Monthly Activity Log'!B14=$E$3))),'Monthly Activity Log'!E14,"") | F15: =IF(AND(('Monthly Activity Log'!C14<>""),(OR($B$3="All",'Monthly Activity Log'!C14=$B$3)),(OR($E$3="All",'Monthly Activity Log'!B14=$E$3))),'Monthly Activity Log'!F14,"") | G15: =IF(AND(('Monthly Activity Log'!C14<>""),(OR($B$3="All",'Monthly Activity Log'!C14=$B$3)),(OR($E$3="All",'Monthly Activity Log'!B14=$E$3))),'Monthly Activity Log'!G14,"") | H15: =IF(AND(('Monthly Activity Log'!C14<>""),(OR($B$3="All",'Monthly Activity Log'!C14=$B$3)),(OR($E$3="All",'Monthly Activity Log'!B14=$E$3))),'Monthly Activity Log'!H14,"") | I15: =IF(AND(('Monthly Activity Log'!C14<>""),(OR($B$3="All",'Monthly Activity Log'!C14=$B$3)),(OR($E$3="All",'Monthly Activity Log'!B14=$E$3))),'Monthly Activity Log'!I14,"") | J15: =IF(AND(('Monthly Activity Log'!C14<>""),(OR($B$3="All",'Monthly Activity Log'!C14=$B$3)),(OR($E$3="All",'Monthly Activity Log'!B14=$E$3))),'Monthly Activity Log'!J14,"") | K15: =IF(AND(('Monthly Activity Log'!C14<>""),(OR($B$3="All",'Monthly Activity Log'!C14=$B$3)),(OR($E$3="All",'Monthly Activity Log'!B14=$E$3))),'Monthly Activity Log'!K14,"")
A16: =IF(AND(('Monthly Activity Log'!C15<>""),(OR($B$3="All",'Monthly Activity Log'!C15=$B$3)),(OR($E$3="All",'Monthly Activity Log'!B15=$E$3))),ROW()-4,"") | B16: =IF(AND(('Monthly Activity Log'!C15<>""),(OR($B$3="All",'Monthly Activity Log'!C15=$B$3)),(OR($E$3="All",'Monthly Activity Log'!B15=$E$3))),'Monthly Activity Log'!B15,"") | C16: =IF(AND(('Monthly Activity Log'!C15<>""),(OR($B$3="All",'Monthly Activity Log'!C15=$B$3)),(OR($E$3="All",'Monthly Activity Log'!B15=$E$3))),'Monthly Activity Log'!C15,"") | D16: =IF(AND(('Monthly Activity Log'!C15<>""),(OR($B$3="All",'Monthly Activity Log'!C15=$B$3)),(OR($E$3="All",'Monthly Activity Log'!B15=$E$3))),'Monthly Activity Log'!D15,"") | E16: =IF(AND(('Monthly Activity Log'!C15<>""),(OR($B$3="All",'Monthly Activity Log'!C15=$B$3)),(OR($E$3="All",'Monthly Activity Log'!B15=$E$3))),'Monthly Activity Log'!E15,"") | F16: =IF(AND(('Monthly Activity Log'!C15<>""),(OR($B$3="All",'Monthly Activity Log'!C15=$B$3)),(OR($E$3="All",'Monthly Activity Log'!B15=$E$3))),'Monthly Activity Log'!F15,"") | G16: =IF(AND(('Monthly Activity Log'!C15<>""),(OR($B$3="All",'Monthly Activity Log'!C15=$B$3)),(OR($E$3="All",'Monthly Activity Log'!B15=$E$3))),'Monthly Activity Log'!G15,"") | H16: =IF(AND(('Monthly Activity Log'!C15<>""),(OR($B$3="All",'Monthly Activity Log'!C15=$B$3)),(OR($E$3="All",'Monthly Activity Log'!B15=$E$3))),'Monthly Activity Log'!H15,"") | I16: =IF(AND(('Monthly Activity Log'!C15<>""),(OR($B$3="All",'Monthly Activity Log'!C15=$B$3)),(OR($E$3="All",'Monthly Activity Log'!B15=$E$3))),'Monthly Activity Log'!I15,"") | J16: =IF(AND(('Monthly Activity Log'!C15<>""),(OR($B$3="All",'Monthly Activity Log'!C15=$B$3)),(OR($E$3="All",'Monthly Activity Log'!B15=$E$3))),'Monthly Activity Log'!J15,"") | K16: =IF(AND(('Monthly Activity Log'!C15<>""),(OR($B$3="All",'Monthly Activity Log'!C15=$B$3)),(OR($E$3="All",'Monthly Activity Log'!B15=$E$3))),'Monthly Activity Log'!K15,"")
... A204: =IF(AND(('Monthly Activity Log'!C203<>""),(OR($B$3="All",'Monthly Activity Log'!C203=$B$3)),(OR($E$3="All",'Monthly Activity Log'!B203=$E$3))),ROW()-4,"") | B204: =IF(AND(('Monthly Activity Log'!C203<>""),(OR($B$3="All",'Monthly Activity Log'!C203=$B$3)),(OR($E$3="All",'Monthly Activity Log'!B203=$E$3))),'Monthly Activity Log'!B203,"") | C204: =IF(AND(('Monthly Activity Log'!C203<>""),(OR($B$3="All",'Monthly Activity Log'!C203=$B$3)),(OR($E$3="All",'Monthly Activity Log'!B203=$E$3))),'Monthly Activity Log'!C203,"") | D204: =IF(AND(('Monthly Activity Log'!C203<>""),(OR($B$3="All",'Monthly Activity Log'!C203=$B$3)),(OR($E$3="All",'Monthly Activity Log'!B203=$E$3))),'Monthly Activity Log'!D203,"") | E204: =IF(AND(('Monthly Activity Log'!C203<>""),(OR($B$3="All",'Monthly Activity Log'!C203=$B$3)),(OR($E$3="All",'Monthly Activity Log'!B203=$E$3))),'Monthly Activity Log'!E203,"") | F204: =IF(AND(('Monthly Activity Log'!C203<>""),(OR($B$3="All",'Monthly Activity Log'!C203=$B$3)),(OR($E$3="All",'Monthly Activity Log'!B203=$E$3))),'Monthly Activity Log'!F203,"") | G204: =IF(AND(('Monthly Activity Log'!C203<>""),(OR($B$3="All",'Monthly Activity Log'!C203=$B$3)),(OR($E$3="All",'Monthly Activity Log'!B203=$E$3))),'Monthly Activity Log'!G203,"") | H204: =IF(AND(('Monthly Activity Log'!C203<>""),(OR($B$3="All",'Monthly Activity Log'!C203=$B$3)),(OR($E$3="All",'Monthly Activity Log'!B203=$E$3))),'Monthly Activity Log'!H203,"") | I204: =IF(AND(('Monthly Activity Log'!C203<>""),(OR($B$3="All",'Monthly Activity Log'!C203=$B$3)),(OR($E$3="All",'Monthly Activity Log'!B203=$E$3))),'Monthly Activity Log'!I203,"") | J204: =IF(AND(('Monthly Activity Log'!C203<>""),(OR($B$3="All",'Monthly Activity Log'!C203=$B$3)),(OR($E$3="All",'Monthly Activity Log'!B203=$E$3))),'Monthly Activity Log'!J203,"") | K204: =IF(AND(('Monthly Activity Log'!C203<>""),(OR($B$3="All",'Monthly Activity Log'!C203=$B$3)),(OR($E$3="All",'Monthly Activity Log'!B203=$E$3))),'Monthly Activity Log'!K203,"")

Sheet Client Report
A1: BA Team – Activities by Client
A2: 📌 Updates automatically from Monthly Activity Log. Use the Month filter to narrow results.
A3: Filter: Month | B3: All
A4: Client | B4: Total | C4: Completed | D4: In Progress | E4: Pending | F4: % Completed | G4: % of All Work | H4: Top Assignee | I4: Top Category | J4: Open Items
A5: SANPC | B5: =IF($B$3="All",COUNTIF('Monthly Activity Log'!H$4:H$200,"SANPC"),COUNTIFS('Monthly Activity Log'!B$4:B$200,$B$3,'Monthly Activity Log'!H$4:H$200,"SANPC")) | C5: =IF($B$3="All",COUNTIFS('Monthly Activity Log'!H$4:H$200,"SANPC",'Monthly Activity Log'!K$4:K$200,"Completed"),COUNTIFS('Monthly Activity Log'!B$4:B$200,$B$3,'Monthly Activity Log'!H$4:H$200,"SANPC",'Monthly Activity Log'!K$4:K$200,"Completed")) | D5: =IF($B$3="All",COUNTIFS('Monthly Activity Log'!H$4:H$200,"SANPC",'Monthly Activity Log'!K$4:K$200,"In Progress"),COUNTIFS('Monthly Activity Log'!B$4:B$200,$B$3,'Monthly Activity Log'!H$4:H$200,"SANPC",'Monthly Activity Log'!K$4:K$200,"In Progress")) | E5: =IF($B$3="All",COUNTIFS('Monthly Activity Log'!H$4:H$200,"SANPC",'Monthly Activity Log'!K$4:K$200,"Pending"),COUNTIFS('Monthly Activity Log'!B$4:B$200,$B$3,'Monthly Activity Log'!H$4:H$200,"SANPC",'Monthly Activity Log'!K$4:K$200,"Pending")) | F5: =IFERROR(C5/B5,0) | G5: =IFERROR(B5/'Summary Dashboard'!A7,0) | H5: =IF(B5=0,"-",IF(IF($B$3="All",COUNTIFS('Monthly Activity Log'!H$4:H$200,"SANPC",'Monthly Activity Log'!C$4:C$200,"Shennaz"),COUNTIFS('Monthly Activity Log'!B$4:B$200,$B$3,'Monthly Activity Log'!H$4:H$200,"SANPC",'Monthly Activity Log'!C$4:C$200,"Shennaz"))=MAX(IF($B$3="All",COUNTIFS('Monthly Activity Log'!H$4:H$200,"SANPC",'Monthly Activity Log'!C$4:C$200,"Shennaz"),COUNTIFS('Monthly Activity Log'!B$4:B$200,$B$3,'Monthly Activity Log'!H$4:H$200,"SANPC",'Monthly Activity Log'!C$4:C$200,"Shennaz")),IF($B$3="All",COUNTIFS('Monthly Activity Log'!H$4:H$200,"SANPC",'Monthly Activity Log'!C$4:C$200,"Nyameka"),COUNTIFS('Monthly Activity Log'!B$4:B$200,$B$3,'Monthly Activity Log'!H$4:H$200,"SANPC",'Monthly Activity Log'!C$4:C$200,"Nyameka")),IF($B$3="All",COUNTIFS('Monthly Activity Log'!H$4:H$200,"SANPC",'Monthly Activity Log'!C$4:C$200,"Lindiwe"),COUNTIFS('Monthly Activity Log'!B$4:B$200,$B$3,'Monthly Activity Log'!H$4:H$200,"SANPC",'Monthly Activity Log'!C$4:C$200,"Lindiwe")),IF($B$3="All",COUNTIFS('Monthly Activity Log'!H$4:H$200,"SANPC",'Monthly Activity Log'!C$4:C$200,"T A Willems"),COUNTIFS('Monthly Activity Log'!B$4:B$200,$B$3,'Monthly Activity Log'!H$4:H$200,"SANPC",'Monthly Activity Log'!C$4:C$200,"T A Willems")),IF($B$3="All",COUNTIFS('Monthly Activity Log'!H$4:H$200,"SANPC",'Monthly Activity Log'!C$4:C$200,"Mphatheleni Matidze"),COUNTIFS('Monthly Activity Log'!B$4:B$200,$B$3,'Monthly Activity Log'!H$4:H$200,"SANPC",'Monthly Activity Log'!C$4:C$200,"Mphatheleni Matidze"))),"Shennaz",IF(IF($B$3="All",COUNTIFS('Monthly Activity Log'!H$4:H$200,"SANPC",'Monthly Activity Log'!C$4:C$200,"Nyameka"),COUNTIFS('Monthly Activity Log'!B$4:B$200,$B$3,'Monthly Activity Log'!H$4:H$200,"SANPC",'Monthly Activity Log'!C$4:C$200,"Nyameka"))=MAX(IF($B$3="All",COUNTIFS('Monthly Activity Log'!H$4:H$200,"SANPC",'Monthly Activity Log'!C$4:C$200,"Shennaz"),COUNTIFS('Monthly Activity Log'!B$4:B$200,$B$3,'Monthly Activity Log'!H$4:H$200,"SANPC",'Monthly Activity Log'!C$4:C$200,"Shennaz")),IF($B$3="All",COUNTIFS('Monthly Activity Log'!H$4:H$200,"SANPC",'Monthly Activity Log'!C$4:C$200,"Nyameka"),COUNTIFS('Monthly Activity Log'!B$4:B$200,$B$3,'Monthly Activity Log'!H$4:H$200,"SANPC",'Monthly Activity Log'!C$4:C$200,"Nyameka")),IF($B$3="All",COUNTIFS('Monthly Activity Log'!H$4:H$200,"SANPC",'Monthly Activity Log'!C$4:C$200,"Lindiwe"),COUNTIFS('Monthly Activity Log'!B$4:B$200,$B$3,'Monthly Activity Log'!H$4:H$200,"SANPC",'Monthly Activity Log'!C$4:C$200,"Lindiwe")),IF($B$3="All",COUNTIFS('Monthly Activity Log'!H$4:H$200,"SANPC",'Monthly Activity Log'!C$4:C$200,"T A Willems"),COUNTIFS('Monthly Activity Log'!B$4:B$200,$B$3,'Monthly Activity Log'!H$4:H$200,"SANPC",'Monthly Activity Log'!C$4:C$200,"T A Willems")),IF($B$3="All",COUNTIFS('Monthly Activity Log'!H$4:H$200,"SANPC",'Monthly Activity Log'!C$4:C$200,"Mphatheleni Matidze"),COUNTIFS('Monthly Activity Log'!B$4:B$200,$B$3,'Monthly Activity Log'!H$4:H$200,"SANPC",'Monthly Activity Log'!C$4:C$200,"Mphatheleni Matidze"))),"Nyameka",IF(IF($B$3="All",COUNTIFS('Monthly Activity Log'!H$4:H$200,"SANPC",'Monthly Activity Log'!C$4:C$200,"Lindiwe"),COUNTIFS('Monthly Activity Log'!B$4:B$200,$B$3,'Monthly Activity Log'!H$4:H$200,"SANPC",'Monthly Activity Log'!C$4:C$200,"Lindiwe"))=MAX(IF($B$3="All",COUNTIFS('Monthly Activity Log'!H$4:H$200,"SANPC",'Monthly Activity Log'!C$4:C$200,"Shennaz"),COUNTIFS('Monthly Activity Log'!B$4:B$200,$B$3,'Monthly Activity Log'!H$4:H$200,"SANPC",'Monthly Activity Log'!C$4:C$200,"Shennaz")),IF($B$3="All",COUNTIFS('Monthly Activity Log'!H$4:H$200,"SANPC",'Monthly Activity Log'!C$4:C$200,"Nyameka"),COUNTIFS('Monthly Activity Log'!B$4:B$200,$B$3,'Monthly Activity Log'!H$4:H$200,"SANPC",'Monthly Activity Log'!C$4:C$200,"Nyameka")),IF($B$3="All",COUNTIFS('Monthly Activity Log'!H$4:H$200,"SANPC",'Monthly Activity Log'!C$4:C$200,"Lindiwe"),COUNTIFS('Monthly Activity Log'!B$4:B$200,$B$3,'Monthly Activity Log'!H$4:H$200,"SANPC",'Monthly Activity Log'!C$4:C$200,"Lindiwe")),IF($B$3="All",COUNTIFS('Monthly Activity Log'!H$4:H$200,"SANPC",'Monthly Activity Log'!C$4:C$200,"T A Willems"),COUNTIFS('Monthly Activity Log'!B$4:B$200,$B$3,'Monthly Activity Log'!H$4:H$200,"SANPC",'Monthly Activity Log'!C$4:C$200,"T A Willems")),IF($B$3="All",COUNTIFS('Monthly Activity Log'!H$4:H$200,"SANPC",'Monthly Activity Log'!C$4:C$200,"Mphatheleni Matidze"),COUNTIFS('Monthly Activity Log'!B$4:B$200,$B$3,'Monthly Activity Log'!H$4:H$200,"SANPC",'Monthly Activity Log'!C$4:C$200,"Mphatheleni Matidze"))),"Lindiwe",IF(IF($B$3="All",COUNTIFS('Monthly Activity Log'!H$4:H$200,"SANPC",'Monthly Activity Log'!C$4:C$200,"T A Willems"),COUNTIFS('Monthly Activity Log'!B$4:B$200,$B$3,'Monthly Activity Log'!H$4:H$200,"SANPC",'Monthly Activity Log'!C$4:C$200,"T A Willems"))=MAX(IF($B$3="All",COUNTIFS('Monthly Activity Log'!H$4:H$200,"SANPC",'Monthly Activity Log'!C$4:C$200,"Shennaz"),COUNTIFS('Monthly Activity Log'!B$4:B$200,$B$3,'Monthly Activity Log'!H$4:H$200,"SANPC",'Monthly Activity Log'!C$4:C$200,"Shennaz")),IF($B$3="All",COUNTIFS('Monthly Activity Log'!H$4:H$200,"SANPC",'Monthly Activity Log'!C$4:C$200,"Nyameka"),COUNTIFS('Monthly Activity Log'!B$4:B$200,$B$3,'Monthly Activity Log'!H$4:H$200,"SANPC",'Monthly Activity Log'!C$4:C$200,"Nyameka")),IF($B$3="All",COUNTIFS('Monthly Activity Log'!H$4:H$200,"SANPC",'Monthly Activity Log'!C$4:C$200,"Lindiwe"),COUNTIFS('Monthly Activity Log'!B$4:B$200,$B$3,'Monthly Activity Log'!H$4:H$200,"SANPC",'Monthly Activity Log'!C$4:C$200,"Lindiwe")),IF($B$3="All",COUNTIFS('Monthly Activity Log'!H$4:H$200,"SANPC",'Monthly Activity Log'!C$4:C$200,"T A Willems"),COUNTIFS('Monthly Activity Log'!B$4:B$200,$B$3,'Monthly Activity Log'!H$4:H$200,"SANPC",'Monthly Activity Log'!C$4:C$200,"T A Willems")),IF($B$3="All",COUNTIFS('Monthly Activity Log'!H$4:H$200,"SANPC",'Monthly Activity Log'!C$4:C$200,"Mphatheleni Matidze"),COUNTIFS('Monthly Activity Log'!B$4:B$200,$B$3,'Monthly Activity Log'!H$4:H$200,"SANPC",'Monthly Activity Log'!C$4:C$200,"Mphatheleni Matidze"))),"T A Willems",IF(IF($B$3="All",COUNTIFS('Monthly Activity Log'!H$4:H$200,"SANPC",'Monthly Activity Log'!C$4:C$200,"Mphatheleni Matidze"),COUNTIFS('Monthly Activity Log'!B$4:B$200,$B$3,'Monthly Activity Log'!H$4:H$200,"SANPC",'Monthly Activity Log'!C$4:C$200,"Mphatheleni Matidze"))=MAX(IF($B$3="All",COUNTIFS('Monthly Activity Log'!H$4:H$200,"SANPC",'Monthly Activity Log'!C$4:C$200,"Shennaz"),COUNTIFS('Monthly Activity Log'!B$4:B$200,$B$3,'Monthly Activity Log'!H$4:H$200,"SANPC",'Monthly Activity Log'!C$4:C$200,"Shennaz")),IF($B$3="All",COUNTIFS('Monthly Activity Log'!H$4:H$200,"SANPC",'Monthly Activity Log'!C$4:C$200,"Nyameka"),COUNTIFS('Monthly Activity Log'!B$4:B$200,$B$3,'Monthly Activity Log'!H$4:H$200,"SANPC",'Monthly Activity Log'!C$4:C$200,"Nyameka")),IF($B$3="All",COUNTIFS('Monthly Activity Log'!H$4:H$200,"SANPC",'Monthly Activity Log'!C$4:C$200,"Lindiwe"),COUNTIFS('Monthly Activity Log'!B$4:B$200,$B$3,'Monthly Activity Log'!H$4:H$200,"SANPC",'Monthly Activity Log'!C$4:C$200,"Lindiwe")),IF($B$3="All",COUNTIFS('Monthly Activity Log'!H$4:H$200,"SANPC",'Monthly Activity Log'!C$4:C$200,"T A Willems"),COUNTIFS('Monthly Activity Log'!B$4:B$200,$B$3,'Monthly Activity Log'!H$4:H$200,"SANPC",'Monthly Activity Log'!C$4:C$200,"T A Willems")),IF($B$3="All",COUNTIFS('Monthly Activity Log'!H$4:H$200,"SANPC",'Monthly Activity Log'!C$4:C$200,"Mphatheleni Matidze"),COUNTIFS('Monthly Activity Log'!B$4:B$200,$B$3,'Monthly Activity Log'!H$4:H$200,"SANPC",'Monthly Activity Log'!C$4:C$200,"Mphatheleni Matidze"))),"Mphatheleni Matidze","-")))))) | I5: =IF(B5=0,"-",IF(IF($B$3="All",COUNTIFS('Monthly Activity Log'!H$4:H$200,"SANPC",'Monthly Activity Log'!I$4:I$200,"Project"),COUNTIFS('Monthly Activity Log'!B$4:B$200,$B$3,'Monthly Activity Log'!H$4:H$200,"SANPC",'Monthly Activity Log'!I$4:I$200,"Project"))=MAX(IF($B$3="All",COUNTIFS('Monthly Activity Log'!H$4:H$200,"SANPC",'Monthly Activity Log'!I$4:I$200,"Project"),COUNTIFS('Monthly Activity Log'!B$4:B$200,$B$3,'Monthly Activity Log'!H$4:H$200,"SANPC",'Monthly Activity Log'!I$4:I$200,"Project")),IF($B$3="All",COUNTIFS('Monthly Activity Log'!H$4:H$200,"SANPC",'Monthly Activity Log'!I$4:I$200,"Incident/Bug Fix"),COUNTIFS('Monthly Activity Log'!B$4:B$200,$B$3,'Monthly Activity Log'!H$4:H$200,"SANPC",'Monthly Activity Log'!I$4:I$200,"Incident/Bug Fix")),IF($B$3="All",COUNTIFS('Monthly Activity Log'!H$4:H$200,"SANPC",'Monthly Activity Log'!I$4:I$200,"Change Request"),COUNTIFS('Monthly Activity Log'!B$4:B$200,$B$3,'Monthly Activity Log'!H$4:H$200,"SANPC",'Monthly Activity Log'!I$4:I$200,"Change Request")),IF($B$3="All",COUNTIFS('Monthly Activity Log'!H$4:H$200,"SANPC",'Monthly Activity Log'!I$4:I$200,"User Support"),COUNTIFS('Monthly Activity Log'!B$4:B$200,$B$3,'Monthly Activity Log'!H$4:H$200,"SANPC",'Monthly Activity Log'!I$4:I$200,"User Support")),IF($B$3="All",COUNTIFS('Monthly Activity Log'!H$4:H$200,"SANPC",'Monthly Activity Log'!I$4:I$200,"Admin/Config"),COUNTIFS('Monthly Activity Log'!B$4:B$200,$B$3,'Monthly Activity Log'!H$4:H$200,"SANPC",'Monthly Activity Log'!I$4:I$200,"Admin/Config")),IF($B$3="All",COUNTIFS('Monthly Activity Log'!H$4:H$200,"SANPC",'Monthly Activity Log'!I$4:I$200,"Reporting"),COUNTIFS('Monthly Activity Log'!B$4:B$200,$B$3,'Monthly Activity Log'!H$4:H$200,"SANPC",'Monthly Activity Log'!I$4:I$200,"Reporting")),IF($B$3="All",COUNTIFS('Monthly Activity Log'!H$4:H$200,"SANPC",'Monthly Activity Log'!I$4:I$200,"Mentoring"),COUNTIFS('Monthly Activity Log'!B$4:B$200,$B$3,'Monthly Activity Log'!H$4:H$200,"SANPC",'Monthly Activity Log'!I$4:I$200,"Mentoring")),IF($B$3="All",COUNTIFS('Monthly Activity Log'!H$4:H$200,"SANPC",'Monthly Activity Log'!I$4:I$200,"Other"),COUNTIFS('Monthly Activity Log'!B$4:B$200,$B$3,'Monthly Activity Log'!H$4:H$200,"SANPC",'Monthly Activity Log'!I$4:I$200,"Other"))),"Project",IF(IF($B$3="All",COUNTIFS('Monthly Activity Log'!H$4:H$200,"SANPC",'Monthly Activity Log'!I$4:I$200,"Incident/Bug Fix"),COUNTIFS('Monthly Activity Log'!B$4:B$200,$B$3,'Monthly Activity Log'!H$4:H$200,"SANPC",'Monthly Activity Log'!I$4:I$200,"Incident/Bug Fix"))=MAX(IF($B$3="All",COUNTIFS('Monthly Activity Log'!H$4:H$200,"SANPC",'Monthly Activity Log'!I$4:I$200,"Project"),COUNTIFS('Monthly Activity Log'!B$4:B$200,$B$3,'Monthly Activity Log'!H$4:H$200,"SANPC",'Monthly Activity Log'!I$4:I$200,"Project")),IF($B$3="All",COUNTIFS('Monthly Activity Log'!H$4:H$200,"SANPC",'Monthly Activity Log'!I$4:I$200,"Incident/Bug Fix"),COUNTIFS('Monthly Activity Log'!B$4:B$200,$B$3,'Monthly Activity Log'!H$4:H$200,"SANPC",'Monthly Activity Log'!I$4:I$200,"Incident/Bug Fix")),IF($B$3="All",COUNTIFS('Monthly Activity Log'!H$4:H$200,"SANPC",'Monthly Activity Log'!I$4:I$200,"Change Request"),COUNTIFS('Monthly Activity Log'!B$4:B$200,$B$3,'Monthly Activity Log'!H$4:H$200,"SANPC",'Monthly Activity Log'!I$4:I$200,"Change Request")),IF($B$3="All",COUNTIFS('Monthly Activity Log'!H$4:H$200,"SANPC",'Monthly Activity Log'!I$4:I$200,"User Support"),COUNTIFS('Monthly Activity Log'!B$4:B$200,$B$3,'Monthly Activity Log'!H$4:H$200,"SANPC",'Monthly Activity Log'!I$4:I$200,"User Support")),IF($B$3="All",COUNTIFS('Monthly Activity Log'!H$4:H$200,"SANPC",'Monthly Activity Log'!I$4:I$200,"Admin/Config"),COUNTIFS('Monthly Activity Log'!B$4:B$200,$B$3,'Monthly Activity Log'!H$4:H$200,"SANPC",'Monthly Activity Log'!I$4:I$200,"Admin/Config")),IF($B$3="All",COUNTIFS('Monthly Activity Log'!H$4:H$200,"SANPC",'Monthly Activity Log'!I$4:I$200,"Reporting"),COUNTIFS('Monthly Activity Log'!B$4:B$200,$B$3,'Monthly Activity Log'!H$4:H$200,"SANPC",'Monthly Activity Log'!I$4:I$200,"Reporting")),IF($B$3="All",COUNTIFS('Monthly Activity Log'!H$4:H$200,"SANPC",'Monthly Activity Log'!I$4:I$200,"Mentoring"),COUNTIFS('Monthly Activity Log'!B$4:B$200,$B$3,'Monthly Activity Log'!H$4:H$200,"SANPC",'Monthly Activity Log'!I$4:I$200,"Mentoring")),IF($B$3="All",COUNTIFS('Monthly Activity Log'!H$4:H$200,"SANPC",'Monthly Activity Log'!I$4:I$200,"Other"),COUNTIFS('Monthly Activity Log'!B$4:B$200,$B$3,'Monthly Activity Log'!H$4:H$200,"SANPC",'Monthly Activity Log'!I$4:I$200,"Other"))),"Incident/Bug Fix",IF(IF($B$3="All",COUNTIFS('Monthly Activity Log'!H$4:H$200,"SANPC",'Monthly Activity Log'!I$4:I$200,"Change Request"),COUNTIFS('Monthly Activity Log'!B$4:B$200,$B$3,'Monthly Activity Log'!H$4:H$200,"SANPC",'Monthly Activity Log'!I$4:I$200,"Change Request"))=MAX(IF($B$3="All",COUNTIFS('Monthly Activity Log'!H$4:H$200,"SANPC",'Monthly Activity Log'!I$4:I$200,"Project"),COUNTIFS('Monthly Activity Log'!B$4:B$200,$B$3,'Monthly Activity Log'!H$4:H$200,"SANPC",'Monthly Activity Log'!I$4:I$200,"Project")),IF($B$3="All",COUNTIFS('Monthly Activity Log'!H$4:H$200,"SANPC",'Monthly Activity Log'!I$4:I$200,"Incident/Bug Fix"),COUNTIFS('Monthly Activity Log'!B$4:B$200,$B$3,'Monthly Activity Log'!H$4:H$200,"SANPC",'Monthly Activity Log'!I$4:I$200,"Incident/Bug Fix")),IF($B$3="All",COUNTIFS('Monthly Activity Log'!H$4:H$200,"SANPC",'Monthly Activity Log'!I$4:I$200,"Change Request"),COUNTIFS('Monthly Activity Log'!B$4:B$200,$B$3,'Monthly Activity Log'!H$4:H$200,"SANPC",'Monthly Activity Log'!I$4:I$200,"Change Request")),IF($B$3="All",COUNTIFS('Monthly Activity Log'!H$4:H$200,"SANPC",'Monthly Activity Log'!I$4:I$200,"User Support"),COUNTIFS('Monthly Activity Log'!B$4:B$200,$B$3,'Monthly Activity Log'!H$4:H$200,"SANPC",'Monthly Activity Log'!I$4:I$200,"User Support")),IF($B$3="All",COUNTIFS('Monthly Activity Log'!H$4:H$200,"SANPC",'Monthly Activity Log'!I$4:I$200,"Admin/Config"),COUNTIFS('Monthly Activity Log'!B$4:B$200,$B$3,'Monthly Activity Log'!H$4:H$200,"SANPC",'Monthly Activity Log'!I$4:I$200,"Admin/Config")),IF($B$3="All",COUNTIFS('Monthly Activity Log'!H$4:H$200,"SANPC",'Monthly Activity Log'!I$4:I$200,"Reporting"),COUNTIFS('Monthly Activity Log'!B$4:B$200,$B$3,'Monthly Activity Log'!H$4:H$200,"SANPC",'Monthly Activity Log'!I$4:I$200,"Reporting")),IF($B$3="All",COUNTIFS('Monthly Activity Log'!H$4:H$200,"SANPC",'Monthly Activity Log'!I$4:I$200,"Mentoring"),COUNTIFS('Monthly Activity Log'!B$4:B$200,$B$3,'Monthly Activity Log'!H$4:H$200,"SANPC",'Monthly Activity Log'!I$4:I$200,"Mentoring")),IF($B$3="All",COUNTIFS('Monthly Activity Log'!H$4:H$200,"SANPC",'Monthly Activity Log'!I$4:I$200,"Other"),COUNTIFS('Monthly Activity Log'!B$4:B$200,$B$3,'Monthly Activity Log'!H$4:H$200,"SANPC",'Monthly Activity Log'!I$4:I$200,"Other"))),"Change Request",IF(IF($B$3="All",COUNTIFS('Monthly Activity Log'!H$4:H$200,"SANPC",'Monthly Activity Log'!I$4:I$200,"User Support"),COUNTIFS('Monthly Activity Log'!B$4:B$200,$B$3,'Monthly Activity Log'!H$4:H$200,"SANPC",'Monthly Activity Log'!I$4:I$200,"User Support"))=MAX(IF($B$3="All",COUNTIFS('Monthly Activity Log'!H$4:H$200,"SANPC",'Monthly Activity Log'!I$4:I$200,"Project"),COUNTIFS('Monthly Activity Log'!B$4:B$200,$B$3,'Monthly Activity Log'!H$4:H$200,"SANPC",'Monthly Activity Log'!I$4:I$200,"Project")),IF($B$3="All",COUNTIFS('Monthly Activity Log'!H$4:H$200,"SANPC",'Monthly Activity Log'!I$4:I$200,"Incident/Bug Fix"),COUNTIFS('Monthly Activity Log'!B$4:B$200,$B$3,'Monthly Activity Log'!H$4:H$200,"SANPC",'Monthly Activity Log'!I$4:I$200,"Incident/Bug Fix")),IF($B$3="All",COUNTIFS('Monthly Activity Log'!H$4:H$200,"SANPC",'Monthly Activity Log'!I$4:I$200,"Change Request"),COUNTIFS('Monthly Activity Log'!B$4:B$200,$B$3,'Monthly Activity Log'!H$4:H$200,"SANPC",'Monthly Activity Log'!I$4:I$200,"Change Request")),IF($B$3="All",COUNTIFS('Monthly Activity Log'!H$4:H$200,"SANPC",'Monthly Activity Log'!I$4:I$200,"User Support"),COUNTIFS('Monthly Activity Log'!B$4:B$200,$B$3,'Monthly Activity Log'!H$4:H$200,"SANPC",'Monthly Activity Log'!I$4:I$200,"User Support")),IF($B$3="All",COUNTIFS('Monthly Activity Log'!H$4:H$200,"SANPC",'Monthly Activity Log'!I$4:I$200,"Admin/Config"),COUNTIFS('Monthly Activity Log'!B$4:B$200,$B$3,'Monthly Activity Log'!H$4:H$200,"SANPC",'Monthly Activity Log'!I$4:I$200,"Admin/Config")),IF($B$3="All",COUNTIFS('Monthly Activity Log'!H$4:H$200,"SANPC",'Monthly Activity Log'!I$4:I$200,"Reporting"),COUNTIFS('Monthly Activity Log'!B$4:B$200,$B$3,'Monthly Activity Log'!H$4:H$200,"SANPC",'Monthly Activity Log'!I$4:I$200,"Reporting")),IF($B$3="All",COUNTIFS('Monthly Activity Log'!H$4:H$200,"SANPC",'Monthly Activity Log'!I$4:I$200,"Mentoring"),COUNTIFS('Monthly Activity Log'!B$4:B$200,$B$3,'Monthly Activity Log'!H$4:H$200,"SANPC",'Monthly Activity Log'!I$4:I$200,"Mentoring")),IF($B$3="All",COUNTIFS('Monthly Activity Log'!H$4:H$200,"SANPC",'Monthly Activity Log'!I$4:I$200,"Other"),COUNTIFS('Monthly Activity Log'!B$4:B$200,$B$3,'Monthly Activity Log'!H$4:H$200,"SANPC",'Monthly Activity Log'!I$4:I$200,"Other"))),"User Support",IF(IF($B$3="All",COUNTIFS('Monthly Activity Log'!H$4:H$200,"SANPC",'Monthly Activity Log'!I$4:I$200,"Admin/Config"),COUNTIFS('Monthly Activity Log'!B$4:B$200,$B$3,'Monthly Activity Log'!H$4:H$200,"SANPC",'Monthly Activity Log'!I$4:I$200,"Admin/Config"))=MAX(IF($B$3="All",COUNTIFS('Monthly Activity Log'!H$4:H$200,"SANPC",'Monthly Activity Log'!I$4:I$200,"Project"),COUNTIFS('Monthly Activity Log'!B$4:B$200,$B$3,'Monthly Activity Log'!H$4:H$200,"SANPC",'Monthly Activity Log'!I$4:I$200,"Project")),IF($B$3="All",COUNTIFS('Monthly Activity Log'!H$4:H$200,"SANPC",'Monthly Activity Log'!I$4:I$200,"Incident/Bug Fix"),COUNTIFS('Monthly Activity Log'!B$4:B$200,$B$3,'Monthly Activity Log'!H$4:H$200,"SANPC",'Monthly Activity Log'!I$4:I$200,"Incident/Bug Fix")),IF($B$3="All",COUNTIFS('Monthly Activity Log'!H$4:H$200,"SANPC",'Monthly Activity Log'!I$4:I$200,"Change Request"),COUNTIFS('Monthly Activity Log'!B$4:B$200,$B$3,'Monthly Activity Log'!H$4:H$200,"SANPC",'Monthly Activity Log'!I$4:I$200,"Change Request")),IF($B$3="All",COUNTIFS('Monthly Activity Log'!H$4:H$200,"SANPC",'Monthly Activity Log'!I$4:I$200,"User Support"),COUNTIFS('Monthly Activity Log'!B$4:B$200,$B$3,'Monthly Activity Log'!H$4:H$200,"SANPC",'Monthly Activity Log'!I$4:I$200,"User Support")),IF($B$3="All",COUNTIFS('Monthly Activity Log'!H$4:H$200,"SANPC",'Monthly Activity Log'!I$4:I$200,"Admin/Config"),COUNTIFS('Monthly Activity Log'!B$4:B$200,$B$3,'Monthly Activity Log'!H$4:H$200,"SANPC",'Monthly Activity Log'!I$4:I$200,"Admin/Config")),IF($B$3="All",COUNTIFS('Monthly Activity Log'!H$4:H$200,"SANPC",'Monthly Activity Log'!I$4:I$200,"Reporting"),COUNTIFS('Monthly Activity Log'!B$4:B$200,$B$3,'Monthly Activity Log'!H$4:H$200,"SANPC",'Monthly Activity Log'!I$4:I$200,"Reporting")),IF($B$3="All",COUNTIFS('Monthly Activity Log'!H$4:H$200,"SANPC",'Monthly Activity Log'!I$4:I$200,"Mentoring"),COUNTIFS('Monthly Activity Log'!B$4:B$200,$B$3,'Monthly Activity Log'!H$4:H$200,"SANPC",'Monthly Activity Log'!I$4:I$200,"Mentoring")),IF($B$3="All",COUNTIFS('Monthly Activity Log'!H$4:H$200,"SANPC",'Monthly Activity Log'!I$4:I$200,"Other"),COUNTIFS('Monthly Activity Log'!B$4:B$200,$B$3,'Monthly Activity Log'!H$4:H$200,"SANPC",'Monthly Activity Log'!I$4:I$200,"Other"))),"Admin/Config",IF(IF($B$3="All",COUNTIFS('Monthly Activity Log'!H$4:H$200,"SANPC",'Monthly Activity Log'!I$4:I$200,"Reporting"),COUNTIFS('Monthly Activity Log'!B$4:B$200,$B$3,'Monthly Activity Log'!H$4:H$200,"SANPC",'Monthly Activity Log'!I$4:I$200,"Reporting"))=MAX(IF($B$3="All",COUNTIFS('Monthly Activity Log'!H$4:H$200,"SANPC",'Monthly Activity Log'!I$4:I$200,"Project"),COUNTIFS('Monthly Activity Log'!B$4:B$200,$B$3,'Monthly Activity Log'!H$4:H$200,"SANPC",'Monthly Activity Log'!I$4:I$200,"Project")),IF($B$3="All",COUNTIFS('Monthly Activity Log'!H$4:H$200,"SANPC",'Monthly Activity Log'!I$4:I$200,"Incident/Bug Fix"),COUNTIFS('Monthly Activity Log'!B$4:B$200,$B$3,'Monthly Activity Log'!H$4:H$200,"SANPC",'Monthly Activity Log'!I$4:I$200,"Incident/Bug Fix")),IF($B$3="All",COUNTIFS('Monthly Activity Log'!H$4:H$200,"SANPC",'Monthly Activity Log'!I$4:I$200,"Change Request"),COUNTIFS('Monthly Activity Log'!B$4:B$200,$B$3,'Monthly Activity Log'!H$4:H$200,"SANPC",'Monthly Activity Log'!I$4:I$200,"Change Request")),IF($B$3="All",COUNTIFS('Monthly Activity Log'!H$4:H$200,"SANPC",'Monthly Activity Log'!I$4:I$200,"User Support"),COUNTIFS('Monthly Activity Log'!B$4:B$200,$B$3,'Monthly Activity Log'!H$4:H$200,"SANPC",'Monthly Activity Log'!I$4:I$200,"User Support")),IF($B$3="All",COUNTIFS('Monthly Activity Log'!H$4:H$200,"SANPC",'Monthly Activity Log'!I$4:I$200,"Admin/Config"),COUNTIFS('Monthly Activity Log'!B$4:B$200,$B$3,'Monthly Activity Log'!H$4:H$200,"SANPC",'Monthly Activity Log'!I$4:I$200,"Admin/Config")),IF($B$3="All",COUNTIFS('Monthly Activity Log'!H$4:H$200,"SANPC",'Monthly Activity Log'!I$4:I$200,"Reporting"),COUNTIFS('Monthly Activity Log'!B$4:B$200,$B$3,'Monthly Activity Log'!H$4:H$200,"SANPC",'Monthly Activity Log'!I$4:I$200,"Reporting")),IF($B$3="All",COUNTIFS('Monthly Activity Log'!H$4:H$200,"SANPC",'Monthly Activity Log'!I$4:I$200,"Mentoring"),COUNTIFS('Monthly Activity Log'!B$4:B$200,$B$3,'Monthly Activity Log'!H$4:H$200,"SANPC",'Monthly Activity Log'!I$4:I$200,"Mentoring")),IF($B$3="All",COUNTIFS('Monthly Activity Log'!H$4:H$200,"SANPC",'Monthly Activity Log'!I$4:I$200,"Other"),COUNTIFS('Monthly Activity Log'!B$4:B$200,$B$3,'Monthly Activity Log'!H$4:H$200,"SANPC",'Monthly Activity Log'!I$4:I$200,"Other"))),"Reporting",IF(IF($B$3="All",COUNTIFS('Monthly Activity Log'!H$4:H$200,"SANPC",'Monthly Activity Log'!I$4:I$200,"Mentoring"),COUNTIFS('Monthly Activity Log'!B$4:B$200,$B$3,'Monthly Activity Log'!H$4:H$200,"SANPC",'Monthly Activity Log'!I$4:I$200,"Mentoring"))=MAX(IF($B$3="All",COUNTIFS('Monthly Activity Log'!H$4:H$200,"SANPC",'Monthly Activity Log'!I$4:I$200,"Project"),COUNTIFS('Monthly Activity Log'!B$4:B$200,$B$3,'Monthly Activity Log'!H$4:H$200,"SANPC",'Monthly Activity Log'!I$4:I$200,"Project")),IF($B$3="All",COUNTIFS('Monthly Activity Log'!H$4:H$200,"SANPC",'Monthly Activity Log'!I$4:I$200,"Incident/Bug Fix"),COUNTIFS('Monthly Activity Log'!B$4:B$200,$B$3,'Monthly Activity Log'!H$4:H$200,"SANPC",'Monthly Activity Log'!I$4:I$200,"Incident/Bug Fix")),IF($B$3="All",COUNTIFS('Monthly Activity Log'!H$4:H$200,"SANPC",'Monthly Activity Log'!I$4:I$200,"Change Request"),COUNTIFS('Monthly Activity Log'!B$4:B$200,$B$3,'Monthly Activity Log'!H$4:H$200,"SANPC",'Monthly Activity Log'!I$4:I$200,"Change Request")),IF($B$3="All",COUNTIFS('Monthly Activity Log'!H$4:H$200,"SANPC",'Monthly Activity Log'!I$4:I$200,"User Support"),COUNTIFS('Monthly Activity Log'!B$4:B$200,$B$3,'Monthly Activity Log'!H$4:H$200,"SANPC",'Monthly Activity Log'!I$4:I$200,"User Support")),IF($B$3="All",COUNTIFS('Monthly Activity Log'!H$4:H$200,"SANPC",'Monthly Activity Log'!I$4:I$200,"Admin/Config"),COUNTIFS('Monthly Activity Log'!B$4:B$200,$B$3,'Monthly Activity Log'!H$4:H$200,"SANPC",'Monthly Activity Log'!I$4:I$200,"Admin/Config")),IF($B$3="All",COUNTIFS('Monthly Activity Log'!H$4:H$200,"SANPC",'Monthly Activity Log'!I$4:I$200,"Reporting"),COUNTIFS('Monthly Activity Log'!B$4:B$200,$B$3,'Monthly Activity Log'!H$4:H$200,"SANPC",'Monthly Activity Log'!I$4:I$200,"Reporting")),IF($B$3="All",COUNTIFS('Monthly Activity Log'!H$4:H$200,"SANPC",'Monthly Activity Log'!I$4:I$200,"Mentoring"),COUNTIFS('Monthly Activity Log'!B$4:B$200,$B$3,'Monthly Activity Log'!H$4:H$200,"SANPC",'Monthly Activity Log'!I$4:I$200,"Mentoring")),IF($B$3="All",COUNTIFS('Monthly Activity Log'!H$4:H$200,"SANPC",'Monthly Activity Log'!I$4:I$200,"Other"),COUNTIFS('Monthly Activity Log'!B$4:B$200,$B$3,'Monthly Activity Log'!H$4:H$200,"SANPC",'Monthly Activity Log'!I$4:I$200,"Other"))),"Mentoring",IF(IF($B$3="All",COUNTIFS('Monthly Activity Log'!H$4:H$200,"SANPC",'Monthly Activity Log'!I$4:I$200,"Other"),COUNTIFS('Monthly Activity Log'!B$4:B$200,$B$3,'Monthly Activity Log'!H$4:H$200,"SANPC",'Monthly Activity Log'!I$4:I$200,"Other"))=MAX(IF($B$3="All",COUNTIFS('Monthly Activity Log'!H$4:H$200,"SANPC",'Monthly Activity Log'!I$4:I$200,"Project"),COUNTIFS('Monthly Activity Log'!B$4:B$200,$B$3,'Monthly Activity Log'!H$4:H$200,"SANPC",'Monthly Activity Log'!I$4:I$200,"Project")),IF($B$3="All",COUNTIFS('Monthly Activity Log'!H$4:H$200,"SANPC",'Monthly Activity Log'!I$4:I$200,"Incident/Bug Fix"),COUNTIFS('Monthly Activity Log'!B$4:B$200,$B$3,'Monthly Activity Log'!H$4:H$200,"SANPC",'Monthly Activity Log'!I$4:I$200,"Incident/Bug Fix")),IF($B$3="All",COUNTIFS('Monthly Activity Log'!H$4:H$200,"SANPC",'Monthly Activity Log'!I$4:I$200,"Change Request"),COUNTIFS('Monthly Activity Log'!B$4:B$200,$B$3,'Monthly Activity Log'!H$4:H$200,"SANPC",'Monthly Activity Log'!I$4:I$200,"Change Request")),IF($B$3="All",COUNTIFS('Monthly Activity Log'!H$4:H$200,"SANPC",'Monthly Activity Log'!I$4:I$200,"User Support"),COUNTIFS('Monthly Activity Log'!B$4:B$200,$B$3,'Monthly Activity Log'!H$4:H$200,"SANPC",'Monthly Activity Log'!I$4:I$200,"User Support")),IF($B$3="All",COUNTIFS('Monthly Activity Log'!H$4:H$200,"SANPC",'Monthly Activity Log'!I$4:I$200,"Admin/Config"),COUNTIFS('Monthly Activity Log'!B$4:B$200,$B$3,'Monthly Activity Log'!H$4:H$200,"SANPC",'Monthly Activity Log'!I$4:I$200,"Admin/Config")),IF($B$3="All",COUNTIFS('Monthly Activity Log'!H$4:H$200,"SANPC",'Monthly Activity Log'!I$4:I$200,"Reporting"),COUNTIFS('Monthly Activity Log'!B$4:B$200,$B$3,'Monthly Activity Log'!H$4:H$200,"SANPC",'Monthly Activity Log'!I$4:I$200,"Reporting")),IF($B$3="All",COUNTIFS('Monthly Activity Log'!H$4:H$200,"SANPC",'Monthly Activity Log'!I$4:I$200,"Mentoring"),COUNTIFS('Monthly Activity Log'!B$4:B$200,$B$3,'Monthly Activity Log'!H$4:H$200,"SANPC",'Monthly Activity Log'!I$4:I$200,"Mentoring")),IF($B$3="All",COUNTIFS('Monthly Activity Log'!H$4:H$200,"SANPC",'Monthly Activity Log'!I$4:I$200,"Other"),COUNTIFS('Monthly Activity Log'!B$4:B$200,$B$3,'Monthly Activity Log'!H$4:H$200,"SANPC",'Monthly Activity Log'!I$4:I$200,"Other"))),"Other","-"))))))))) | J5: =D5+E5
A6: PetroSA | B6: =IF($B$3="All",COUNTIF('Monthly Activity Log'!H$4:H$200,"PetroSA"),COUNTIFS('Monthly Activity Log'!B$4:B$200,$B$3,'Monthly Activity Log'!H$4:H$200,"PetroSA")) | C6: =IF($B$3="All",COUNTIFS('Monthly Activity Log'!H$4:H$200,"PetroSA",'Monthly Activity Log'!K$4:K$200,"Completed"),COUNTIFS('Monthly Activity Log'!B$4:B$200,$B$3,'Monthly Activity Log'!H$4:H$200,"PetroSA",'Monthly Activity Log'!K$4:K$200,"Completed")) | D6: =IF($B$3="All",COUNTIFS('Monthly Activity Log'!H$4:H$200,"PetroSA",'Monthly Activity Log'!K$4:K$200,"In Progress"),COUNTIFS('Monthly Activity Log'!B$4:B$200,$B$3,'Monthly Activity Log'!H$4:H$200,"PetroSA",'Monthly Activity Log'!K$4:K$200,"In Progress")) | E6: =IF($B$3="All",COUNTIFS('Monthly Activity Log'!H$4:H$200,"PetroSA",'Monthly Activity Log'!K$4:K$200,"Pending"),COUNTIFS('Monthly Activity Log'!B$4:B$200,$B$3,'Monthly Activity Log'!H$4:H$200,"PetroSA",'Monthly Activity Log'!K$4:K$200,"Pending")) | F6: =IFERROR(C6/B6,0) | G6: =IFERROR(B6/'Summary Dashboard'!A7,0) | H6: =IF(B6=0,"-",IF(IF($B$3="All",COUNTIFS('Monthly Activity Log'!H$4:H$200,"PetroSA",'Monthly Activity Log'!C$4:C$200,"Shennaz"),COUNTIFS('Monthly Activity Log'!B$4:B$200,$B$3,'Monthly Activity Log'!H$4:H$200,"PetroSA",'Monthly Activity Log'!C$4:C$200,"Shennaz"))=MAX(IF($B$3="All",COUNTIFS('Monthly Activity Log'!H$4:H$200,"PetroSA",'Monthly Activity Log'!C$4:C$200,"Shennaz"),COUNTIFS('Monthly Activity Log'!B$4:B$200,$B$3,'Monthly Activity Log'!H$4:H$200,"PetroSA",'Monthly Activity Log'!C$4:C$200,"Shennaz")),IF($B$3="All",COUNTIFS('Monthly Activity Log'!H$4:H$200,"PetroSA",'Monthly Activity Log'!C$4:C$200,"Nyameka"),COUNTIFS('Monthly Activity Log'!B$4:B$200,$B$3,'Monthly Activity Log'!H$4:H$200,"PetroSA",'Monthly Activity Log'!C$4:C$200,"Nyameka")),IF($B$3="All",COUNTIFS('Monthly Activity Log'!H$4:H$200,"PetroSA",'Monthly Activity Log'!C$4:C$200,"Lindiwe"),COUNTIFS('Monthly Activity Log'!B$4:B$200,$B$3,'Monthly Activity Log'!H$4:H$200,"PetroSA",'Monthly Activity Log'!C$4:C$200,"Lindiwe")),IF($B$3="All",COUNTIFS('Monthly Activity Log'!H$4:H$200,"PetroSA",'Monthly Activity Log'!C$4:C$200,"T A Willems"),COUNTIFS('Monthly Activity Log'!B$4:B$200,$B$3,'Monthly Activity Log'!H$4:H$200,"PetroSA",'Monthly Activity Log'!C$4:C$200,"T A Willems")),IF($B$3="All",COUNTIFS('Monthly Activity Log'!H$4:H$200,"PetroSA",'Monthly Activity Log'!C$4:C$200,"Mphatheleni Matidze"),COUNTIFS('Monthly Activity Log'!B$4:B$200,$B$3,'Monthly Activity Log'!H$4:H$200,"PetroSA",'Monthly Activity Log'!C$4:C$200,"Mphatheleni Matidze"))),"Shennaz",IF(IF($B$3="All",COUNTIFS('Monthly Activity Log'!H$4:H$200,"PetroSA",'Monthly Activity Log'!C$4:C$200,"Nyameka"),COUNTIFS('Monthly Activity Log'!B$4:B$200,$B$3,'Monthly Activity Log'!H$4:H$200,"PetroSA",'Monthly Activity Log'!C$4:C$200,"Nyameka"))=MAX(IF($B$3="All",COUNTIFS('Monthly Activity Log'!H$4:H$200,"PetroSA",'Monthly Activity Log'!C$4:C$200,"Shennaz"),COUNTIFS('Monthly Activity Log'!B$4:B$200,$B$3,'Monthly Activity Log'!H$4:H$200,"PetroSA",'Monthly Activity Log'!C$4:C$200,"Shennaz")),IF($B$3="All",COUNTIFS('Monthly Activity Log'!H$4:H$200,"PetroSA",'Monthly Activity Log'!C$4:C$200,"Nyameka"),COUNTIFS('Monthly Activity Log'!B$4:B$200,$B$3,'Monthly Activity Log'!H$4:H$200,"PetroSA",'Monthly Activity Log'!C$4:C$200,"Nyameka")),IF($B$3="All",COUNTIFS('Monthly Activity Log'!H$4:H$200,"PetroSA",'Monthly Activity Log'!C$4:C$200,"Lindiwe"),COUNTIFS('Monthly Activity Log'!B$4:B$200,$B$3,'Monthly Activity Log'!H$4:H$200,"PetroSA",'Monthly Activity Log'!C$4:C$200,"Lindiwe")),IF($B$3="All",COUNTIFS('Monthly Activity Log'!H$4:H$200,"PetroSA",'Monthly Activity Log'!C$4:C$200,"T A Willems"),COUNTIFS('Monthly Activity Log'!B$4:B$200,$B$3,'Monthly Activity Log'!H$4:H$200,"PetroSA",'Monthly Activity Log'!C$4:C$200,"T A Willems")),IF($B$3="All",COUNTIFS('Monthly Activity Log'!H$4:H$200,"PetroSA",'Monthly Activity Log'!C$4:C$200,"Mphatheleni Matidze"),COUNTIFS('Monthly Activity Log'!B$4:B$200,$B$3,'Monthly Activity Log'!H$4:H$200,"PetroSA",'Monthly Activity Log'!C$4:C$200,"Mphatheleni Matidze"))),"Nyameka",IF(IF($B$3="All",COUNTIFS('Monthly Activity Log'!H$4:H$200,"PetroSA",'Monthly Activity Log'!C$4:C$200,"Lindiwe"),COUNTIFS('Monthly Activity Log'!B$4:B$200,$B$3,'Monthly Activity Log'!H$4:H$200,"PetroSA",'Monthly Activity Log'!C$4:C$200,"Lindiwe"))=MAX(IF($B$3="All",COUNTIFS('Monthly Activity Log'!H$4:H$200,"PetroSA",'Monthly Activity Log'!C$4:C$200,"Shennaz"),COUNTIFS('Monthly Activity Log'!B$4:B$200,$B$3,'Monthly Activity Log'!H$4:H$200,"PetroSA",'Monthly Activity Log'!C$4:C$200,"Shennaz")),IF($B$3="All",COUNTIFS('Monthly Activity Log'!H$4:H$200,"PetroSA",'Monthly Activity Log'!C$4:C$200,"Nyameka"),COUNTIFS('Monthly Activity Log'!B$4:B$200,$B$3,'Monthly Activity Log'!H$4:H$200,"PetroSA",'Monthly Activity Log'!C$4:C$200,"Nyameka")),IF($B$3="All",COUNTIFS('Monthly Activity Log'!H$4:H$200,"PetroSA",'Monthly Activity Log'!C$4:C$200,"Lindiwe"),COUNTIFS('Monthly Activity Log'!B$4:B$200,$B$3,'Monthly Activity Log'!H$4:H$200,"PetroSA",'Monthly Activity Log'!C$4:C$200,"Lindiwe")),IF($B$3="All",COUNTIFS('Monthly Activity Log'!H$4:H$200,"PetroSA",'Monthly Activity Log'!C$4:C$200,"T A Willems"),COUNTIFS('Monthly Activity Log'!B$4:B$200,$B$3,'Monthly Activity Log'!H$4:H$200,"PetroSA",'Monthly Activity Log'!C$4:C$200,"T A Willems")),IF($B$3="All",COUNTIFS('Monthly Activity Log'!H$4:H$200,"PetroSA",'Monthly Activity Log'!C$4:C$200,"Mphatheleni Matidze"),COUNTIFS('Monthly Activity Log'!B$4:B$200,$B$3,'Monthly Activity Log'!H$4:H$200,"PetroSA",'Monthly Activity Log'!C$4:C$200,"Mphatheleni Matidze"))),"Lindiwe",IF(IF($B$3="All",COUNTIFS('Monthly Activity Log'!H$4:H$200,"PetroSA",'Monthly Activity Log'!C$4:C$200,"T A Willems"),COUNTIFS('Monthly Activity Log'!B$4:B$200,$B$3,'Monthly Activity Log'!H$4:H$200,"PetroSA",'Monthly Activity Log'!C$4:C$200,"T A Willems"))=MAX(IF($B$3="All",COUNTIFS('Monthly Activity Log'!H$4:H$200,"PetroSA",'Monthly Activity Log'!C$4:C$200,"Shennaz"),COUNTIFS('Monthly Activity Log'!B$4:B$200,$B$3,'Monthly Activity Log'!H$4:H$200,"PetroSA",'Monthly Activity Log'!C$4:C$200,"Shennaz")),IF($B$3="All",COUNTIFS('Monthly Activity Log'!H$4:H$200,"PetroSA",'Monthly Activity Log'!C$4:C$200,"Nyameka"),COUNTIFS('Monthly Activity Log'!B$4:B$200,$B$3,'Monthly Activity Log'!H$4:H$200,"PetroSA",'Monthly Activity Log'!C$4:C$200,"Nyameka")),IF($B$3="All",COUNTIFS('Monthly Activity Log'!H$4:H$200,"PetroSA",'Monthly Activity Log'!C$4:C$200,"Lindiwe"),COUNTIFS('Monthly Activity Log'!B$4:B$200,$B$3,'Monthly Activity Log'!H$4:H$200,"PetroSA",'Monthly Activity Log'!C$4:C$200,"Lindiwe")),IF($B$3="All",COUNTIFS('Monthly Activity Log'!H$4:H$200,"PetroSA",'Monthly Activity Log'!C$4:C$200,"T A Willems"),COUNTIFS('Monthly Activity Log'!B$4:B$200,$B$3,'Monthly Activity Log'!H$4:H$200,"PetroSA",'Monthly Activity Log'!C$4:C$200,"T A Willems")),IF($B$3="All",COUNTIFS('Monthly Activity Log'!H$4:H$200,"PetroSA",'Monthly Activity Log'!C$4:C$200,"Mphatheleni Matidze"),COUNTIFS('Monthly Activity Log'!B$4:B$200,$B$3,'Monthly Activity Log'!H$4:H$200,"PetroSA",'Monthly Activity Log'!C$4:C$200,"Mphatheleni Matidze"))),"T A Willems",IF(IF($B$3="All",COUNTIFS('Monthly Activity Log'!H$4:H$200,"PetroSA",'Monthly Activity Log'!C$4:C$200,"Mphatheleni Matidze"),COUNTIFS('Monthly Activity Log'!B$4:B$200,$B$3,'Monthly Activity Log'!H$4:H$200,"PetroSA",'Monthly Activity Log'!C$4:C$200,"Mphatheleni Matidze"))=MAX(IF($B$3="All",COUNTIFS('Monthly Activity Log'!H$4:H$200,"PetroSA",'Monthly Activity Log'!C$4:C$200,"Shennaz"),COUNTIFS('Monthly Activity Log'!B$4:B$200,$B$3,'Monthly Activity Log'!H$4:H$200,"PetroSA",'Monthly Activity Log'!C$4:C$200,"Shennaz")),IF($B$3="All",COUNTIFS('Monthly Activity Log'!H$4:H$200,"PetroSA",'Monthly Activity Log'!C$4:C$200,"Nyameka"),COUNTIFS('Monthly Activity Log'!B$4:B$200,$B$3,'Monthly Activity Log'!H$4:H$200,"PetroSA",'Monthly Activity Log'!C$4:C$200,"Nyameka")),IF($B$3="All",COUNTIFS('Monthly Activity Log'!H$4:H$200,"PetroSA",'Monthly Activity Log'!C$4:C$200,"Lindiwe"),COUNTIFS('Monthly Activity Log'!B$4:B$200,$B$3,'Monthly Activity Log'!H$4:H$200,"PetroSA",'Monthly Activity Log'!C$4:C$200,"Lindiwe")),IF($B$3="All",COUNTIFS('Monthly Activity Log'!H$4:H$200,"PetroSA",'Monthly Activity Log'!C$4:C$200,"T A Willems"),COUNTIFS('Monthly Activity Log'!B$4:B$200,$B$3,'Monthly Activity Log'!H$4:H$200,"PetroSA",'Monthly Activity Log'!C$4:C$200,"T A Willems")),IF($B$3="All",COUNTIFS('Monthly Activity Log'!H$4:H$200,"PetroSA",'Monthly Activity Log'!C$4:C$200,"Mphatheleni Matidze"),COUNTIFS('Monthly Activity Log'!B$4:B$200,$B$3,'Monthly Activity Log'!H$4:H$200,"PetroSA",'Monthly Activity Log'!C$4:C$200,"Mphatheleni Matidze"))),"Mphatheleni Matidze","-")))))) | I6: =IF(B6=0,"-",IF(IF($B$3="All",COUNTIFS('Monthly Activity Log'!H$4:H$200,"PetroSA",'Monthly Activity Log'!I$4:I$200,"Project"),COUNTIFS('Monthly Activity Log'!B$4:B$200,$B$3,'Monthly Activity Log'!H$4:H$200,"PetroSA",'Monthly Activity Log'!I$4:I$200,"Project"))=MAX(IF($B$3="All",COUNTIFS('Monthly Activity Log'!H$4:H$200,"PetroSA",'Monthly Activity Log'!I$4:I$200,"Project"),COUNTIFS('Monthly Activity Log'!B$4:B$200,$B$3,'Monthly Activity Log'!H$4:H$200,"PetroSA",'Monthly Activity Log'!I$4:I$200,"Project")),IF($B$3="All",COUNTIFS('Monthly Activity Log'!H$4:H$200,"PetroSA",'Monthly Activity Log'!I$4:I$200,"Incident/Bug Fix"),COUNTIFS('Monthly Activity Log'!B$4:B$200,$B$3,'Monthly Activity Log'!H$4:H$200,"PetroSA",'Monthly Activity Log'!I$4:I$200,"Incident/Bug Fix")),IF($B$3="All",COUNTIFS('Monthly Activity Log'!H$4:H$200,"PetroSA",'Monthly Activity Log'!I$4:I$200,"Change Request"),COUNTIFS('Monthly Activity Log'!B$4:B$200,$B$3,'Monthly Activity Log'!H$4:H$200,"PetroSA",'Monthly Activity Log'!I$4:I$200,"Change Request")),IF($B$3="All",COUNTIFS('Monthly Activity Log'!H$4:H$200,"PetroSA",'Monthly Activity Log'!I$4:I$200,"User Support"),COUNTIFS('Monthly Activity Log'!B$4:B$200,$B$3,'Monthly Activity Log'!H$4:H$200,"PetroSA",'Monthly Activity Log'!I$4:I$200,"User Support")),IF($B$3="All",COUNTIFS('Monthly Activity Log'!H$4:H$200,"PetroSA",'Monthly Activity Log'!I$4:I$200,"Admin/Config"),COUNTIFS('Monthly Activity Log'!B$4:B$200,$B$3,'Monthly Activity Log'!H$4:H$200,"PetroSA",'Monthly Activity Log'!I$4:I$200,"Admin/Config")),IF($B$3="All",COUNTIFS('Monthly Activity Log'!H$4:H$200,"PetroSA",'Monthly Activity Log'!I$4:I$200,"Reporting"),COUNTIFS('Monthly Activity Log'!B$4:B$200,$B$3,'Monthly Activity Log'!H$4:H$200,"PetroSA",'Monthly Activity Log'!I$4:I$200,"Reporting")),IF($B$3="All",COUNTIFS('Monthly Activity Log'!H$4:H$200,"PetroSA",'Monthly Activity Log'!I$4:I$200,"Mentoring"),COUNTIFS('Monthly Activity Log'!B$4:B$200,$B$3,'Monthly Activity Log'!H$4:H$200,"PetroSA",'Monthly Activity Log'!I$4:I$200,"Mentoring")),IF($B$3="All",COUNTIFS('Monthly Activity Log'!H$4:H$200,"PetroSA",'Monthly Activity Log'!I$4:I$200,"Other"),COUNTIFS('Monthly Activity Log'!B$4:B$200,$B$3,'Monthly Activity Log'!H$4:H$200,"PetroSA",'Monthly Activity Log'!I$4:I$200,"Other"))),"Project",IF(IF($B$3="All",COUNTIFS('Monthly Activity Log'!H$4:H$200,"PetroSA",'Monthly Activity Log'!I$4:I$200,"Incident/Bug Fix"),COUNTIFS('Monthly Activity Log'!B$4:B$200,$B$3,'Monthly Activity Log'!H$4:H$200,"PetroSA",'Monthly Activity Log'!I$4:I$200,"Incident/Bug Fix"))=MAX(IF($B$3="All",COUNTIFS('Monthly Activity Log'!H$4:H$200,"PetroSA",'Monthly Activity Log'!I$4:I$200,"Project"),COUNTIFS('Monthly Activity Log'!B$4:B$200,$B$3,'Monthly Activity Log'!H$4:H$200,"PetroSA",'Monthly Activity Log'!I$4:I$200,"Project")),IF($B$3="All",COUNTIFS('Monthly Activity Log'!H$4:H$200,"PetroSA",'Monthly Activity Log'!I$4:I$200,"Incident/Bug Fix"),COUNTIFS('Monthly Activity Log'!B$4:B$200,$B$3,'Monthly Activity Log'!H$4:H$200,"PetroSA",'Monthly Activity Log'!I$4:I$200,"Incident/Bug Fix")),IF($B$3="All",COUNTIFS('Monthly Activity Log'!H$4:H$200,"PetroSA",'Monthly Activity Log'!I$4:I$200,"Change Request"),COUNTIFS('Monthly Activity Log'!B$4:B$200,$B$3,'Monthly Activity Log'!H$4:H$200,"PetroSA",'Monthly Activity Log'!I$4:I$200,"Change Request")),IF($B$3="All",COUNTIFS('Monthly Activity Log'!H$4:H$200,"PetroSA",'Monthly Activity Log'!I$4:I$200,"User Support"),COUNTIFS('Monthly Activity Log'!B$4:B$200,$B$3,'Monthly Activity Log'!H$4:H$200,"PetroSA",'Monthly Activity Log'!I$4:I$200,"User Support")),IF($B$3="All",COUNTIFS('Monthly Activity Log'!H$4:H$200,"PetroSA",'Monthly Activity Log'!I$4:I$200,"Admin/Config"),COUNTIFS('Monthly Activity Log'!B$4:B$200,$B$3,'Monthly Activity Log'!H$4:H$200,"PetroSA",'Monthly Activity Log'!I$4:I$200,"Admin/Config")),IF($B$3="All",COUNTIFS('Monthly Activity Log'!H$4:H$200,"PetroSA",'Monthly Activity Log'!I$4:I$200,"Reporting"),COUNTIFS('Monthly Activity Log'!B$4:B$200,$B$3,'Monthly Activity Log'!H$4:H$200,"PetroSA",'Monthly Activity Log'!I$4:I$200,"Reporting")),IF($B$3="All",COUNTIFS('Monthly Activity Log'!H$4:H$200,"PetroSA",'Monthly Activity Log'!I$4:I$200,"Mentoring"),COUNTIFS('Monthly Activity Log'!B$4:B$200,$B$3,'Monthly Activity Log'!H$4:H$200,"PetroSA",'Monthly Activity Log'!I$4:I$200,"Mentoring")),IF($B$3="All",COUNTIFS('Monthly Activity Log'!H$4:H$200,"PetroSA",'Monthly Activity Log'!I$4:I$200,"Other"),COUNTIFS('Monthly Activity Log'!B$4:B$200,$B$3,'Monthly Activity Log'!H$4:H$200,"PetroSA",'Monthly Activity Log'!I$4:I$200,"Other"))),"Incident/Bug Fix",IF(IF($B$3="All",COUNTIFS('Monthly Activity Log'!H$4:H$200,"PetroSA",'Monthly Activity Log'!I$4:I$200,"Change Request"),COUNTIFS('Monthly Activity Log'!B$4:B$200,$B$3,'Monthly Activity Log'!H$4:H$200,"PetroSA",'Monthly Activity Log'!I$4:I$200,"Change Request"))=MAX(IF($B$3="All",COUNTIFS('Monthly Activity Log'!H$4:H$200,"PetroSA",'Monthly Activity Log'!I$4:I$200,"Project"),COUNTIFS('Monthly Activity Log'!B$4:B$200,$B$3,'Monthly Activity Log'!H$4:H$200,"PetroSA",'Monthly Activity Log'!I$4:I$200,"Project")),IF($B$3="All",COUNTIFS('Monthly Activity Log'!H$4:H$200,"PetroSA",'Monthly Activity Log'!I$4:I$200,"Incident/Bug Fix"),COUNTIFS('Monthly Activity Log'!B$4:B$200,$B$3,'Monthly Activity Log'!H$4:H$200,"PetroSA",'Monthly Activity Log'!I$4:I$200,"Incident/Bug Fix")),IF($B$3="All",COUNTIFS('Monthly Activity Log'!H$4:H$200,"PetroSA",'Monthly Activity Log'!I$4:I$200,"Change Request"),COUNTIFS('Monthly Activity Log'!B$4:B$200,$B$3,'Monthly Activity Log'!H$4:H$200,"PetroSA",'Monthly Activity Log'!I$4:I$200,"Change Request")),IF($B$3="All",COUNTIFS('Monthly Activity Log'!H$4:H$200,"PetroSA",'Monthly Activity Log'!I$4:I$200,"User Support"),COUNTIFS('Monthly Activity Log'!B$4:B$200,$B$3,'Monthly Activity Log'!H$4:H$200,"PetroSA",'Monthly Activity Log'!I$4:I$200,"User Support")),IF($B$3="All",COUNTIFS('Monthly Activity Log'!H$4:H$200,"PetroSA",'Monthly Activity Log'!I$4:I$200,"Admin/Config"),COUNTIFS('Monthly Activity Log'!B$4:B$200,$B$3,'Monthly Activity Log'!H$4:H$200,"PetroSA",'Monthly Activity Log'!I$4:I$200,"Admin/Config")),IF($B$3="All",COUNTIFS('Monthly Activity Log'!H$4:H$200,"PetroSA",'Monthly Activity Log'!I$4:I$200,"Reporting"),COUNTIFS('Monthly Activity Log'!B$4:B$200,$B$3,'Monthly Activity Log'!H$4:H$200,"PetroSA",'Monthly Activity Log'!I$4:I$200,"Reporting")),IF($B$3="All",COUNTIFS('Monthly Activity Log'!H$4:H$200,"PetroSA",'Monthly Activity Log'!I$4:I$200,"Mentoring"),COUNTIFS('Monthly Activity Log'!B$4:B$200,$B$3,'Monthly Activity Log'!H$4:H$200,"PetroSA",'Monthly Activity Log'!I$4:I$200,"Mentoring")),IF($B$3="All",COUNTIFS('Monthly Activity Log'!H$4:H$200,"PetroSA",'Monthly Activity Log'!I$4:I$200,"Other"),COUNTIFS('Monthly Activity Log'!B$4:B$200,$B$3,'Monthly Activity Log'!H$4:H$200,"PetroSA",'Monthly Activity Log'!I$4:I$200,"Other"))),"Change Request",IF(IF($B$3="All",COUNTIFS('Monthly Activity Log'!H$4:H$200,"PetroSA",'Monthly Activity Log'!I$4:I$200,"User Support"),COUNTIFS('Monthly Activity Log'!B$4:B$200,$B$3,'Monthly Activity Log'!H$4:H$200,"PetroSA",'Monthly Activity Log'!I$4:I$200,"User Support"))=MAX(IF($B$3="All",COUNTIFS('Monthly Activity Log'!H$4:H$200,"PetroSA",'Monthly Activity Log'!I$4:I$200,"Project"),COUNTIFS('Monthly Activity Log'!B$4:B$200,$B$3,'Monthly Activity Log'!H$4:H$200,"PetroSA",'Monthly Activity Log'!I$4:I$200,"Project")),IF($B$3="All",COUNTIFS('Monthly Activity Log'!H$4:H$200,"PetroSA",'Monthly Activity Log'!I$4:I$200,"Incident/Bug Fix"),COUNTIFS('Monthly Activity Log'!B$4:B$200,$B$3,'Monthly Activity Log'!H$4:H$200,"PetroSA",'Monthly Activity Log'!I$4:I$200,"Incident/Bug Fix")),IF($B$3="All",COUNTIFS('Monthly Activity Log'!H$4:H$200,"PetroSA",'Monthly Activity Log'!I$4:I$200,"Change Request"),COUNTIFS('Monthly Activity Log'!B$4:B$200,$B$3,'Monthly Activity Log'!H$4:H$200,"PetroSA",'Monthly Activity Log'!I$4:I$200,"Change Request")),IF($B$3="All",COUNTIFS('Monthly Activity Log'!H$4:H$200,"PetroSA",'Monthly Activity Log'!I$4:I$200,"User Support"),COUNTIFS('Monthly Activity Log'!B$4:B$200,$B$3,'Monthly Activity Log'!H$4:H$200,"PetroSA",'Monthly Activity Log'!I$4:I$200,"User Support")),IF($B$3="All",COUNTIFS('Monthly Activity Log'!H$4:H$200,"PetroSA",'Monthly Activity Log'!I$4:I$200,"Admin/Config"),COUNTIFS('Monthly Activity Log'!B$4:B$200,$B$3,'Monthly Activity Log'!H$4:H$200,"PetroSA",'Monthly Activity Log'!I$4:I$200,"Admin/Config")),IF($B$3="All",COUNTIFS('Monthly Activity Log'!H$4:H$200,"PetroSA",'Monthly Activity Log'!I$4:I$200,"Reporting"),COUNTIFS('Monthly Activity Log'!B$4:B$200,$B$3,'Monthly Activity Log'!H$4:H$200,"PetroSA",'Monthly Activity Log'!I$4:I$200,"Reporting")),IF($B$3="All",COUNTIFS('Monthly Activity Log'!H$4:H$200,"PetroSA",'Monthly Activity Log'!I$4:I$200,"Mentoring"),COUNTIFS('Monthly Activity Log'!B$4:B$200,$B$3,'Monthly Activity Log'!H$4:H$200,"PetroSA",'Monthly Activity Log'!I$4:I$200,"Mentoring")),IF($B$3="All",COUNTIFS('Monthly Activity Log'!H$4:H$200,"PetroSA",'Monthly Activity Log'!I$4:I$200,"Other"),COUNTIFS('Monthly Activity Log'!B$4:B$200,$B$3,'Monthly Activity Log'!H$4:H$200,"PetroSA",'Monthly Activity Log'!I$4:I$200,"Other"))),"User Support",IF(IF($B$3="All",COUNTIFS('Monthly Activity Log'!H$4:H$200,"PetroSA",'Monthly Activity Log'!I$4:I$200,"Admin/Config"),COUNTIFS('Monthly Activity Log'!B$4:B$200,$B$3,'Monthly Activity Log'!H$4:H$200,"PetroSA",'Monthly Activity Log'!I$4:I$200,"Admin/Config"))=MAX(IF($B$3="All",COUNTIFS('Monthly Activity Log'!H$4:H$200,"PetroSA",'Monthly Activity Log'!I$4:I$200,"Project"),COUNTIFS('Monthly Activity Log'!B$4:B$200,$B$3,'Monthly Activity Log'!H$4:H$200,"PetroSA",'Monthly Activity Log'!I$4:I$200,"Project")),IF($B$3="All",COUNTIFS('Monthly Activity Log'!H$4:H$200,"PetroSA",'Monthly Activity Log'!I$4:I$200,"Incident/Bug Fix"),COUNTIFS('Monthly Activity Log'!B$4:B$200,$B$3,'Monthly Activity Log'!H$4:H$200,"PetroSA",'Monthly Activity Log'!I$4:I$200,"Incident/Bug Fix")),IF($B$3="All",COUNTIFS('Monthly Activity Log'!H$4:H$200,"PetroSA",'Monthly Activity Log'!I$4:I$200,"Change Request"),COUNTIFS('Monthly Activity Log'!B$4:B$200,$B$3,'Monthly Activity Log'!H$4:H$200,"PetroSA",'Monthly Activity Log'!I$4:I$200,"Change Request")),IF($B$3="All",COUNTIFS('Monthly Activity Log'!H$4:H$200,"PetroSA",'Monthly Activity Log'!I$4:I$200,"User Support"),COUNTIFS('Monthly Activity Log'!B$4:B$200,$B$3,'Monthly Activity Log'!H$4:H$200,"PetroSA",'Monthly Activity Log'!I$4:I$200,"User Support")),IF($B$3="All",COUNTIFS('Monthly Activity Log'!H$4:H$200,"PetroSA",'Monthly Activity Log'!I$4:I$200,"Admin/Config"),COUNTIFS('Monthly Activity Log'!B$4:B$200,$B$3,'Monthly Activity Log'!H$4:H$200,"PetroSA",'Monthly Activity Log'!I$4:I$200,"Admin/Config")),IF($B$3="All",COUNTIFS('Monthly Activity Log'!H$4:H$200,"PetroSA",'Monthly Activity Log'!I$4:I$200,"Reporting"),COUNTIFS('Monthly Activity Log'!B$4:B$200,$B$3,'Monthly Activity Log'!H$4:H$200,"PetroSA",'Monthly Activity Log'!I$4:I$200,"Reporting")),IF($B$3="All",COUNTIFS('Monthly Activity Log'!H$4:H$200,"PetroSA",'Monthly Activity Log'!I$4:I$200,"Mentoring"),COUNTIFS('Monthly Activity Log'!B$4:B$200,$B$3,'Monthly Activity Log'!H$4:H$200,"PetroSA",'Monthly Activity Log'!I$4:I$200,"Mentoring")),IF($B$3="All",COUNTIFS('Monthly Activity Log'!H$4:H$200,"PetroSA",'Monthly Activity Log'!I$4:I$200,"Other"),COUNTIFS('Monthly Activity Log'!B$4:B$200,$B$3,'Monthly Activity Log'!H$4:H$200,"PetroSA",'Monthly Activity Log'!I$4:I$200,"Other"))),"Admin/Config",IF(IF($B$3="All",COUNTIFS('Monthly Activity Log'!H$4:H$200,"PetroSA",'Monthly Activity Log'!I$4:I$200,"Reporting"),COUNTIFS('Monthly Activity Log'!B$4:B$200,$B$3,'Monthly Activity Log'!H$4:H$200,"PetroSA",'Monthly Activity Log'!I$4:I$200,"Reporting"))=MAX(IF($B$3="All",COUNTIFS('Monthly Activity Log'!H$4:H$200,"PetroSA",'Monthly Activity Log'!I$4:I$200,"Project"),COUNTIFS('Monthly Activity Log'!B$4:B$200,$B$3,'Monthly Activity Log'!H$4:H$200,"PetroSA",'Monthly Activity Log'!I$4:I$200,"Project")),IF($B$3="All",COUNTIFS('Monthly Activity Log'!H$4:H$200,"PetroSA",'Monthly Activity Log'!I$4:I$200,"Incident/Bug Fix"),COUNTIFS('Monthly Activity Log'!B$4:B$200,$B$3,'Monthly Activity Log'!H$4:H$200,"PetroSA",'Monthly Activity Log'!I$4:I$200,"Incident/Bug Fix")),IF($B$3="All",COUNTIFS('Monthly Activity Log'!H$4:H$200,"PetroSA",'Monthly Activity Log'!I$4:I$200,"Change Request"),COUNTIFS('Monthly Activity Log'!B$4:B$200,$B$3,'Monthly Activity Log'!H$4:H$200,"PetroSA",'Monthly Activity Log'!I$4:I$200,"Change Request")),IF($B$3="All",COUNTIFS('Monthly Activity Log'!H$4:H$200,"PetroSA",'Monthly Activity Log'!I$4:I$200,"User Support"),COUNTIFS('Monthly Activity Log'!B$4:B$200,$B$3,'Monthly Activity Log'!H$4:H$200,"PetroSA",'Monthly Activity Log'!I$4:I$200,"User Support")),IF($B$3="All",COUNTIFS('Monthly Activity Log'!H$4:H$200,"PetroSA",'Monthly Activity Log'!I$4:I$200,"Admin/Config"),COUNTIFS('Monthly Activity Log'!B$4:B$200,$B$3,'Monthly Activity Log'!H$4:H$200,"PetroSA",'Monthly Activity Log'!I$4:I$200,"Admin/Config")),IF($B$3="All",COUNTIFS('Monthly Activity Log'!H$4:H$200,"PetroSA",'Monthly Activity Log'!I$4:I$200,"Reporting"),COUNTIFS('Monthly Activity Log'!B$4:B$200,$B$3,'Monthly Activity Log'!H$4:H$200,"PetroSA",'Monthly Activity Log'!I$4:I$200,"Reporting")),IF($B$3="All",COUNTIFS('Monthly Activity Log'!H$4:H$200,"PetroSA",'Monthly Activity Log'!I$4:I$200,"Mentoring"),COUNTIFS('Monthly Activity Log'!B$4:B$200,$B$3,'Monthly Activity Log'!H$4:H$200,"PetroSA",'Monthly Activity Log'!I$4:I$200,"Mentoring")),IF($B$3="All",COUNTIFS('Monthly Activity Log'!H$4:H$200,"PetroSA",'Monthly Activity Log'!I$4:I$200,"Other"),COUNTIFS('Monthly Activity Log'!B$4:B$200,$B$3,'Monthly Activity Log'!H$4:H$200,"PetroSA",'Monthly Activity Log'!I$4:I$200,"Other"))),"Reporting",IF(IF($B$3="All",COUNTIFS('Monthly Activity Log'!H$4:H$200,"PetroSA",'Monthly Activity Log'!I$4:I$200,"Mentoring"),COUNTIFS('Monthly Activity Log'!B$4:B$200,$B$3,'Monthly Activity Log'!H$4:H$200,"PetroSA",'Monthly Activity Log'!I$4:I$200,"Mentoring"))=MAX(IF($B$3="All",COUNTIFS('Monthly Activity Log'!H$4:H$200,"PetroSA",'Monthly Activity Log'!I$4:I$200,"Project"),COUNTIFS('Monthly Activity Log'!B$4:B$200,$B$3,'Monthly Activity Log'!H$4:H$200,"PetroSA",'Monthly Activity Log'!I$4:I$200,"Project")),IF($B$3="All",COUNTIFS('Monthly Activity Log'!H$4:H$200,"PetroSA",'Monthly Activity Log'!I$4:I$200,"Incident/Bug Fix"),COUNTIFS('Monthly Activity Log'!B$4:B$200,$B$3,'Monthly Activity Log'!H$4:H$200,"PetroSA",'Monthly Activity Log'!I$4:I$200,"Incident/Bug Fix")),IF($B$3="All",COUNTIFS('Monthly Activity Log'!H$4:H$200,"PetroSA",'Monthly Activity Log'!I$4:I$200,"Change Request"),COUNTIFS('Monthly Activity Log'!B$4:B$200,$B$3,'Monthly Activity Log'!H$4:H$200,"PetroSA",'Monthly Activity Log'!I$4:I$200,"Change Request")),IF($B$3="All",COUNTIFS('Monthly Activity Log'!H$4:H$200,"PetroSA",'Monthly Activity Log'!I$4:I$200,"User Support"),COUNTIFS('Monthly Activity Log'!B$4:B$200,$B$3,'Monthly Activity Log'!H$4:H$200,"PetroSA",'Monthly Activity Log'!I$4:I$200,"User Support")),IF($B$3="All",COUNTIFS('Monthly Activity Log'!H$4:H$200,"PetroSA",'Monthly Activity Log'!I$4:I$200,"Admin/Config"),COUNTIFS('Monthly Activity Log'!B$4:B$200,$B$3,'Monthly Activity Log'!H$4:H$200,"PetroSA",'Monthly Activity Log'!I$4:I$200,"Admin/Config")),IF($B$3="All",COUNTIFS('Monthly Activity Log'!H$4:H$200,"PetroSA",'Monthly Activity Log'!I$4:I$200,"Reporting"),COUNTIFS('Monthly Activity Log'!B$4:B$200,$B$3,'Monthly Activity Log'!H$4:H$200,"PetroSA",'Monthly Activity Log'!I$4:I$200,"Reporting")),IF($B$3="All",COUNTIFS('Monthly Activity Log'!H$4:H$200,"PetroSA",'Monthly Activity Log'!I$4:I$200,"Mentoring"),COUNTIFS('Monthly Activity Log'!B$4:B$200,$B$3,'Monthly Activity Log'!H$4:H$200,"PetroSA",'Monthly Activity Log'!I$4:I$200,"Mentoring")),IF($B$3="All",COUNTIFS('Monthly Activity Log'!H$4:H$200,"PetroSA",'Monthly Activity Log'!I$4:I$200,"Other"),COUNTIFS('Monthly Activity Log'!B$4:B$200,$B$3,'Monthly Activity Log'!H$4:H$200,"PetroSA",'Monthly Activity Log'!I$4:I$200,"Other"))),"Mentoring",IF(IF($B$3="All",COUNTIFS('Monthly Activity Log'!H$4:H$200,"PetroSA",'Monthly Activity Log'!I$4:I$200,"Other"),COUNTIFS('Monthly Activity Log'!B$4:B$200,$B$3,'Monthly Activity Log'!H$4:H$200,"PetroSA",'Monthly Activity Log'!I$4:I$200,"Other"))=MAX(IF($B$3="All",COUNTIFS('Monthly Activity Log'!H$4:H$200,"PetroSA",'Monthly Activity Log'!I$4:I$200,"Project"),COUNTIFS('Monthly Activity Log'!B$4:B$200,$B$3,'Monthly Activity Log'!H$4:H$200,"PetroSA",'Monthly Activity Log'!I$4:I$200,"Project")),IF($B$3="All",COUNTIFS('Monthly Activity Log'!H$4:H$200,"PetroSA",'Monthly Activity Log'!I$4:I$200,"Incident/Bug Fix"),COUNTIFS('Monthly Activity Log'!B$4:B$200,$B$3,'Monthly Activity Log'!H$4:H$200,"PetroSA",'Monthly Activity Log'!I$4:I$200,"Incident/Bug Fix")),IF($B$3="All",COUNTIFS('Monthly Activity Log'!H$4:H$200,"PetroSA",'Monthly Activity Log'!I$4:I$200,"Change Request"),COUNTIFS('Monthly Activity Log'!B$4:B$200,$B$3,'Monthly Activity Log'!H$4:H$200,"PetroSA",'Monthly Activity Log'!I$4:I$200,"Change Request")),IF($B$3="All",COUNTIFS('Monthly Activity Log'!H$4:H$200,"PetroSA",'Monthly Activity Log'!I$4:I$200,"User Support"),COUNTIFS('Monthly Activity Log'!B$4:B$200,$B$3,'Monthly Activity Log'!H$4:H$200,"PetroSA",'Monthly Activity Log'!I$4:I$200,"User Support")),IF($B$3="All",COUNTIFS('Monthly Activity Log'!H$4:H$200,"PetroSA",'Monthly Activity Log'!I$4:I$200,"Admin/Config"),COUNTIFS('Monthly Activity Log'!B$4:B$200,$B$3,'Monthly Activity Log'!H$4:H$200,"PetroSA",'Monthly Activity Log'!I$4:I$200,"Admin/Config")),IF($B$3="All",COUNTIFS('Monthly Activity Log'!H$4:H$200,"PetroSA",'Monthly Activity Log'!I$4:I$200,"Reporting"),COUNTIFS('Monthly Activity Log'!B$4:B$200,$B$3,'Monthly Activity Log'!H$4:H$200,"PetroSA",'Monthly Activity Log'!I$4:I$200,"Reporting")),IF($B$3="All",COUNTIFS('Monthly Activity Log'!H$4:H$200,"PetroSA",'Monthly Activity Log'!I$4:I$200,"Mentoring"),COUNTIFS('Monthly Activity Log'!B$4:B$200,$B$3,'Monthly Activity Log'!H$4:H$200,"PetroSA",'Monthly Activity Log'!I$4:I$200,"Mentoring")),IF($B$3="All",COUNTIFS('Monthly Activity Log'!H$4:H$200,"PetroSA",'Monthly Activity Log'!I$4:I$200,"Other"),COUNTIFS('Monthly Activity Log'!B$4:B$200,$B$3,'Monthly Activity Log'!H$4:H$200,"PetroSA",'Monthly Activity Log'!I$4:I$200,"Other"))),"Other","-"))))))))) | J6: =D6+E6
A7: PetroSA Ghana | B7: =IF($B$3="All",COUNTIF('Monthly Activity Log'!H$4:H$200,"PetroSA Ghana"),COUNTIFS('Monthly Activity Log'!B$4:B$200,$B$3,'Monthly Activity Log'!H$4:H$200,"PetroSA Ghana")) | C7: =IF($B$3="All",COUNTIFS('Monthly Activity Log'!H$4:H$200,"PetroSA Ghana",'Monthly Activity Log'!K$4:K$200,"Completed"),COUNTIFS('Monthly Activity Log'!B$4:B$200,$B$3,'Monthly Activity Log'!H$4:H$200,"PetroSA Ghana",'Monthly Activity Log'!K$4:K$200,"Completed")) | D7: =IF($B$3="All",COUNTIFS('Monthly Activity Log'!H$4:H$200,"PetroSA Ghana",'Monthly Activity Log'!K$4:K$200,"In Progress"),COUNTIFS('Monthly Activity Log'!B$4:B$200,$B$3,'Monthly Activity Log'!H$4:H$200,"PetroSA Ghana",'Monthly Activity Log'!K$4:K$200,"In Progress")) | E7: =IF($B$3="All",COUNTIFS('Monthly Activity Log'!H$4:H$200,"PetroSA Ghana",'Monthly Activity Log'!K$4:K$200,"Pending"),COUNTIFS('Monthly Activity Log'!B$4:B$200,$B$3,'Monthly Activity Log'!H$4:H$200,"PetroSA Ghana",'Monthly Activity Log'!K$4:K$200,"Pending")) | F7: =IFERROR(C7/B7,0) | G7: =IFERROR(B7/'Summary Dashboard'!A7,0) | H7: =IF(B7=0,"-",IF(IF($B$3="All",COUNTIFS('Monthly Activity Log'!H$4:H$200,"PetroSA Ghana",'Monthly Activity Log'!C$4:C$200,"Shennaz"),COUNTIFS('Monthly Activity Log'!B$4:B$200,$B$3,'Monthly Activity Log'!H$4:H$200,"PetroSA Ghana",'Monthly Activity Log'!C$4:C$200,"Shennaz"))=MAX(IF($B$3="All",COUNTIFS('Monthly Activity Log'!H$4:H$200,"PetroSA Ghana",'Monthly Activity Log'!C$4:C$200,"Shennaz"),COUNTIFS('Monthly Activity Log'!B$4:B$200,$B$3,'Monthly Activity Log'!H$4:H$200,"PetroSA Ghana",'Monthly Activity Log'!C$4:C$200,"Shennaz")),IF($B$3="All",COUNTIFS('Monthly Activity Log'!H$4:H$200,"PetroSA Ghana",'Monthly Activity Log'!C$4:C$200,"Nyameka"),COUNTIFS('Monthly Activity Log'!B$4:B$200,$B$3,'Monthly Activity Log'!H$4:H$200,"PetroSA Ghana",'Monthly Activity Log'!C$4:C$200,"Nyameka")),IF($B$3="All",COUNTIFS('Monthly Activity Log'!H$4:H$200,"PetroSA Ghana",'Monthly Activity Log'!C$4:C$200,"Lindiwe"),COUNTIFS('Monthly Activity Log'!B$4:B$200,$B$3,'Monthly Activity Log'!H$4:H$200,"PetroSA Ghana",'Monthly Activity Log'!C$4:C$200,"Lindiwe")),IF($B$3="All",COUNTIFS('Monthly Activity Log'!H$4:H$200,"PetroSA Ghana",'Monthly Activity Log'!C$4:C$200,"T A Willems"),COUNTIFS('Monthly Activity Log'!B$4:B$200,$B$3,'Monthly Activity Log'!H$4:H$200,"PetroSA Ghana",'Monthly Activity Log'!C$4:C$200,"T A Willems")),IF($B$3="All",COUNTIFS('Monthly Activity Log'!H$4:H$200,"PetroSA Ghana",'Monthly Activity Log'!C$4:C$200,"Mphatheleni Matidze"),COUNTIFS('Monthly Activity Log'!B$4:B$200,$B$3,'Monthly Activity Log'!H$4:H$200,"PetroSA Ghana",'Monthly Activity Log'!C$4:C$200,"Mphatheleni Matidze"))),"Shennaz",IF(IF($B$3="All",COUNTIFS('Monthly Activity Log'!H$4:H$200,"PetroSA Ghana",'Monthly Activity Log'!C$4:C$200,"Nyameka"),COUNTIFS('Monthly Activity Log'!B$4:B$200,$B$3,'Monthly Activity Log'!H$4:H$200,"PetroSA Ghana",'Monthly Activity Log'!C$4:C$200,"Nyameka"))=MAX(IF($B$3="All",COUNTIFS('Monthly Activity Log'!H$4:H$200,"PetroSA Ghana",'Monthly Activity Log'!C$4:C$200,"Shennaz"),COUNTIFS('Monthly Activity Log'!B$4:B$200,$B$3,'Monthly Activity Log'!H$4:H$200,"PetroSA Ghana",'Monthly Activity Log'!C$4:C$200,"Shennaz")),IF($B$3="All",COUNTIFS('Monthly Activity Log'!H$4:H$200,"PetroSA Ghana",'Monthly Activity Log'!C$4:C$200,"Nyameka"),COUNTIFS('Monthly Activity Log'!B$4:B$200,$B$3,'Monthly Activity Log'!H$4:H$200,"PetroSA Ghana",'Monthly Activity Log'!C$4:C$200,"Nyameka")),IF($B$3="All",COUNTIFS('Monthly Activity Log'!H$4:H$200,"PetroSA Ghana",'Monthly Activity Log'!C$4:C$200,"Lindiwe"),COUNTIFS('Monthly Activity Log'!B$4:B$200,$B$3,'Monthly Activity Log'!H$4:H$200,"PetroSA Ghana",'Monthly Activity Log'!C$4:C$200,"Lindiwe")),IF($B$3="All",COUNTIFS('Monthly Activity Log'!H$4:H$200,"PetroSA Ghana",'Monthly Activity Log'!C$4:C$200,"T A Willems"),COUNTIFS('Monthly Activity Log'!B$4:B$200,$B$3,'Monthly Activity Log'!H$4:H$200,"PetroSA Ghana",'Monthly Activity Log'!C$4:C$200,"T A Willems")),IF($B$3="All",COUNTIFS('Monthly Activity Log'!H$4:H$200,"PetroSA Ghana",'Monthly Activity Log'!C$4:C$200,"Mphatheleni Matidze"),COUNTIFS('Monthly Activity Log'!B$4:B$200,$B$3,'Monthly Activity Log'!H$4:H$200,"PetroSA Ghana",'Monthly Activity Log'!C$4:C$200,"Mphatheleni Matidze"))),"Nyameka",IF(IF($B$3="All",COUNTIFS('Monthly Activity Log'!H$4:H$200,"PetroSA Ghana",'Monthly Activity Log'!C$4:C$200,"Lindiwe"),COUNTIFS('Monthly Activity Log'!B$4:B$200,$B$3,'Monthly Activity Log'!H$4:H$200,"PetroSA Ghana",'Monthly Activity Log'!C$4:C$200,"Lindiwe"))=MAX(IF($B$3="All",COUNTIFS('Monthly Activity Log'!H$4:H$200,"PetroSA Ghana",'Monthly Activity Log'!C$4:C$200,"Shennaz"),COUNTIFS('Monthly Activity Log'!B$4:B$200,$B$3,'Monthly Activity Log'!H$4:H$200,"PetroSA Ghana",'Monthly Activity Log'!C$4:C$200,"Shennaz")),IF($B$3="All",COUNTIFS('Monthly Activity Log'!H$4:H$200,"PetroSA Ghana",'Monthly Activity Log'!C$4:C$200,"Nyameka"),COUNTIFS('Monthly Activity Log'!B$4:B$200,$B$3,'Monthly Activity Log'!H$4:H$200,"PetroSA Ghana",'Monthly Activity Log'!C$4:C$200,"Nyameka")),IF($B$3="All",COUNTIFS('Monthly Activity Log'!H$4:H$200,"PetroSA Ghana",'Monthly Activity Log'!C$4:C$200,"Lindiwe"),COUNTIFS('Monthly Activity Log'!B$4:B$200,$B$3,'Monthly Activity Log'!H$4:H$200,"PetroSA Ghana",'Monthly Activity Log'!C$4:C$200,"Lindiwe")),IF($B$3="All",COUNTIFS('Monthly Activity Log'!H$4:H$200,"PetroSA Ghana",'Monthly Activity Log'!C$4:C$200,"T A Willems"),COUNTIFS('Monthly Activity Log'!B$4:B$200,$B$3,'Monthly Activity Log'!H$4:H$200,"PetroSA Ghana",'Monthly Activity Log'!C$4:C$200,"T A Willems")),IF($B$3="All",COUNTIFS('Monthly Activity Log'!H$4:H$200,"PetroSA Ghana",'Monthly Activity Log'!C$4:C$200,"Mphatheleni Matidze"),COUNTIFS('Monthly Activity Log'!B$4:B$200,$B$3,'Monthly Activity Log'!H$4:H$200,"PetroSA Ghana",'Monthly Activity Log'!C$4:C$200,"Mphatheleni Matidze"))),"Lindiwe",IF(IF($B$3="All",COUNTIFS('Monthly Activity Log'!H$4:H$200,"PetroSA Ghana",'Monthly Activity Log'!C$4:C$200,"T A Willems"),COUNTIFS('Monthly Activity Log'!B$4:B$200,$B$3,'Monthly Activity Log'!H$4:H$200,"PetroSA Ghana",'Monthly Activity Log'!C$4:C$200,"T A Willems"))=MAX(IF($B$3="All",COUNTIFS('Monthly Activity Log'!H$4:H$200,"PetroSA Ghana",'Monthly Activity Log'!C$4:C$200,"Shennaz"),COUNTIFS('Monthly Activity Log'!B$4:B$200,$B$3,'Monthly Activity Log'!H$4:H$200,"PetroSA Ghana",'Monthly Activity Log'!C$4:C$200,"Shennaz")),IF($B$3="All",COUNTIFS('Monthly Activity Log'!H$4:H$200,"PetroSA Ghana",'Monthly Activity Log'!C$4:C$200,"Nyameka"),COUNTIFS('Monthly Activity Log'!B$4:B$200,$B$3,'Monthly Activity Log'!H$4:H$200,"PetroSA Ghana",'Monthly Activity Log'!C$4:C$200,"Nyameka")),IF($B$3="All",COUNTIFS('Monthly Activity Log'!H$4:H$200,"PetroSA Ghana",'Monthly Activity Log'!C$4:C$200,"Lindiwe"),COUNTIFS('Monthly Activity Log'!B$4:B$200,$B$3,'Monthly Activity Log'!H$4:H$200,"PetroSA Ghana",'Monthly Activity Log'!C$4:C$200,"Lindiwe")),IF($B$3="All",COUNTIFS('Monthly Activity Log'!H$4:H$200,"PetroSA Ghana",'Monthly Activity Log'!C$4:C$200,"T A Willems"),COUNTIFS('Monthly Activity Log'!B$4:B$200,$B$3,'Monthly Activity Log'!H$4:H$200,"PetroSA Ghana",'Monthly Activity Log'!C$4:C$200,"T A Willems")),IF($B$3="All",COUNTIFS('Monthly Activity Log'!H$4:H$200,"PetroSA Ghana",'Monthly Activity Log'!C$4:C$200,"Mphatheleni Matidze"),COUNTIFS('Monthly Activity Log'!B$4:B$200,$B$3,'Monthly Activity Log'!H$4:H$200,"PetroSA Ghana",'Monthly Activity Log'!C$4:C$200,"Mphatheleni Matidze"))),"T A Willems",IF(IF($B$3="All",COUNTIFS('Monthly Activity Log'!H$4:H$200,"PetroSA Ghana",'Monthly Activity Log'!C$4:C$200,"Mphatheleni Matidze"),COUNTIFS('Monthly Activity Log'!B$4:B$200,$B$3,'Monthly Activity Log'!H$4:H$200,"PetroSA Ghana",'Monthly Activity Log'!C$4:C$200,"Mphatheleni Matidze"))=MAX(IF($B$3="All",COUNTIFS('Monthly Activity Log'!H$4:H$200,"PetroSA Ghana",'Monthly Activity Log'!C$4:C$200,"Shennaz"),COUNTIFS('Monthly Activity Log'!B$4:B$200,$B$3,'Monthly Activity Log'!H$4:H$200,"PetroSA Ghana",'Monthly Activity Log'!C$4:C$200,"Shennaz")),IF($B$3="All",COUNTIFS('Monthly Activity Log'!H$4:H$200,"PetroSA Ghana",'Monthly Activity Log'!C$4:C$200,"Nyameka"),COUNTIFS('Monthly Activity Log'!B$4:B$200,$B$3,'Monthly Activity Log'!H$4:H$200,"PetroSA Ghana",'Monthly Activity Log'!C$4:C$200,"Nyameka")),IF($B$3="All",COUNTIFS('Monthly Activity Log'!H$4:H$200,"PetroSA Ghana",'Monthly Activity Log'!C$4:C$200,"Lindiwe"),COUNTIFS('Monthly Activity Log'!B$4:B$200,$B$3,'Monthly Activity Log'!H$4:H$200,"PetroSA Ghana",'Monthly Activity Log'!C$4:C$200,"Lindiwe")),IF($B$3="All",COUNTIFS('Monthly Activity Log'!H$4:H$200,"PetroSA Ghana",'Monthly Activity Log'!C$4:C$200,"T A Willems"),COUNTIFS('Monthly Activity Log'!B$4:B$200,$B$3,'Monthly Activity Log'!H$4:H$200,"PetroSA Ghana",'Monthly Activity Log'!C$4:C$200,"T A Willems")),IF($B$3="All",COUNTIFS('Monthly Activity Log'!H$4:H$200,"PetroSA Ghana",'Monthly Activity Log'!C$4:C$200,"Mphatheleni Matidze"),COUNTIFS('Monthly Activity Log'!B$4:B$200,$B$3,'Monthly Activity Log'!H$4:H$200,"PetroSA Ghana",'Monthly Activity Log'!C$4:C$200,"Mphatheleni Matidze"))),"Mphatheleni Matidze","-")))))) | I7: =IF(B7=0,"-",IF(IF($B$3="All",COUNTIFS('Monthly Activity Log'!H$4:H$200,"PetroSA Ghana",'Monthly Activity Log'!I$4:I$200,"Project"),COUNTIFS('Monthly Activity Log'!B$4:B$200,$B$3,'Monthly Activity Log'!H$4:H$200,"PetroSA Ghana",'Monthly Activity Log'!I$4:I$200,"Project"))=MAX(IF($B$3="All",COUNTIFS('Monthly Activity Log'!H$4:H$200,"PetroSA Ghana",'Monthly Activity Log'!I$4:I$200,"Project"),COUNTIFS('Monthly Activity Log'!B$4:B$200,$B$3,'Monthly Activity Log'!H$4:H$200,"PetroSA Ghana",'Monthly Activity Log'!I$4:I$200,"Project")),IF($B$3="All",COUNTIFS('Monthly Activity Log'!H$4:H$200,"PetroSA Ghana",'Monthly Activity Log'!I$4:I$200,"Incident/Bug Fix"),COUNTIFS('Monthly Activity Log'!B$4:B$200,$B$3,'Monthly Activity Log'!H$4:H$200,"PetroSA Ghana",'Monthly Activity Log'!I$4:I$200,"Incident/Bug Fix")),IF($B$3="All",COUNTIFS('Monthly Activity Log'!H$4:H$200,"PetroSA Ghana",'Monthly Activity Log'!I$4:I$200,"Change Request"),COUNTIFS('Monthly Activity Log'!B$4:B$200,$B$3,'Monthly Activity Log'!H$4:H$200,"PetroSA Ghana",'Monthly Activity Log'!I$4:I$200,"Change Request")),IF($B$3="All",COUNTIFS('Monthly Activity Log'!H$4:H$200,"PetroSA Ghana",'Monthly Activity Log'!I$4:I$200,"User Support"),COUNTIFS('Monthly Activity Log'!B$4:B$200,$B$3,'Monthly Activity Log'!H$4:H$200,"PetroSA Ghana",'Monthly Activity Log'!I$4:I$200,"User Support")),IF($B$3="All",COUNTIFS('Monthly Activity Log'!H$4:H$200,"PetroSA Ghana",'Monthly Activity Log'!I$4:I$200,"Admin/Config"),COUNTIFS('Monthly Activity Log'!B$4:B$200,$B$3,'Monthly Activity Log'!H$4:H$200,"PetroSA Ghana",'Monthly Activity Log'!I$4:I$200,"Admin/Config")),IF($B$3="All",COUNTIFS('Monthly Activity Log'!H$4:H$200,"PetroSA Ghana",'Monthly Activity Log'!I$4:I$200,"Reporting"),COUNTIFS('Monthly Activity Log'!B$4:B$200,$B$3,'Monthly Activity Log'!H$4:H$200,"PetroSA Ghana",'Monthly Activity Log'!I$4:I$200,"Reporting")),IF($B$3="All",COUNTIFS('Monthly Activity Log'!H$4:H$200,"PetroSA Ghana",'Monthly Activity Log'!I$4:I$200,"Mentoring"),COUNTIFS('Monthly Activity Log'!B$4:B$200,$B$3,'Monthly Activity Log'!H$4:H$200,"PetroSA Ghana",'Monthly Activity Log'!I$4:I$200,"Mentoring")),IF($B$3="All",COUNTIFS('Monthly Activity Log'!H$4:H$200,"PetroSA Ghana",'Monthly Activity Log'!I$4:I$200,"Other"),COUNTIFS('Monthly Activity Log'!B$4:B$200,$B$3,'Monthly Activity Log'!H$4:H$200,"PetroSA Ghana",'Monthly Activity Log'!I$4:I$200,"Other"))),"Project",IF(IF($B$3="All",COUNTIFS('Monthly Activity Log'!H$4:H$200,"PetroSA Ghana",'Monthly Activity Log'!I$4:I$200,"Incident/Bug Fix"),COUNTIFS('Monthly Activity Log'!B$4:B$200,$B$3,'Monthly Activity Log'!H$4:H$200,"PetroSA Ghana",'Monthly Activity Log'!I$4:I$200,"Incident/Bug Fix"))=MAX(IF($B$3="All",COUNTIFS('Monthly Activity Log'!H$4:H$200,"PetroSA Ghana",'Monthly Activity Log'!I$4:I$200,"Project"),COUNTIFS('Monthly Activity Log'!B$4:B$200,$B$3,'Monthly Activity Log'!H$4:H$200,"PetroSA Ghana",'Monthly Activity Log'!I$4:I$200,"Project")),IF($B$3="All",COUNTIFS('Monthly Activity Log'!H$4:H$200,"PetroSA Ghana",'Monthly Activity Log'!I$4:I$200,"Incident/Bug Fix"),COUNTIFS('Monthly Activity Log'!B$4:B$200,$B$3,'Monthly Activity Log'!H$4:H$200,"PetroSA Ghana",'Monthly Activity Log'!I$4:I$200,"Incident/Bug Fix")),IF($B$3="All",COUNTIFS('Monthly Activity Log'!H$4:H$200,"PetroSA Ghana",'Monthly Activity Log'!I$4:I$200,"Change Request"),COUNTIFS('Monthly Activity Log'!B$4:B$200,$B$3,'Monthly Activity Log'!H$4:H$200,"PetroSA Ghana",'Monthly Activity Log'!I$4:I$200,"Change Request")),IF($B$3="All",COUNTIFS('Monthly Activity Log'!H$4:H$200,"PetroSA Ghana",'Monthly Activity Log'!I$4:I$200,"User Support"),COUNTIFS('Monthly Activity Log'!B$4:B$200,$B$3,'Monthly Activity Log'!H$4:H$200,"PetroSA Ghana",'Monthly Activity Log'!I$4:I$200,"User Support")),IF($B$3="All",COUNTIFS('Monthly Activity Log'!H$4:H$200,"PetroSA Ghana",'Monthly Activity Log'!I$4:I$200,"Admin/Config"),COUNTIFS('Monthly Activity Log'!B$4:B$200,$B$3,'Monthly Activity Log'!H$4:H$200,"PetroSA Ghana",'Monthly Activity Log'!I$4:I$200,"Admin/Config")),IF($B$3="All",COUNTIFS('Monthly Activity Log'!H$4:H$200,"PetroSA Ghana",'Monthly Activity Log'!I$4:I$200,"Reporting"),COUNTIFS('Monthly Activity Log'!B$4:B$200,$B$3,'Monthly Activity Log'!H$4:H$200,"PetroSA Ghana",'Monthly Activity Log'!I$4:I$200,"Reporting")),IF($B$3="All",COUNTIFS('Monthly Activity Log'!H$4:H$200,"PetroSA Ghana",'Monthly Activity Log'!I$4:I$200,"Mentoring"),COUNTIFS('Monthly Activity Log'!B$4:B$200,$B$3,'Monthly Activity Log'!H$4:H$200,"PetroSA Ghana",'Monthly Activity Log'!I$4:I$200,"Mentoring")),IF($B$3="All",COUNTIFS('Monthly Activity Log'!H$4:H$200,"PetroSA Ghana",'Monthly Activity Log'!I$4:I$200,"Other"),COUNTIFS('Monthly Activity Log'!B$4:B$200,$B$3,'Monthly Activity Log'!H$4:H$200,"PetroSA Ghana",'Monthly Activity Log'!I$4:I$200,"Other"))),"Incident/Bug Fix",IF(IF($B$3="All",COUNTIFS('Monthly Activity Log'!H$4:H$200,"PetroSA Ghana",'Monthly Activity Log'!I$4:I$200,"Change Request"),COUNTIFS('Monthly Activity Log'!B$4:B$200,$B$3,'Monthly Activity Log'!H$4:H$200,"PetroSA Ghana",'Monthly Activity Log'!I$4:I$200,"Change Request"))=MAX(IF($B$3="All",COUNTIFS('Monthly Activity Log'!H$4:H$200,"PetroSA Ghana",'Monthly Activity Log'!I$4:I$200,"Project"),COUNTIFS('Monthly Activity Log'!B$4:B$200,$B$3,'Monthly Activity Log'!H$4:H$200,"PetroSA Ghana",'Monthly Activity Log'!I$4:I$200,"Project")),IF($B$3="All",COUNTIFS('Monthly Activity Log'!H$4:H$200,"PetroSA Ghana",'Monthly Activity Log'!I$4:I$200,"Incident/Bug Fix"),COUNTIFS('Monthly Activity Log'!B$4:B$200,$B$3,'Monthly Activity Log'!H$4:H$200,"PetroSA Ghana",'Monthly Activity Log'!I$4:I$200,"Incident/Bug Fix")),IF($B$3="All",COUNTIFS('Monthly Activity Log'!H$4:H$200,"PetroSA Ghana",'Monthly Activity Log'!I$4:I$200,"Change Request"),COUNTIFS('Monthly Activity Log'!B$4:B$200,$B$3,'Monthly Activity Log'!H$4:H$200,"PetroSA Ghana",'Monthly Activity Log'!I$4:I$200,"Change Request")),IF($B$3="All",COUNTIFS('Monthly Activity Log'!H$4:H$200,"PetroSA Ghana",'Monthly Activity Log'!I$4:I$200,"User Support"),COUNTIFS('Monthly Activity Log'!B$4:B$200,$B$3,'Monthly Activity Log'!H$4:H$200,"PetroSA Ghana",'Monthly Activity Log'!I$4:I$200,"User Support")),IF($B$3="All",COUNTIFS('Monthly Activity Log'!H$4:H$200,"PetroSA Ghana",'Monthly Activity Log'!I$4:I$200,"Admin/Config"),COUNTIFS('Monthly Activity Log'!B$4:B$200,$B$3,'Monthly Activity Log'!H$4:H$200,"PetroSA Ghana",'Monthly Activity Log'!I$4:I$200,"Admin/Config")),IF($B$3="All",COUNTIFS('Monthly Activity Log'!H$4:H$200,"PetroSA Ghana",'Monthly Activity Log'!I$4:I$200,"Reporting"),COUNTIFS('Monthly Activity Log'!B$4:B$200,$B$3,'Monthly Activity Log'!H$4:H$200,"PetroSA Ghana",'Monthly Activity Log'!I$4:I$200,"Reporting")),IF($B$3="All",COUNTIFS('Monthly Activity Log'!H$4:H$200,"PetroSA Ghana",'Monthly Activity Log'!I$4:I$200,"Mentoring"),COUNTIFS('Monthly Activity Log'!B$4:B$200,$B$3,'Monthly Activity Log'!H$4:H$200,"PetroSA Ghana",'Monthly Activity Log'!I$4:I$200,"Mentoring")),IF($B$3="All",COUNTIFS('Monthly Activity Log'!H$4:H$200,"PetroSA Ghana",'Monthly Activity Log'!I$4:I$200,"Other"),COUNTIFS('Monthly Activity Log'!B$4:B$200,$B$3,'Monthly Activity Log'!H$4:H$200,"PetroSA Ghana",'Monthly Activity Log'!I$4:I$200,"Other"))),"Change Request",IF(IF($B$3="All",COUNTIFS('Monthly Activity Log'!H$4:H$200,"PetroSA Ghana",'Monthly Activity Log'!I$4:I$200,"User Support"),COUNTIFS('Monthly Activity Log'!B$4:B$200,$B$3,'Monthly Activity Log'!H$4:H$200,"PetroSA Ghana",'Monthly Activity Log'!I$4:I$200,"User Support"))=MAX(IF($B$3="All",COUNTIFS('Monthly Activity Log'!H$4:H$200,"PetroSA Ghana",'Monthly Activity Log'!I$4:I$200,"Project"),COUNTIFS('Monthly Activity Log'!B$4:B$200,$B$3,'Monthly Activity Log'!H$4:H$200,"PetroSA Ghana",'Monthly Activity Log'!I$4:I$200,"Project")),IF($B$3="All",COUNTIFS('Monthly Activity Log'!H$4:H$200,"PetroSA Ghana",'Monthly Activity Log'!I$4:I$200,"Incident/Bug Fix"),COUNTIFS('Monthly Activity Log'!B$4:B$200,$B$3,'Monthly Activity Log'!H$4:H$200,"PetroSA Ghana",'Monthly Activity Log'!I$4:I$200,"Incident/Bug Fix")),IF($B$3="All",COUNTIFS('Monthly Activity Log'!H$4:H$200,"PetroSA Ghana",'Monthly Activity Log'!I$4:I$200,"Change Request"),COUNTIFS('Monthly Activity Log'!B$4:B$200,$B$3,'Monthly Activity Log'!H$4:H$200,"PetroSA Ghana",'Monthly Activity Log'!I$4:I$200,"Change Request")),IF($B$3="All",COUNTIFS('Monthly Activity Log'!H$4:H$200,"PetroSA Ghana",'Monthly Activity Log'!I$4:I$200,"User Support"),COUNTIFS('Monthly Activity Log'!B$4:B$200,$B$3,'Monthly Activity Log'!H$4:H$200,"PetroSA Ghana",'Monthly Activity Log'!I$4:I$200,"User Support")),IF($B$3="All",COUNTIFS('Monthly Activity Log'!H$4:H$200,"PetroSA Ghana",'Monthly Activity Log'!I$4:I$200,"Admin/Config"),COUNTIFS('Monthly Activity Log'!B$4:B$200,$B$3,'Monthly Activity Log'!H$4:H$200,"PetroSA Ghana",'Monthly Activity Log'!I$4:I$200,"Admin/Config")),IF($B$3="All",COUNTIFS('Monthly Activity Log'!H$4:H$200,"PetroSA Ghana",'Monthly Activity Log'!I$4:I$200,"Reporting"),COUNTIFS('Monthly Activity Log'!B$4:B$200,$B$3,'Monthly Activity Log'!H$4:H$200,"PetroSA Ghana",'Monthly Activity Log'!I$4:I$200,"Reporting")),IF($B$3="All",COUNTIFS('Monthly Activity Log'!H$4:H$200,"PetroSA Ghana",'Monthly Activity Log'!I$4:I$200,"Mentoring"),COUNTIFS('Monthly Activity Log'!B$4:B$200,$B$3,'Monthly Activity Log'!H$4:H$200,"PetroSA Ghana",'Monthly Activity Log'!I$4:I$200,"Mentoring")),IF($B$3="All",COUNTIFS('Monthly Activity Log'!H$4:H$200,"PetroSA Ghana",'Monthly Activity Log'!I$4:I$200,"Other"),COUNTIFS('Monthly Activity Log'!B$4:B$200,$B$3,'Monthly Activity Log'!H$4:H$200,"PetroSA Ghana",'Monthly Activity Log'!I$4:I$200,"Other"))),"User Support",IF(IF($B$3="All",COUNTIFS('Monthly Activity Log'!H$4:H$200,"PetroSA Ghana",'Monthly Activity Log'!I$4:I$200,"Admin/Config"),COUNTIFS('Monthly Activity Log'!B$4:B$200,$B$3,'Monthly Activity Log'!H$4:H$200,"PetroSA Ghana",'Monthly Activity Log'!I$4:I$200,"Admin/Config"))=MAX(IF($B$3="All",COUNTIFS('Monthly Activity Log'!H$4:H$200,"PetroSA Ghana",'Monthly Activity Log'!I$4:I$200,"Project"),COUNTIFS('Monthly Activity Log'!B$4:B$200,$B$3,'Monthly Activity Log'!H$4:H$200,"PetroSA Ghana",'Monthly Activity Log'!I$4:I$200,"Project")),IF($B$3="All",COUNTIFS('Monthly Activity Log'!H$4:H$200,"PetroSA Ghana",'Monthly Activity Log'!I$4:I$200,"Incident/Bug Fix"),COUNTIFS('Monthly Activity Log'!B$4:B$200,$B$3,'Monthly Activity Log'!H$4:H$200,"PetroSA Ghana",'Monthly Activity Log'!I$4:I$200,"Incident/Bug Fix")),IF($B$3="All",COUNTIFS('Monthly Activity Log'!H$4:H$200,"PetroSA Ghana",'Monthly Activity Log'!I$4:I$200,"Change Request"),COUNTIFS('Monthly Activity Log'!B$4:B$200,$B$3,'Monthly Activity Log'!H$4:H$200,"PetroSA Ghana",'Monthly Activity Log'!I$4:I$200,"Change Request")),IF($B$3="All",COUNTIFS('Monthly Activity Log'!H$4:H$200,"PetroSA Ghana",'Monthly Activity Log'!I$4:I$200,"User Support"),COUNTIFS('Monthly Activity Log'!B$4:B$200,$B$3,'Monthly Activity Log'!H$4:H$200,"PetroSA Ghana",'Monthly Activity Log'!I$4:I$200,"User Support")),IF($B$3="All",COUNTIFS('Monthly Activity Log'!H$4:H$200,"PetroSA Ghana",'Monthly Activity Log'!I$4:I$200,"Admin/Config"),COUNTIFS('Monthly Activity Log'!B$4:B$200,$B$3,'Monthly Activity Log'!H$4:H$200,"PetroSA Ghana",'Monthly Activity Log'!I$4:I$200,"Admin/Config")),IF($B$3="All",COUNTIFS('Monthly Activity Log'!H$4:H$200,"PetroSA Ghana",'Monthly Activity Log'!I$4:I$200,"Reporting"),COUNTIFS('Monthly Activity Log'!B$4:B$200,$B$3,'Monthly Activity Log'!H$4:H$200,"PetroSA Ghana",'Monthly Activity Log'!I$4:I$200,"Reporting")),IF($B$3="All",COUNTIFS('Monthly Activity Log'!H$4:H$200,"PetroSA Ghana",'Monthly Activity Log'!I$4:I$200,"Mentoring"),COUNTIFS('Monthly Activity Log'!B$4:B$200,$B$3,'Monthly Activity Log'!H$4:H$200,"PetroSA Ghana",'Monthly Activity Log'!I$4:I$200,"Mentoring")),IF($B$3="All",COUNTIFS('Monthly Activity Log'!H$4:H$200,"PetroSA Ghana",'Monthly Activity Log'!I$4:I$200,"Other"),COUNTIFS('Monthly Activity Log'!B$4:B$200,$B$3,'Monthly Activity Log'!H$4:H$200,"PetroSA Ghana",'Monthly Activity Log'!I$4:I$200,"Other"))),"Admin/Config",IF(IF($B$3="All",COUNTIFS('Monthly Activity Log'!H$4:H$200,"PetroSA Ghana",'Monthly Activity Log'!I$4:I$200,"Reporting"),COUNTIFS('Monthly Activity Log'!B$4:B$200,$B$3,'Monthly Activity Log'!H$4:H$200,"PetroSA Ghana",'Monthly Activity Log'!I$4:I$200,"Reporting"))=MAX(IF($B$3="All",COUNTIFS('Monthly Activity Log'!H$4:H$200,"PetroSA Ghana",'Monthly Activity Log'!I$4:I$200,"Project"),COUNTIFS('Monthly Activity Log'!B$4:B$200,$B$3,'Monthly Activity Log'!H$4:H$200,"PetroSA Ghana",'Monthly Activity Log'!I$4:I$200,"Project")),IF($B$3="All",COUNTIFS('Monthly Activity Log'!H$4:H$200,"PetroSA Ghana",'Monthly Activity Log'!I$4:I$200,"Incident/Bug Fix"),COUNTIFS('Monthly Activity Log'!B$4:B$200,$B$3,'Monthly Activity Log'!H$4:H$200,"PetroSA Ghana",'Monthly Activity Log'!I$4:I$200,"Incident/Bug Fix")),IF($B$3="All",COUNTIFS('Monthly Activity Log'!H$4:H$200,"PetroSA Ghana",'Monthly Activity Log'!I$4:I$200,"Change Request"),COUNTIFS('Monthly Activity Log'!B$4:B$200,$B$3,'Monthly Activity Log'!H$4:H$200,"PetroSA Ghana",'Monthly Activity Log'!I$4:I$200,"Change Request")),IF($B$3="All",COUNTIFS('Monthly Activity Log'!H$4:H$200,"PetroSA Ghana",'Monthly Activity Log'!I$4:I$200,"User Support"),COUNTIFS('Monthly Activity Log'!B$4:B$200,$B$3,'Monthly Activity Log'!H$4:H$200,"PetroSA Ghana",'Monthly Activity Log'!I$4:I$200,"User Support")),IF($B$3="All",COUNTIFS('Monthly Activity Log'!H$4:H$200,"PetroSA Ghana",'Monthly Activity Log'!I$4:I$200,"Admin/Config"),COUNTIFS('Monthly Activity Log'!B$4:B$200,$B$3,'Monthly Activity Log'!H$4:H$200,"PetroSA Ghana",'Monthly Activity Log'!I$4:I$200,"Admin/Config")),IF($B$3="All",COUNTIFS('Monthly Activity Log'!H$4:H$200,"PetroSA Ghana",'Monthly Activity Log'!I$4:I$200,"Reporting"),COUNTIFS('Monthly Activity Log'!B$4:B$200,$B$3,'Monthly Activity Log'!H$4:H$200,"PetroSA Ghana",'Monthly Activity Log'!I$4:I$200,"Reporting")),IF($B$3="All",COUNTIFS('Monthly Activity Log'!H$4:H$200,"PetroSA Ghana",'Monthly Activity Log'!I$4:I$200,"Mentoring"),COUNTIFS('Monthly Activity Log'!B$4:B$200,$B$3,'Monthly Activity Log'!H$4:H$200,"PetroSA Ghana",'Monthly Activity Log'!I$4:I$200,"Mentoring")),IF($B$3="All",COUNTIFS('Monthly Activity Log'!H$4:H$200,"PetroSA Ghana",'Monthly Activity Log'!I$4:I$200,"Other"),COUNTIFS('Monthly Activity Log'!B$4:B$200,$B$3,'Monthly Activity Log'!H$4:H$200,"PetroSA Ghana",'Monthly Activity Log'!I$4:I$200,"Other"))),"Reporting",IF(IF($B$3="All",COUNTIFS('Monthly Activity Log'!H$4:H$200,"PetroSA Ghana",'Monthly Activity Log'!I$4:I$200,"Mentoring"),COUNTIFS('Monthly Activity Log'!B$4:B$200,$B$3,'Monthly Activity Log'!H$4:H$200,"PetroSA Ghana",'Monthly Activity Log'!I$4:I$200,"Mentoring"))=MAX(IF($B$3="All",COUNTIFS('Monthly Activity Log'!H$4:H$200,"PetroSA Ghana",'Monthly Activity Log'!I$4:I$200,"Project"),COUNTIFS('Monthly Activity Log'!B$4:B$200,$B$3,'Monthly Activity Log'!H$4:H$200,"PetroSA Ghana",'Monthly Activity Log'!I$4:I$200,"Project")),IF($B$3="All",COUNTIFS('Monthly Activity Log'!H$4:H$200,"PetroSA Ghana",'Monthly Activity Log'!I$4:I$200,"Incident/Bug Fix"),COUNTIFS('Monthly Activity Log'!B$4:B$200,$B$3,'Monthly Activity Log'!H$4:H$200,"PetroSA Ghana",'Monthly Activity Log'!I$4:I$200,"Incident/Bug Fix")),IF($B$3="All",COUNTIFS('Monthly Activity Log'!H$4:H$200,"PetroSA Ghana",'Monthly Activity Log'!I$4:I$200,"Change Request"),COUNTIFS('Monthly Activity Log'!B$4:B$200,$B$3,'Monthly Activity Log'!H$4:H$200,"PetroSA Ghana",'Monthly Activity Log'!I$4:I$200,"Change Request")),IF($B$3="All",COUNTIFS('Monthly Activity Log'!H$4:H$200,"PetroSA Ghana",'Monthly Activity Log'!I$4:I$200,"User Support"),COUNTIFS('Monthly Activity Log'!B$4:B$200,$B$3,'Monthly Activity Log'!H$4:H$200,"PetroSA Ghana",'Monthly Activity Log'!I$4:I$200,"User Support")),IF($B$3="All",COUNTIFS('Monthly Activity Log'!H$4:H$200,"PetroSA Ghana",'Monthly Activity Log'!I$4:I$200,"Admin/Config"),COUNTIFS('Monthly Activity Log'!B$4:B$200,$B$3,'Monthly Activity Log'!H$4:H$200,"PetroSA Ghana",'Monthly Activity Log'!I$4:I$200,"Admin/Config")),IF($B$3="All",COUNTIFS('Monthly Activity Log'!H$4:H$200,"PetroSA Ghana",'Monthly Activity Log'!I$4:I$200,"Reporting"),COUNTIFS('Monthly Activity Log'!B$4:B$200,$B$3,'Monthly Activity Log'!H$4:H$200,"PetroSA Ghana",'Monthly Activity Log'!I$4:I$200,"Reporting")),IF($B$3="All",COUNTIFS('Monthly Activity Log'!H$4:H$200,"PetroSA Ghana",'Monthly Activity Log'!I$4:I$200,"Mentoring"),COUNTIFS('Monthly Activity Log'!B$4:B$200,$B$3,'Monthly Activity Log'!H$4:H$200,"PetroSA Ghana",'Monthly Activity Log'!I$4:I$200,"Mentoring")),IF($B$3="All",COUNTIFS('Monthly Activity Log'!H$4:H$200,"PetroSA Ghana",'Monthly Activity Log'!I$4:I$200,"Other"),COUNTIFS('Monthly Activity Log'!B$4:B$200,$B$3,'Monthly Activity Log'!H$4:H$200,"PetroSA Ghana",'Monthly Activity Log'!I$4:I$200,"Other"))),"Mentoring",IF(IF($B$3="All",COUNTIFS('Monthly Activity Log'!H$4:H$200,"PetroSA Ghana",'Monthly Activity Log'!I$4:I$200,"Other"),COUNTIFS('Monthly Activity Log'!B$4:B$200,$B$3,'Monthly Activity Log'!H$4:H$200,"PetroSA Ghana",'Monthly Activity Log'!I$4:I$200,"Other"))=MAX(IF($B$3="All",COUNTIFS('Monthly Activity Log'!H$4:H$200,"PetroSA Ghana",'Monthly Activity Log'!I$4:I$200,"Project"),COUNTIFS('Monthly Activity Log'!B$4:B$200,$B$3,'Monthly Activity Log'!H$4:H$200,"PetroSA Ghana",'Monthly Activity Log'!I$4:I$200,"Project")),IF($B$3="All",COUNTIFS('Monthly Activity Log'!H$4:H$200,"PetroSA Ghana",'Monthly Activity Log'!I$4:I$200,"Incident/Bug Fix"),COUNTIFS('Monthly Activity Log'!B$4:B$200,$B$3,'Monthly Activity Log'!H$4:H$200,"PetroSA Ghana",'Monthly Activity Log'!I$4:I$200,"Incident/Bug Fix")),IF($B$3="All",COUNTIFS('Monthly Activity Log'!H$4:H$200,"PetroSA Ghana",'Monthly Activity Log'!I$4:I$200,"Change Request"),COUNTIFS('Monthly Activity Log'!B$4:B$200,$B$3,'Monthly Activity Log'!H$4:H$200,"PetroSA Ghana",'Monthly Activity Log'!I$4:I$200,"Change Request")),IF($B$3="All",COUNTIFS('Monthly Activity Log'!H$4:H$200,"PetroSA Ghana",'Monthly Activity Log'!I$4:I$200,"User Support"),COUNTIFS('Monthly Activity Log'!B$4:B$200,$B$3,'Monthly Activity Log'!H$4:H$200,"PetroSA Ghana",'Monthly Activity Log'!I$4:I$200,"User Support")),IF($B$3="All",COUNTIFS('Monthly Activity Log'!H$4:H$200,"PetroSA Ghana",'Monthly Activity Log'!I$4:I$200,"Admin/Config"),COUNTIFS('Monthly Activity Log'!B$4:B$200,$B$3,'Monthly Activity Log'!H$4:H$200,"PetroSA Ghana",'Monthly Activity Log'!I$4:I$200,"Admin/Config")),IF($B$3="All",COUNTIFS('Monthly Activity Log'!H$4:H$200,"PetroSA Ghana",'Monthly Activity Log'!I$4:I$200,"Reporting"),COUNTIFS('Monthly Activity Log'!B$4:B$200,$B$3,'Monthly Activity Log'!H$4:H$200,"PetroSA Ghana",'Monthly Activity Log'!I$4:I$200,"Reporting")),IF($B$3="All",COUNTIFS('Monthly Activity Log'!H$4:H$200,"PetroSA Ghana",'Monthly Activity Log'!I$4:I$200,"Mentoring"),COUNTIFS('Monthly Activity Log'!B$4:B$200,$B$3,'Monthly Activity Log'!H$4:H$200,"PetroSA Ghana",'Monthly Activity Log'!I$4:I$200,"Mentoring")),IF($B$3="All",COUNTIFS('Monthly Activity Log'!H$4:H$200,"PetroSA Ghana",'Monthly Activity Log'!I$4:I$200,"Other"),COUNTIFS('Monthly Activity Log'!B$4:B$200,$B$3,'Monthly Activity Log'!H$4:H$200,"PetroSA Ghana",'Monthly Activity Log'!I$4:I$200,"Other"))),"Other","-"))))))))) | J7: =D7+E7
A8: Legacy/CEF | B8: =IF($B$3="All",COUNTIF('Monthly Activity Log'!H$4:H$200,"Legacy/CEF"),COUNTIFS('Monthly Activity Log'!B$4:B$200,$B$3,'Monthly Activity Log'!H$4:H$200,"Legacy/CEF")) | C8: =IF($B$3="All",COUNTIFS('Monthly Activity Log'!H$4:H$200,"Legacy/CEF",'Monthly Activity Log'!K$4:K$200,"Completed"),COUNTIFS('Monthly Activity Log'!B$4:B$200,$B$3,'Monthly Activity Log'!H$4:H$200,"Legacy/CEF",'Monthly Activity Log'!K$4:K$200,"Completed")) | D8: =IF($B$3="All",COUNTIFS('Monthly Activity Log'!H$4:H$200,"Legacy/CEF",'Monthly Activity Log'!K$4:K$200,"In Progress"),COUNTIFS('Monthly Activity Log'!B$4:B$200,$B$3,'Monthly Activity Log'!H$4:H$200,"Legacy/CEF",'Monthly Activity Log'!K$4:K$200,"In Progress")) | E8: =IF($B$3="All",COUNTIFS('Monthly Activity Log'!H$4:H$200,"Legacy/CEF",'Monthly Activity Log'!K$4:K$200,"Pending"),COUNTIFS('Monthly Activity Log'!B$4:B$200,$B$3,'Monthly Activity Log'!H$4:H$200,"Legacy/CEF",'Monthly Activity Log'!K$4:K$200,"Pending")) | F8: =IFERROR(C8/B8,0) | G8: =IFERROR(B8/'Summary Dashboard'!A7,0) | H8: =IF(B8=0,"-",IF(IF($B$3="All",COUNTIFS('Monthly Activity Log'!H$4:H$200,"Legacy/CEF",'Monthly Activity Log'!C$4:C$200,"Shennaz"),COUNTIFS('Monthly Activity Log'!B$4:B$200,$B$3,'Monthly Activity Log'!H$4:H$200,"Legacy/CEF",'Monthly Activity Log'!C$4:C$200,"Shennaz"))=MAX(IF($B$3="All",COUNTIFS('Monthly Activity Log'!H$4:H$200,"Legacy/CEF",'Monthly Activity Log'!C$4:C$200,"Shennaz"),COUNTIFS('Monthly Activity Log'!B$4:B$200,$B$3,'Monthly Activity Log'!H$4:H$200,"Legacy/CEF",'Monthly Activity Log'!C$4:C$200,"Shennaz")),IF($B$3="All",COUNTIFS('Monthly Activity Log'!H$4:H$200,"Legacy/CEF",'Monthly Activity Log'!C$4:C$200,"Nyameka"),COUNTIFS('Monthly Activity Log'!B$4:B$200,$B$3,'Monthly Activity Log'!H$4:H$200,"Legacy/CEF",'Monthly Activity Log'!C$4:C$200,"Nyameka")),IF($B$3="All",COUNTIFS('Monthly Activity Log'!H$4:H$200,"Legacy/CEF",'Monthly Activity Log'!C$4:C$200,"Lindiwe"),COUNTIFS('Monthly Activity Log'!B$4:B$200,$B$3,'Monthly Activity Log'!H$4:H$200,"Legacy/CEF",'Monthly Activity Log'!C$4:C$200,"Lindiwe")),IF($B$3="All",COUNTIFS('Monthly Activity Log'!H$4:H$200,"Legacy/CEF",'Monthly Activity Log'!C$4:C$200,"T A Willems"),COUNTIFS('Monthly Activity Log'!B$4:B$200,$B$3,'Monthly Activity Log'!H$4:H$200,"Legacy/CEF",'Monthly Activity Log'!C$4:C$200,"T A Willems")),IF($B$3="All",COUNTIFS('Monthly Activity Log'!H$4:H$200,"Legacy/CEF",'Monthly Activity Log'!C$4:C$200,"Mphatheleni Matidze"),COUNTIFS('Monthly Activity Log'!B$4:B$200,$B$3,'Monthly Activity Log'!H$4:H$200,"Legacy/CEF",'Monthly Activity Log'!C$4:C$200,"Mphatheleni Matidze"))),"Shennaz",IF(IF($B$3="All",COUNTIFS('Monthly Activity Log'!H$4:H$200,"Legacy/CEF",'Monthly Activity Log'!C$4:C$200,"Nyameka"),COUNTIFS('Monthly Activity Log'!B$4:B$200,$B$3,'Monthly Activity Log'!H$4:H$200,"Legacy/CEF",'Monthly Activity Log'!C$4:C$200,"Nyameka"))=MAX(IF($B$3="All",COUNTIFS('Monthly Activity Log'!H$4:H$200,"Legacy/CEF",'Monthly Activity Log'!C$4:C$200,"Shennaz"),COUNTIFS('Monthly Activity Log'!B$4:B$200,$B$3,'Monthly Activity Log'!H$4:H$200,"Legacy/CEF",'Monthly Activity Log'!C$4:C$200,"Shennaz")),IF($B$3="All",COUNTIFS('Monthly Activity Log'!H$4:H$200,"Legacy/CEF",'Monthly Activity Log'!C$4:C$200,"Nyameka"),COUNTIFS('Monthly Activity Log'!B$4:B$200,$B$3,'Monthly Activity Log'!H$4:H$200,"Legacy/CEF",'Monthly Activity Log'!C$4:C$200,"Nyameka")),IF($B$3="All",COUNTIFS('Monthly Activity Log'!H$4:H$200,"Legacy/CEF",'Monthly Activity Log'!C$4:C$200,"Lindiwe"),COUNTIFS('Monthly Activity Log'!B$4:B$200,$B$3,'Monthly Activity Log'!H$4:H$200,"Legacy/CEF",'Monthly Activity Log'!C$4:C$200,"Lindiwe")),IF($B$3="All",COUNTIFS('Monthly Activity Log'!H$4:H$200,"Legacy/CEF",'Monthly Activity Log'!C$4:C$200,"T A Willems"),COUNTIFS('Monthly Activity Log'!B$4:B$200,$B$3,'Monthly Activity Log'!H$4:H$200,"Legacy/CEF",'Monthly Activity Log'!C$4:C$200,"T A Willems")),IF($B$3="All",COUNTIFS('Monthly Activity Log'!H$4:H$200,"Legacy/CEF",'Monthly Activity Log'!C$4:C$200,"Mphatheleni Matidze"),COUNTIFS('Monthly Activity Log'!B$4:B$200,$B$3,'Monthly Activity Log'!H$4:H$200,"Legacy/CEF",'Monthly Activity Log'!C$4:C$200,"Mphatheleni Matidze"))),"Nyameka",IF(IF($B$3="All",COUNTIFS('Monthly Activity Log'!H$4:H$200,"Legacy/CEF",'Monthly Activity Log'!C$4:C$200,"Lindiwe"),COUNTIFS('Monthly Activity Log'!B$4:B$200,$B$3,'Monthly Activity Log'!H$4:H$200,"Legacy/CEF",'Monthly Activity Log'!C$4:C$200,"Lindiwe"))=MAX(IF($B$3="All",COUNTIFS('Monthly Activity Log'!H$4:H$200,"Legacy/CEF",'Monthly Activity Log'!C$4:C$200,"Shennaz"),COUNTIFS('Monthly Activity Log'!B$4:B$200,$B$3,'Monthly Activity Log'!H$4:H$200,"Legacy/CEF",'Monthly Activity Log'!C$4:C$200,"Shennaz")),IF($B$3="All",COUNTIFS('Monthly Activity Log'!H$4:H$200,"Legacy/CEF",'Monthly Activity Log'!C$4:C$200,"Nyameka"),COUNTIFS('Monthly Activity Log'!B$4:B$200,$B$3,'Monthly Activity Log'!H$4:H$200,"Legacy/CEF",'Monthly Activity Log'!C$4:C$200,"Nyameka")),IF($B$3="All",COUNTIFS('Monthly Activity Log'!H$4:H$200,"Legacy/CEF",'Monthly Activity Log'!C$4:C$200,"Lindiwe"),COUNTIFS('Monthly Activity Log'!B$4:B$200,$B$3,'Monthly Activity Log'!H$4:H$200,"Legacy/CEF",'Monthly Activity Log'!C$4:C$200,"Lindiwe")),IF($B$3="All",COUNTIFS('Monthly Activity Log'!H$4:H$200,"Legacy/CEF",'Monthly Activity Log'!C$4:C$200,"T A Willems"),COUNTIFS('Monthly Activity Log'!B$4:B$200,$B$3,'Monthly Activity Log'!H$4:H$200,"Legacy/CEF",'Monthly Activity Log'!C$4:C$200,"T A Willems")),IF($B$3="All",COUNTIFS('Monthly Activity Log'!H$4:H$200,"Legacy/CEF",'Monthly Activity Log'!C$4:C$200,"Mphatheleni Matidze"),COUNTIFS('Monthly Activity Log'!B$4:B$200,$B$3,'Monthly Activity Log'!H$4:H$200,"Legacy/CEF",'Monthly Activity Log'!C$4:C$200,"Mphatheleni Matidze"))),"Lindiwe",IF(IF($B$3="All",COUNTIFS('Monthly Activity Log'!H$4:H$200,"Legacy/CEF",'Monthly Activity Log'!C$4:C$200,"T A Willems"),COUNTIFS('Monthly Activity Log'!B$4:B$200,$B$3,'Monthly Activity Log'!H$4:H$200,"Legacy/CEF",'Monthly Activity Log'!C$4:C$200,"T A Willems"))=MAX(IF($B$3="All",COUNTIFS('Monthly Activity Log'!H$4:H$200,"Legacy/CEF",'Monthly Activity Log'!C$4:C$200,"Shennaz"),COUNTIFS('Monthly Activity Log'!B$4:B$200,$B$3,'Monthly Activity Log'!H$4:H$200,"Legacy/CEF",'Monthly Activity Log'!C$4:C$200,"Shennaz")),IF($B$3="All",COUNTIFS('Monthly Activity Log'!H$4:H$200,"Legacy/CEF",'Monthly Activity Log'!C$4:C$200,"Nyameka"),COUNTIFS('Monthly Activity Log'!B$4:B$200,$B$3,'Monthly Activity Log'!H$4:H$200,"Legacy/CEF",'Monthly Activity Log'!C$4:C$200,"Nyameka")),IF($B$3="All",COUNTIFS('Monthly Activity Log'!H$4:H$200,"Legacy/CEF",'Monthly Activity Log'!C$4:C$200,"Lindiwe"),COUNTIFS('Monthly Activity Log'!B$4:B$200,$B$3,'Monthly Activity Log'!H$4:H$200,"Legacy/CEF",'Monthly Activity Log'!C$4:C$200,"Lindiwe")),IF($B$3="All",COUNTIFS('Monthly Activity Log'!H$4:H$200,"Legacy/CEF",'Monthly Activity Log'!C$4:C$200,"T A Willems"),COUNTIFS('Monthly Activity Log'!B$4:B$200,$B$3,'Monthly Activity Log'!H$4:H$200,"Legacy/CEF",'Monthly Activity Log'!C$4:C$200,"T A Willems")),IF($B$3="All",COUNTIFS('Monthly Activity Log'!H$4:H$200,"Legacy/CEF",'Monthly Activity Log'!C$4:C$200,"Mphatheleni Matidze"),COUNTIFS('Monthly Activity Log'!B$4:B$200,$B$3,'Monthly Activity Log'!H$4:H$200,"Legacy/CEF",'Monthly Activity Log'!C$4:C$200,"Mphatheleni Matidze"))),"T A Willems",IF(IF($B$3="All",COUNTIFS('Monthly Activity Log'!H$4:H$200,"Legacy/CEF",'Monthly Activity Log'!C$4:C$200,"Mphatheleni Matidze"),COUNTIFS('Monthly Activity Log'!B$4:B$200,$B$3,'Monthly Activity Log'!H$4:H$200,"Legacy/CEF",'Monthly Activity Log'!C$4:C$200,"Mphatheleni Matidze"))=MAX(IF($B$3="All",COUNTIFS('Monthly Activity Log'!H$4:H$200,"Legacy/CEF",'Monthly Activity Log'!C$4:C$200,"Shennaz"),COUNTIFS('Monthly Activity Log'!B$4:B$200,$B$3,'Monthly Activity Log'!H$4:H$200,"Legacy/CEF",'Monthly Activity Log'!C$4:C$200,"Shennaz")),IF($B$3="All",COUNTIFS('Monthly Activity Log'!H$4:H$200,"Legacy/CEF",'Monthly Activity Log'!C$4:C$200,"Nyameka"),COUNTIFS('Monthly Activity Log'!B$4:B$200,$B$3,'Monthly Activity Log'!H$4:H$200,"Legacy/CEF",'Monthly Activity Log'!C$4:C$200,"Nyameka")),IF($B$3="All",COUNTIFS('Monthly Activity Log'!H$4:H$200,"Legacy/CEF",'Monthly Activity Log'!C$4:C$200,"Lindiwe"),COUNTIFS('Monthly Activity Log'!B$4:B$200,$B$3,'Monthly Activity Log'!H$4:H$200,"Legacy/CEF",'Monthly Activity Log'!C$4:C$200,"Lindiwe")),IF($B$3="All",COUNTIFS('Monthly Activity Log'!H$4:H$200,"Legacy/CEF",'Monthly Activity Log'!C$4:C$200,"T A Willems"),COUNTIFS('Monthly Activity Log'!B$4:B$200,$B$3,'Monthly Activity Log'!H$4:H$200,"Legacy/CEF",'Monthly Activity Log'!C$4:C$200,"T A Willems")),IF($B$3="All",COUNTIFS('Monthly Activity Log'!H$4:H$200,"Legacy/CEF",'Monthly Activity Log'!C$4:C$200,"Mphatheleni Matidze"),COUNTIFS('Monthly Activity Log'!B$4:B$200,$B$3,'Monthly Activity Log'!H$4:H$200,"Legacy/CEF",'Monthly Activity Log'!C$4:C$200,"Mphatheleni Matidze"))),"Mphatheleni Matidze","-")))))) | I8: =IF(B8=0,"-",IF(IF($B$3="All",COUNTIFS('Monthly Activity Log'!H$4:H$200,"Legacy/CEF",'Monthly Activity Log'!I$4:I$200,"Project"),COUNTIFS('Monthly Activity Log'!B$4:B$200,$B$3,'Monthly Activity Log'!H$4:H$200,"Legacy/CEF",'Monthly Activity Log'!I$4:I$200,"Project"))=MAX(IF($B$3="All",COUNTIFS('Monthly Activity Log'!H$4:H$200,"Legacy/CEF",'Monthly Activity Log'!I$4:I$200,"Project"),COUNTIFS('Monthly Activity Log'!B$4:B$200,$B$3,'Monthly Activity Log'!H$4:H$200,"Legacy/CEF",'Monthly Activity Log'!I$4:I$200,"Project")),IF($B$3="All",COUNTIFS('Monthly Activity Log'!H$4:H$200,"Legacy/CEF",'Monthly Activity Log'!I$4:I$200,"Incident/Bug Fix"),COUNTIFS('Monthly Activity Log'!B$4:B$200,$B$3,'Monthly Activity Log'!H$4:H$200,"Legacy/CEF",'Monthly Activity Log'!I$4:I$200,"Incident/Bug Fix")),IF($B$3="All",COUNTIFS('Monthly Activity Log'!H$4:H$200,"Legacy/CEF",'Monthly Activity Log'!I$4:I$200,"Change Request"),COUNTIFS('Monthly Activity Log'!B$4:B$200,$B$3,'Monthly Activity Log'!H$4:H$200,"Legacy/CEF",'Monthly Activity Log'!I$4:I$200,"Change Request")),IF($B$3="All",COUNTIFS('Monthly Activity Log'!H$4:H$200,"Legacy/CEF",'Monthly Activity Log'!I$4:I$200,"User Support"),COUNTIFS('Monthly Activity Log'!B$4:B$200,$B$3,'Monthly Activity Log'!H$4:H$200,"Legacy/CEF",'Monthly Activity Log'!I$4:I$200,"User Support")),IF($B$3="All",COUNTIFS('Monthly Activity Log'!H$4:H$200,"Legacy/CEF",'Monthly Activity Log'!I$4:I$200,"Admin/Config"),COUNTIFS('Monthly Activity Log'!B$4:B$200,$B$3,'Monthly Activity Log'!H$4:H$200,"Legacy/CEF",'Monthly Activity Log'!I$4:I$200,"Admin/Config")),IF($B$3="All",COUNTIFS('Monthly Activity Log'!H$4:H$200,"Legacy/CEF",'Monthly Activity Log'!I$4:I$200,"Reporting"),COUNTIFS('Monthly Activity Log'!B$4:B$200,$B$3,'Monthly Activity Log'!H$4:H$200,"Legacy/CEF",'Monthly Activity Log'!I$4:I$200,"Reporting")),IF($B$3="All",COUNTIFS('Monthly Activity Log'!H$4:H$200,"Legacy/CEF",'Monthly Activity Log'!I$4:I$200,"Mentoring"),COUNTIFS('Monthly Activity Log'!B$4:B$200,$B$3,'Monthly Activity Log'!H$4:H$200,"Legacy/CEF",'Monthly Activity Log'!I$4:I$200,"Mentoring")),IF($B$3="All",COUNTIFS('Monthly Activity Log'!H$4:H$200,"Legacy/CEF",'Monthly Activity Log'!I$4:I$200,"Other"),COUNTIFS('Monthly Activity Log'!B$4:B$200,$B$3,'Monthly Activity Log'!H$4:H$200,"Legacy/CEF",'Monthly Activity Log'!I$4:I$200,"Other"))),"Project",IF(IF($B$3="All",COUNTIFS('Monthly Activity Log'!H$4:H$200,"Legacy/CEF",'Monthly Activity Log'!I$4:I$200,"Incident/Bug Fix"),COUNTIFS('Monthly Activity Log'!B$4:B$200,$B$3,'Monthly Activity Log'!H$4:H$200,"Legacy/CEF",'Monthly Activity Log'!I$4:I$200,"Incident/Bug Fix"))=MAX(IF($B$3="All",COUNTIFS('Monthly Activity Log'!H$4:H$200,"Legacy/CEF",'Monthly Activity Log'!I$4:I$200,"Project"),COUNTIFS('Monthly Activity Log'!B$4:B$200,$B$3,'Monthly Activity Log'!H$4:H$200,"Legacy/CEF",'Monthly Activity Log'!I$4:I$200,"Project")),IF($B$3="All",COUNTIFS('Monthly Activity Log'!H$4:H$200,"Legacy/CEF",'Monthly Activity Log'!I$4:I$200,"Incident/Bug Fix"),COUNTIFS('Monthly Activity Log'!B$4:B$200,$B$3,'Monthly Activity Log'!H$4:H$200,"Legacy/CEF",'Monthly Activity Log'!I$4:I$200,"Incident/Bug Fix")),IF($B$3="All",COUNTIFS('Monthly Activity Log'!H$4:H$200,"Legacy/CEF",'Monthly Activity Log'!I$4:I$200,"Change Request"),COUNTIFS('Monthly Activity Log'!B$4:B$200,$B$3,'Monthly Activity Log'!H$4:H$200,"Legacy/CEF",'Monthly Activity Log'!I$4:I$200,"Change Request")),IF($B$3="All",COUNTIFS('Monthly Activity Log'!H$4:H$200,"Legacy/CEF",'Monthly Activity Log'!I$4:I$200,"User Support"),COUNTIFS('Monthly Activity Log'!B$4:B$200,$B$3,'Monthly Activity Log'!H$4:H$200,"Legacy/CEF",'Monthly Activity Log'!I$4:I$200,"User Support")),IF($B$3="All",COUNTIFS('Monthly Activity Log'!H$4:H$200,"Legacy/CEF",'Monthly Activity Log'!I$4:I$200,"Admin/Config"),COUNTIFS('Monthly Activity Log'!B$4:B$200,$B$3,'Monthly Activity Log'!H$4:H$200,"Legacy/CEF",'Monthly Activity Log'!I$4:I$200,"Admin/Config")),IF($B$3="All",COUNTIFS('Monthly Activity Log'!H$4:H$200,"Legacy/CEF",'Monthly Activity Log'!I$4:I$200,"Reporting"),COUNTIFS('Monthly Activity Log'!B$4:B$200,$B$3,'Monthly Activity Log'!H$4:H$200,"Legacy/CEF",'Monthly Activity Log'!I$4:I$200,"Reporting")),IF($B$3="All",COUNTIFS('Monthly Activity Log'!H$4:H$200,"Legacy/CEF",'Monthly Activity Log'!I$4:I$200,"Mentoring"),COUNTIFS('Monthly Activity Log'!B$4:B$200,$B$3,'Monthly Activity Log'!H$4:H$200,"Legacy/CEF",'Monthly Activity Log'!I$4:I$200,"Mentoring")),IF($B$3="All",COUNTIFS('Monthly Activity Log'!H$4:H$200,"Legacy/CEF",'Monthly Activity Log'!I$4:I$200,"Other"),COUNTIFS('Monthly Activity Log'!B$4:B$200,$B$3,'Monthly Activity Log'!H$4:H$200,"Legacy/CEF",'Monthly Activity Log'!I$4:I$200,"Other"))),"Incident/Bug Fix",IF(IF($B$3="All",COUNTIFS('Monthly Activity Log'!H$4:H$200,"Legacy/CEF",'Monthly Activity Log'!I$4:I$200,"Change Request"),COUNTIFS('Monthly Activity Log'!B$4:B$200,$B$3,'Monthly Activity Log'!H$4:H$200,"Legacy/CEF",'Monthly Activity Log'!I$4:I$200,"Change Request"))=MAX(IF($B$3="All",COUNTIFS('Monthly Activity Log'!H$4:H$200,"Legacy/CEF",'Monthly Activity Log'!I$4:I$200,"Project"),COUNTIFS('Monthly Activity Log'!B$4:B$200,$B$3,'Monthly Activity Log'!H$4:H$200,"Legacy/CEF",'Monthly Activity Log'!I$4:I$200,"Project")),IF($B$3="All",COUNTIFS('Monthly Activity Log'!H$4:H$200,"Legacy/CEF",'Monthly Activity Log'!I$4:I$200,"Incident/Bug Fix"),COUNTIFS('Monthly Activity Log'!B$4:B$200,$B$3,'Monthly Activity Log'!H$4:H$200,"Legacy/CEF",'Monthly Activity Log'!I$4:I$200,"Incident/Bug Fix")),IF($B$3="All",COUNTIFS('Monthly Activity Log'!H$4:H$200,"Legacy/CEF",'Monthly Activity Log'!I$4:I$200,"Change Request"),COUNTIFS('Monthly Activity Log'!B$4:B$200,$B$3,'Monthly Activity Log'!H$4:H$200,"Legacy/CEF",'Monthly Activity Log'!I$4:I$200,"Change Request")),IF($B$3="All",COUNTIFS('Monthly Activity Log'!H$4:H$200,"Legacy/CEF",'Monthly Activity Log'!I$4:I$200,"User Support"),COUNTIFS('Monthly Activity Log'!B$4:B$200,$B$3,'Monthly Activity Log'!H$4:H$200,"Legacy/CEF",'Monthly Activity Log'!I$4:I$200,"User Support")),IF($B$3="All",COUNTIFS('Monthly Activity Log'!H$4:H$200,"Legacy/CEF",'Monthly Activity Log'!I$4:I$200,"Admin/Config"),COUNTIFS('Monthly Activity Log'!B$4:B$200,$B$3,'Monthly Activity Log'!H$4:H$200,"Legacy/CEF",'Monthly Activity Log'!I$4:I$200,"Admin/Config")),IF($B$3="All",COUNTIFS('Monthly Activity Log'!H$4:H$200,"Legacy/CEF",'Monthly Activity Log'!I$4:I$200,"Reporting"),COUNTIFS('Monthly Activity Log'!B$4:B$200,$B$3,'Monthly Activity Log'!H$4:H$200,"Legacy/CEF",'Monthly Activity Log'!I$4:I$200,"Reporting")),IF($B$3="All",COUNTIFS('Monthly Activity Log'!H$4:H$200,"Legacy/CEF",'Monthly Activity Log'!I$4:I$200,"Mentoring"),COUNTIFS('Monthly Activity Log'!B$4:B$200,$B$3,'Monthly Activity Log'!H$4:H$200,"Legacy/CEF",'Monthly Activity Log'!I$4:I$200,"Mentoring")),IF($B$3="All",COUNTIFS('Monthly Activity Log'!H$4:H$200,"Legacy/CEF",'Monthly Activity Log'!I$4:I$200,"Other"),COUNTIFS('Monthly Activity Log'!B$4:B$200,$B$3,'Monthly Activity Log'!H$4:H$200,"Legacy/CEF",'Monthly Activity Log'!I$4:I$200,"Other"))),"Change Request",IF(IF($B$3="All",COUNTIFS('Monthly Activity Log'!H$4:H$200,"Legacy/CEF",'Monthly Activity Log'!I$4:I$200,"User Support"),COUNTIFS('Monthly Activity Log'!B$4:B$200,$B$3,'Monthly Activity Log'!H$4:H$200,"Legacy/CEF",'Monthly Activity Log'!I$4:I$200,"User Support"))=MAX(IF($B$3="All",COUNTIFS('Monthly Activity Log'!H$4:H$200,"Legacy/CEF",'Monthly Activity Log'!I$4:I$200,"Project"),COUNTIFS('Monthly Activity Log'!B$4:B$200,$B$3,'Monthly Activity Log'!H$4:H$200,"Legacy/CEF",'Monthly Activity Log'!I$4:I$200,"Project")),IF($B$3="All",COUNTIFS('Monthly Activity Log'!H$4:H$200,"Legacy/CEF",'Monthly Activity Log'!I$4:I$200,"Incident/Bug Fix"),COUNTIFS('Monthly Activity Log'!B$4:B$200,$B$3,'Monthly Activity Log'!H$4:H$200,"Legacy/CEF",'Monthly Activity Log'!I$4:I$200,"Incident/Bug Fix")),IF($B$3="All",COUNTIFS('Monthly Activity Log'!H$4:H$200,"Legacy/CEF",'Monthly Activity Log'!I$4:I$200,"Change Request"),COUNTIFS('Monthly Activity Log'!B$4:B$200,$B$3,'Monthly Activity Log'!H$4:H$200,"Legacy/CEF",'Monthly Activity Log'!I$4:I$200,"Change Request")),IF($B$3="All",COUNTIFS('Monthly Activity Log'!H$4:H$200,"Legacy/CEF",'Monthly Activity Log'!I$4:I$200,"User Support"),COUNTIFS('Monthly Activity Log'!B$4:B$200,$B$3,'Monthly Activity Log'!H$4:H$200,"Legacy/CEF",'Monthly Activity Log'!I$4:I$200,"User Support")),IF($B$3="All",COUNTIFS('Monthly Activity Log'!H$4:H$200,"Legacy/CEF",'Monthly Activity Log'!I$4:I$200,"Admin/Config"),COUNTIFS('Monthly Activity Log'!B$4:B$200,$B$3,'Monthly Activity Log'!H$4:H$200,"Legacy/CEF",'Monthly Activity Log'!I$4:I$200,"Admin/Config")),IF($B$3="All",COUNTIFS('Monthly Activity Log'!H$4:H$200,"Legacy/CEF",'Monthly Activity Log'!I$4:I$200,"Reporting"),COUNTIFS('Monthly Activity Log'!B$4:B$200,$B$3,'Monthly Activity Log'!H$4:H$200,"Legacy/CEF",'Monthly Activity Log'!I$4:I$200,"Reporting")),IF($B$3="All",COUNTIFS('Monthly Activity Log'!H$4:H$200,"Legacy/CEF",'Monthly Activity Log'!I$4:I$200,"Mentoring"),COUNTIFS('Monthly Activity Log'!B$4:B$200,$B$3,'Monthly Activity Log'!H$4:H$200,"Legacy/CEF",'Monthly Activity Log'!I$4:I$200,"Mentoring")),IF($B$3="All",COUNTIFS('Monthly Activity Log'!H$4:H$200,"Legacy/CEF",'Monthly Activity Log'!I$4:I$200,"Other"),COUNTIFS('Monthly Activity Log'!B$4:B$200,$B$3,'Monthly Activity Log'!H$4:H$200,"Legacy/CEF",'Monthly Activity Log'!I$4:I$200,"Other"))),"User Support",IF(IF($B$3="All",COUNTIFS('Monthly Activity Log'!H$4:H$200,"Legacy/CEF",'Monthly Activity Log'!I$4:I$200,"Admin/Config"),COUNTIFS('Monthly Activity Log'!B$4:B$200,$B$3,'Monthly Activity Log'!H$4:H$200,"Legacy/CEF",'Monthly Activity Log'!I$4:I$200,"Admin/Config"))=MAX(IF($B$3="All",COUNTIFS('Monthly Activity Log'!H$4:H$200,"Legacy/CEF",'Monthly Activity Log'!I$4:I$200,"Project"),COUNTIFS('Monthly Activity Log'!B$4:B$200,$B$3,'Monthly Activity Log'!H$4:H$200,"Legacy/CEF",'Monthly Activity Log'!I$4:I$200,"Project")),IF($B$3="All",COUNTIFS('Monthly Activity Log'!H$4:H$200,"Legacy/CEF",'Monthly Activity Log'!I$4:I$200,"Incident/Bug Fix"),COUNTIFS('Monthly Activity Log'!B$4:B$200,$B$3,'Monthly Activity Log'!H$4:H$200,"Legacy/CEF",'Monthly Activity Log'!I$4:I$200,"Incident/Bug Fix")),IF($B$3="All",COUNTIFS('Monthly Activity Log'!H$4:H$200,"Legacy/CEF",'Monthly Activity Log'!I$4:I$200,"Change Request"),COUNTIFS('Monthly Activity Log'!B$4:B$200,$B$3,'Monthly Activity Log'!H$4:H$200,"Legacy/CEF",'Monthly Activity Log'!I$4:I$200,"Change Request")),IF($B$3="All",COUNTIFS('Monthly Activity Log'!H$4:H$200,"Legacy/CEF",'Monthly Activity Log'!I$4:I$200,"User Support"),COUNTIFS('Monthly Activity Log'!B$4:B$200,$B$3,'Monthly Activity Log'!H$4:H$200,"Legacy/CEF",'Monthly Activity Log'!I$4:I$200,"User Support")),IF($B$3="All",COUNTIFS('Monthly Activity Log'!H$4:H$200,"Legacy/CEF",'Monthly Activity Log'!I$4:I$200,"Admin/Config"),COUNTIFS('Monthly Activity Log'!B$4:B$200,$B$3,'Monthly Activity Log'!H$4:H$200,"Legacy/CEF",'Monthly Activity Log'!I$4:I$200,"Admin/Config")),IF($B$3="All",COUNTIFS('Monthly Activity Log'!H$4:H$200,"Legacy/CEF",'Monthly Activity Log'!I$4:I$200,"Reporting"),COUNTIFS('Monthly Activity Log'!B$4:B$200,$B$3,'Monthly Activity Log'!H$4:H$200,"Legacy/CEF",'Monthly Activity Log'!I$4:I$200,"Reporting")),IF($B$3="All",COUNTIFS('Monthly Activity Log'!H$4:H$200,"Legacy/CEF",'Monthly Activity Log'!I$4:I$200,"Mentoring"),COUNTIFS('Monthly Activity Log'!B$4:B$200,$B$3,'Monthly Activity Log'!H$4:H$200,"Legacy/CEF",'Monthly Activity Log'!I$4:I$200,"Mentoring")),IF($B$3="All",COUNTIFS('Monthly Activity Log'!H$4:H$200,"Legacy/CEF",'Monthly Activity Log'!I$4:I$200,"Other"),COUNTIFS('Monthly Activity Log'!B$4:B$200,$B$3,'Monthly Activity Log'!H$4:H$200,"Legacy/CEF",'Monthly Activity Log'!I$4:I$200,"Other"))),"Admin/Config",IF(IF($B$3="All",COUNTIFS('Monthly Activity Log'!H$4:H$200,"Legacy/CEF",'Monthly Activity Log'!I$4:I$200,"Reporting"),COUNTIFS('Monthly Activity Log'!B$4:B$200,$B$3,'Monthly Activity Log'!H$4:H$200,"Legacy/CEF",'Monthly Activity Log'!I$4:I$200,"Reporting"))=MAX(IF($B$3="All",COUNTIFS('Monthly Activity Log'!H$4:H$200,"Legacy/CEF",'Monthly Activity Log'!I$4:I$200,"Project"),COUNTIFS('Monthly Activity Log'!B$4:B$200,$B$3,'Monthly Activity Log'!H$4:H$200,"Legacy/CEF",'Monthly Activity Log'!I$4:I$200,"Project")),IF($B$3="All",COUNTIFS('Monthly Activity Log'!H$4:H$200,"Legacy/CEF",'Monthly Activity Log'!I$4:I$200,"Incident/Bug Fix"),COUNTIFS('Monthly Activity Log'!B$4:B$200,$B$3,'Monthly Activity Log'!H$4:H$200,"Legacy/CEF",'Monthly Activity Log'!I$4:I$200,"Incident/Bug Fix")),IF($B$3="All",COUNTIFS('Monthly Activity Log'!H$4:H$200,"Legacy/CEF",'Monthly Activity Log'!I$4:I$200,"Change Request"),COUNTIFS('Monthly Activity Log'!B$4:B$200,$B$3,'Monthly Activity Log'!H$4:H$200,"Legacy/CEF",'Monthly Activity Log'!I$4:I$200,"Change Request")),IF($B$3="All",COUNTIFS('Monthly Activity Log'!H$4:H$200,"Legacy/CEF",'Monthly Activity Log'!I$4:I$200,"User Support"),COUNTIFS('Monthly Activity Log'!B$4:B$200,$B$3,'Monthly Activity Log'!H$4:H$200,"Legacy/CEF",'Monthly Activity Log'!I$4:I$200,"User Support")),IF($B$3="All",COUNTIFS('Monthly Activity Log'!H$4:H$200,"Legacy/CEF",'Monthly Activity Log'!I$4:I$200,"Admin/Config"),COUNTIFS('Monthly Activity Log'!B$4:B$200,$B$3,'Monthly Activity Log'!H$4:H$200,"Legacy/CEF",'Monthly Activity Log'!I$4:I$200,"Admin/Config")),IF($B$3="All",COUNTIFS('Monthly Activity Log'!H$4:H$200,"Legacy/CEF",'Monthly Activity Log'!I$4:I$200,"Reporting"),COUNTIFS('Monthly Activity Log'!B$4:B$200,$B$3,'Monthly Activity Log'!H$4:H$200,"Legacy/CEF",'Monthly Activity Log'!I$4:I$200,"Reporting")),IF($B$3="All",COUNTIFS('Monthly Activity Log'!H$4:H$200,"Legacy/CEF",'Monthly Activity Log'!I$4:I$200,"Mentoring"),COUNTIFS('Monthly Activity Log'!B$4:B$200,$B$3,'Monthly Activity Log'!H$4:H$200,"Legacy/CEF",'Monthly Activity Log'!I$4:I$200,"Mentoring")),IF($B$3="All",COUNTIFS('Monthly Activity Log'!H$4:H$200,"Legacy/CEF",'Monthly Activity Log'!I$4:I$200,"Other"),COUNTIFS('Monthly Activity Log'!B$4:B$200,$B$3,'Monthly Activity Log'!H$4:H$200,"Legacy/CEF",'Monthly Activity Log'!I$4:I$200,"Other"))),"Reporting",IF(IF($B$3="All",COUNTIFS('Monthly Activity Log'!H$4:H$200,"Legacy/CEF",'Monthly Activity Log'!I$4:I$200,"Mentoring"),COUNTIFS('Monthly Activity Log'!B$4:B$200,$B$3,'Monthly Activity Log'!H$4:H$200,"Legacy/CEF",'Monthly Activity Log'!I$4:I$200,"Mentoring"))=MAX(IF($B$3="All",COUNTIFS('Monthly Activity Log'!H$4:H$200,"Legacy/CEF",'Monthly Activity Log'!I$4:I$200,"Project"),COUNTIFS('Monthly Activity Log'!B$4:B$200,$B$3,'Monthly Activity Log'!H$4:H$200,"Legacy/CEF",'Monthly Activity Log'!I$4:I$200,"Project")),IF($B$3="All",COUNTIFS('Monthly Activity Log'!H$4:H$200,"Legacy/CEF",'Monthly Activity Log'!I$4:I$200,"Incident/Bug Fix"),COUNTIFS('Monthly Activity Log'!B$4:B$200,$B$3,'Monthly Activity Log'!H$4:H$200,"Legacy/CEF",'Monthly Activity Log'!I$4:I$200,"Incident/Bug Fix")),IF($B$3="All",COUNTIFS('Monthly Activity Log'!H$4:H$200,"Legacy/CEF",'Monthly Activity Log'!I$4:I$200,"Change Request"),COUNTIFS('Monthly Activity Log'!B$4:B$200,$B$3,'Monthly Activity Log'!H$4:H$200,"Legacy/CEF",'Monthly Activity Log'!I$4:I$200,"Change Request")),IF($B$3="All",COUNTIFS('Monthly Activity Log'!H$4:H$200,"Legacy/CEF",'Monthly Activity Log'!I$4:I$200,"User Support"),COUNTIFS('Monthly Activity Log'!B$4:B$200,$B$3,'Monthly Activity Log'!H$4:H$200,"Legacy/CEF",'Monthly Activity Log'!I$4:I$200,"User Support")),IF($B$3="All",COUNTIFS('Monthly Activity Log'!H$4:H$200,"Legacy/CEF",'Monthly Activity Log'!I$4:I$200,"Admin/Config"),COUNTIFS('Monthly Activity Log'!B$4:B$200,$B$3,'Monthly Activity Log'!H$4:H$200,"Legacy/CEF",'Monthly Activity Log'!I$4:I$200,"Admin/Config")),IF($B$3="All",COUNTIFS('Monthly Activity Log'!H$4:H$200,"Legacy/CEF",'Monthly Activity Log'!I$4:I$200,"Reporting"),COUNTIFS('Monthly Activity Log'!B$4:B$200,$B$3,'Monthly Activity Log'!H$4:H$200,"Legacy/CEF",'Monthly Activity Log'!I$4:I$200,"Reporting")),IF($B$3="All",COUNTIFS('Monthly Activity Log'!H$4:H$200,"Legacy/CEF",'Monthly Activity Log'!I$4:I$200,"Mentoring"),COUNTIFS('Monthly Activity Log'!B$4:B$200,$B$3,'Monthly Activity Log'!H$4:H$200,"Legacy/CEF",'Monthly Activity Log'!I$4:I$200,"Mentoring")),IF($B$3="All",COUNTIFS('Monthly Activity Log'!H$4:H$200,"Legacy/CEF",'Monthly Activity Log'!I$4:I$200,"Other"),COUNTIFS('Monthly Activity Log'!B$4:B$200,$B$3,'Monthly Activity Log'!H$4:H$200,"Legacy/CEF",'Monthly Activity Log'!I$4:I$200,"Other"))),"Mentoring",IF(IF($B$3="All",COUNTIFS('Monthly Activity Log'!H$4:H$200,"Legacy/CEF",'Monthly Activity Log'!I$4:I$200,"Other"),COUNTIFS('Monthly Activity Log'!B$4:B$200,$B$3,'Monthly Activity Log'!H$4:H$200,"Legacy/CEF",'Monthly Activity Log'!I$4:I$200,"Other"))=MAX(IF($B$3="All",COUNTIFS('Monthly Activity Log'!H$4:H$200,"Legacy/CEF",'Monthly Activity Log'!I$4:I$200,"Project"),COUNTIFS('Monthly Activity Log'!B$4:B$200,$B$3,'Monthly Activity Log'!H$4:H$200,"Legacy/CEF",'Monthly Activity Log'!I$4:I$200,"Project")),IF($B$3="All",COUNTIFS('Monthly Activity Log'!H$4:H$200,"Legacy/CEF",'Monthly Activity Log'!I$4:I$200,"Incident/Bug Fix"),COUNTIFS('Monthly Activity Log'!B$4:B$200,$B$3,'Monthly Activity Log'!H$4:H$200,"Legacy/CEF",'Monthly Activity Log'!I$4:I$200,"Incident/Bug Fix")),IF($B$3="All",COUNTIFS('Monthly Activity Log'!H$4:H$200,"Legacy/CEF",'Monthly Activity Log'!I$4:I$200,"Change Request"),COUNTIFS('Monthly Activity Log'!B$4:B$200,$B$3,'Monthly Activity Log'!H$4:H$200,"Legacy/CEF",'Monthly Activity Log'!I$4:I$200,"Change Request")),IF($B$3="All",COUNTIFS('Monthly Activity Log'!H$4:H$200,"Legacy/CEF",'Monthly Activity Log'!I$4:I$200,"User Support"),COUNTIFS('Monthly Activity Log'!B$4:B$200,$B$3,'Monthly Activity Log'!H$4:H$200,"Legacy/CEF",'Monthly Activity Log'!I$4:I$200,"User Support")),IF($B$3="All",COUNTIFS('Monthly Activity Log'!H$4:H$200,"Legacy/CEF",'Monthly Activity Log'!I$4:I$200,"Admin/Config"),COUNTIFS('Monthly Activity Log'!B$4:B$200,$B$3,'Monthly Activity Log'!H$4:H$200,"Legacy/CEF",'Monthly Activity Log'!I$4:I$200,"Admin/Config")),IF($B$3="All",COUNTIFS('Monthly Activity Log'!H$4:H$200,"Legacy/CEF",'Monthly Activity Log'!I$4:I$200,"Reporting"),COUNTIFS('Monthly Activity Log'!B$4:B$200,$B$3,'Monthly Activity Log'!H$4:H$200,"Legacy/CEF",'Monthly Activity Log'!I$4:I$200,"Reporting")),IF($B$3="All",COUNTIFS('Monthly Activity Log'!H$4:H$200,"Legacy/CEF",'Monthly Activity Log'!I$4:I$200,"Mentoring"),COUNTIFS('Monthly Activity Log'!B$4:B$200,$B$3,'Monthly Activity Log'!H$4:H$200,"Legacy/CEF",'Monthly Activity Log'!I$4:I$200,"Mentoring")),IF($B$3="All",COUNTIFS('Monthly Activity Log'!H$4:H$200,"Legacy/CEF",'Monthly Activity Log'!I$4:I$200,"Other"),COUNTIFS('Monthly Activity Log'!B$4:B$200,$B$3,'Monthly Activity Log'!H$4:H$200,"Legacy/CEF",'Monthly Activity Log'!I$4:I$200,"Other"))),"Other","-"))))))))) | J8: =D8+E8
A9: SANPC/SFF | B9: =IF($B$3="All",COUNTIF('Monthly Activity Log'!H$4:H$200,"SANPC/SFF"),COUNTIFS('Monthly Activity Log'!B$4:B$200,$B$3,'Monthly Activity Log'!H$4:H$200,"SANPC/SFF")) | C9: =IF($B$3="All",COUNTIFS('Monthly Activity Log'!H$4:H$200,"SANPC/SFF",'Monthly Activity Log'!K$4:K$200,"Completed"),COUNTIFS('Monthly Activity Log'!B$4:B$200,$B$3,'Monthly Activity Log'!H$4:H$200,"SANPC/SFF",'Monthly Activity Log'!K$4:K$200,"Completed")) | D9: =IF($B$3="All",COUNTIFS('Monthly Activity Log'!H$4:H$200,"SANPC/SFF",'Monthly Activity Log'!K$4:K$200,"In Progress"),COUNTIFS('Monthly Activity Log'!B$4:B$200,$B$3,'Monthly Activity Log'!H$4:H$200,"SANPC/SFF",'Monthly Activity Log'!K$4:K$200,"In Progress")) | E9: =IF($B$3="All",COUNTIFS('Monthly Activity Log'!H$4:H$200,"SANPC/SFF",'Monthly Activity Log'!K$4:K$200,"Pending"),COUNTIFS('Monthly Activity Log'!B$4:B$200,$B$3,'Monthly Activity Log'!H$4:H$200,"SANPC/SFF",'Monthly Activity Log'!K$4:K$200,"Pending")) | F9: =IFERROR(C9/B9,0) | G9: =IFERROR(B9/'Summary Dashboard'!A7,0) | H9: =IF(B9=0,"-",IF(IF($B$3="All",COUNTIFS('Monthly Activity Log'!H$4:H$200,"SANPC/SFF",'Monthly Activity Log'!C$4:C$200,"Shennaz"),COUNTIFS('Monthly Activity Log'!B$4:B$200,$B$3,'Monthly Activity Log'!H$4:H$200,"SANPC/SFF",'Monthly Activity Log'!C$4:C$200,"Shennaz"))=MAX(IF($B$3="All",COUNTIFS('Monthly Activity Log'!H$4:H$200,"SANPC/SFF",'Monthly Activity Log'!C$4:C$200,"Shennaz"),COUNTIFS('Monthly Activity Log'!B$4:B$200,$B$3,'Monthly Activity Log'!H$4:H$200,"SANPC/SFF",'Monthly Activity Log'!C$4:C$200,"Shennaz")),IF($B$3="All",COUNTIFS('Monthly Activity Log'!H$4:H$200,"SANPC/SFF",'Monthly Activity Log'!C$4:C$200,"Nyameka"),COUNTIFS('Monthly Activity Log'!B$4:B$200,$B$3,'Monthly Activity Log'!H$4:H$200,"SANPC/SFF",'Monthly Activity Log'!C$4:C$200,"Nyameka")),IF($B$3="All",COUNTIFS('Monthly Activity Log'!H$4:H$200,"SANPC/SFF",'Monthly Activity Log'!C$4:C$200,"Lindiwe"),COUNTIFS('Monthly Activity Log'!B$4:B$200,$B$3,'Monthly Activity Log'!H$4:H$200,"SANPC/SFF",'Monthly Activity Log'!C$4:C$200,"Lindiwe")),IF($B$3="All",COUNTIFS('Monthly Activity Log'!H$4:H$200,"SANPC/SFF",'Monthly Activity Log'!C$4:C$200,"T A Willems"),COUNTIFS('Monthly Activity Log'!B$4:B$200,$B$3,'Monthly Activity Log'!H$4:H$200,"SANPC/SFF",'Monthly Activity Log'!C$4:C$200,"T A Willems")),IF($B$3="All",COUNTIFS('Monthly Activity Log'!H$4:H$200,"SANPC/SFF",'Monthly Activity Log'!C$4:C$200,"Mphatheleni Matidze"),COUNTIFS('Monthly Activity Log'!B$4:B$200,$B$3,'Monthly Activity Log'!H$4:H$200,"SANPC/SFF",'Monthly Activity Log'!C$4:C$200,"Mphatheleni Matidze"))),"Shennaz",IF(IF($B$3="All",COUNTIFS('Monthly Activity Log'!H$4:H$200,"SANPC/SFF",'Monthly Activity Log'!C$4:C$200,"Nyameka"),COUNTIFS('Monthly Activity Log'!B$4:B$200,$B$3,'Monthly Activity Log'!H$4:H$200,"SANPC/SFF",'Monthly Activity Log'!C$4:C$200,"Nyameka"))=MAX(IF($B$3="All",COUNTIFS('Monthly Activity Log'!H$4:H$200,"SANPC/SFF",'Monthly Activity Log'!C$4:C$200,"Shennaz"),COUNTIFS('Monthly Activity Log'!B$4:B$200,$B$3,'Monthly Activity Log'!H$4:H$200,"SANPC/SFF",'Monthly Activity Log'!C$4:C$200,"Shennaz")),IF($B$3="All",COUNTIFS('Monthly Activity Log'!H$4:H$200,"SANPC/SFF",'Monthly Activity Log'!C$4:C$200,"Nyameka"),COUNTIFS('Monthly Activity Log'!B$4:B$200,$B$3,'Monthly Activity Log'!H$4:H$200,"SANPC/SFF",'Monthly Activity Log'!C$4:C$200,"Nyameka")),IF($B$3="All",COUNTIFS('Monthly Activity Log'!H$4:H$200,"SANPC/SFF",'Monthly Activity Log'!C$4:C$200,"Lindiwe"),COUNTIFS('Monthly Activity Log'!B$4:B$200,$B$3,'Monthly Activity Log'!H$4:H$200,"SANPC/SFF",'Monthly Activity Log'!C$4:C$200,"Lindiwe")),IF($B$3="All",COUNTIFS('Monthly Activity Log'!H$4:H$200,"SANPC/SFF",'Monthly Activity Log'!C$4:C$200,"T A Willems"),COUNTIFS('Monthly Activity Log'!B$4:B$200,$B$3,'Monthly Activity Log'!H$4:H$200,"SANPC/SFF",'Monthly Activity Log'!C$4:C$200,"T A Willems")),IF($B$3="All",COUNTIFS('Monthly Activity Log'!H$4:H$200,"SANPC/SFF",'Monthly Activity Log'!C$4:C$200,"Mphatheleni Matidze"),COUNTIFS('Monthly Activity Log'!B$4:B$200,$B$3,'Monthly Activity Log'!H$4:H$200,"SANPC/SFF",'Monthly Activity Log'!C$4:C$200,"Mphatheleni Matidze"))),"Nyameka",IF(IF($B$3="All",COUNTIFS('Monthly Activity Log'!H$4:H$200,"SANPC/SFF",'Monthly Activity Log'!C$4:C$200,"Lindiwe"),COUNTIFS('Monthly Activity Log'!B$4:B$200,$B$3,'Monthly Activity Log'!H$4:H$200,"SANPC/SFF",'Monthly Activity Log'!C$4:C$200,"Lindiwe"))=MAX(IF($B$3="All",COUNTIFS('Monthly Activity Log'!H$4:H$200,"SANPC/SFF",'Monthly Activity Log'!C$4:C$200,"Shennaz"),COUNTIFS('Monthly Activity Log'!B$4:B$200,$B$3,'Monthly Activity Log'!H$4:H$200,"SANPC/SFF",'Monthly Activity Log'!C$4:C$200,"Shennaz")),IF($B$3="All",COUNTIFS('Monthly Activity Log'!H$4:H$200,"SANPC/SFF",'Monthly Activity Log'!C$4:C$200,"Nyameka"),COUNTIFS('Monthly Activity Log'!B$4:B$200,$B$3,'Monthly Activity Log'!H$4:H$200,"SANPC/SFF",'Monthly Activity Log'!C$4:C$200,"Nyameka")),IF($B$3="All",COUNTIFS('Monthly Activity Log'!H$4:H$200,"SANPC/SFF",'Monthly Activity Log'!C$4:C$200,"Lindiwe"),COUNTIFS('Monthly Activity Log'!B$4:B$200,$B$3,'Monthly Activity Log'!H$4:H$200,"SANPC/SFF",'Monthly Activity Log'!C$4:C$200,"Lindiwe")),IF($B$3="All",COUNTIFS('Monthly Activity Log'!H$4:H$200,"SANPC/SFF",'Monthly Activity Log'!C$4:C$200,"T A Willems"),COUNTIFS('Monthly Activity Log'!B$4:B$200,$B$3,'Monthly Activity Log'!H$4:H$200,"SANPC/SFF",'Monthly Activity Log'!C$4:C$200,"T A Willems")),IF($B$3="All",COUNTIFS('Monthly Activity Log'!H$4:H$200,"SANPC/SFF",'Monthly Activity Log'!C$4:C$200,"Mphatheleni Matidze"),COUNTIFS('Monthly Activity Log'!B$4:B$200,$B$3,'Monthly Activity Log'!H$4:H$200,"SANPC/SFF",'Monthly Activity Log'!C$4:C$200,"Mphatheleni Matidze"))),"Lindiwe",IF(IF($B$3="All",COUNTIFS('Monthly Activity Log'!H$4:H$200,"SANPC/SFF",'Monthly Activity Log'!C$4:C$200,"T A Willems"),COUNTIFS('Monthly Activity Log'!B$4:B$200,$B$3,'Monthly Activity Log'!H$4:H$200,"SANPC/SFF",'Monthly Activity Log'!C$4:C$200,"T A Willems"))=MAX(IF($B$3="All",COUNTIFS('Monthly Activity Log'!H$4:H$200,"SANPC/SFF",'Monthly Activity Log'!C$4:C$200,"Shennaz"),COUNTIFS('Monthly Activity Log'!B$4:B$200,$B$3,'Monthly Activity Log'!H$4:H$200,"SANPC/SFF",'Monthly Activity Log'!C$4:C$200,"Shennaz")),IF($B$3="All",COUNTIFS('Monthly Activity Log'!H$4:H$200,"SANPC/SFF",'Monthly Activity Log'!C$4:C$200,"Nyameka"),COUNTIFS('Monthly Activity Log'!B$4:B$200,$B$3,'Monthly Activity Log'!H$4:H$200,"SANPC/SFF",'Monthly Activity Log'!C$4:C$200,"Nyameka")),IF($B$3="All",COUNTIFS('Monthly Activity Log'!H$4:H$200,"SANPC/SFF",'Monthly Activity Log'!C$4:C$200,"Lindiwe"),COUNTIFS('Monthly Activity Log'!B$4:B$200,$B$3,'Monthly Activity Log'!H$4:H$200,"SANPC/SFF",'Monthly Activity Log'!C$4:C$200,"Lindiwe")),IF($B$3="All",COUNTIFS('Monthly Activity Log'!H$4:H$200,"SANPC/SFF",'Monthly Activity Log'!C$4:C$200,"T A Willems"),COUNTIFS('Monthly Activity Log'!B$4:B$200,$B$3,'Monthly Activity Log'!H$4:H$200,"SANPC/SFF",'Monthly Activity Log'!C$4:C$200,"T A Willems")),IF($B$3="All",COUNTIFS('Monthly Activity Log'!H$4:H$200,"SANPC/SFF",'Monthly Activity Log'!C$4:C$200,"Mphatheleni Matidze"),COUNTIFS('Monthly Activity Log'!B$4:B$200,$B$3,'Monthly Activity Log'!H$4:H$200,"SANPC/SFF",'Monthly Activity Log'!C$4:C$200,"Mphatheleni Matidze"))),"T A Willems",IF(IF($B$3="All",COUNTIFS('Monthly Activity Log'!H$4:H$200,"SANPC/SFF",'Monthly Activity Log'!C$4:C$200,"Mphatheleni Matidze"),COUNTIFS('Monthly Activity Log'!B$4:B$200,$B$3,'Monthly Activity Log'!H$4:H$200,"SANPC/SFF",'Monthly Activity Log'!C$4:C$200,"Mphatheleni Matidze"))=MAX(IF($B$3="All",COUNTIFS('Monthly Activity Log'!H$4:H$200,"SANPC/SFF",'Monthly Activity Log'!C$4:C$200,"Shennaz"),COUNTIFS('Monthly Activity Log'!B$4:B$200,$B$3,'Monthly Activity Log'!H$4:H$200,"SANPC/SFF",'Monthly Activity Log'!C$4:C$200,"Shennaz")),IF($B$3="All",COUNTIFS('Monthly Activity Log'!H$4:H$200,"SANPC/SFF",'Monthly Activity Log'!C$4:C$200,"Nyameka"),COUNTIFS('Monthly Activity Log'!B$4:B$200,$B$3,'Monthly Activity Log'!H$4:H$200,"SANPC/SFF",'Monthly Activity Log'!C$4:C$200,"Nyameka")),IF($B$3="All",COUNTIFS('Monthly Activity Log'!H$4:H$200,"SANPC/SFF",'Monthly Activity Log'!C$4:C$200,"Lindiwe"),COUNTIFS('Monthly Activity Log'!B$4:B$200,$B$3,'Monthly Activity Log'!H$4:H$200,"SANPC/SFF",'Monthly Activity Log'!C$4:C$200,"Lindiwe")),IF($B$3="All",COUNTIFS('Monthly Activity Log'!H$4:H$200,"SANPC/SFF",'Monthly Activity Log'!C$4:C$200,"T A Willems"),COUNTIFS('Monthly Activity Log'!B$4:B$200,$B$3,'Monthly Activity Log'!H$4:H$200,"SANPC/SFF",'Monthly Activity Log'!C$4:C$200,"T A Willems")),IF($B$3="All",COUNTIFS('Monthly Activity Log'!H$4:H$200,"SANPC/SFF",'Monthly Activity Log'!C$4:C$200,"Mphatheleni Matidze"),COUNTIFS('Monthly Activity Log'!B$4:B$200,$B$3,'Monthly Activity Log'!H$4:H$200,"SANPC/SFF",'Monthly Activity Log'!C$4:C$200,"Mphatheleni Matidze"))),"Mphatheleni Matidze","-")))))) | I9: =IF(B9=0,"-",IF(IF($B$3="All",COUNTIFS('Monthly Activity Log'!H$4:H$200,"SANPC/SFF",'Monthly Activity Log'!I$4:I$200,"Project"),COUNTIFS('Monthly Activity Log'!B$4:B$200,$B$3,'Monthly Activity Log'!H$4:H$200,"SANPC/SFF",'Monthly Activity Log'!I$4:I$200,"Project"))=MAX(IF($B$3="All",COUNTIFS('Monthly Activity Log'!H$4:H$200,"SANPC/SFF",'Monthly Activity Log'!I$4:I$200,"Project"),COUNTIFS('Monthly Activity Log'!B$4:B$200,$B$3,'Monthly Activity Log'!H$4:H$200,"SANPC/SFF",'Monthly Activity Log'!I$4:I$200,"Project")),IF($B$3="All",COUNTIFS('Monthly Activity Log'!H$4:H$200,"SANPC/SFF",'Monthly Activity Log'!I$4:I$200,"Incident/Bug Fix"),COUNTIFS('Monthly Activity Log'!B$4:B$200,$B$3,'Monthly Activity Log'!H$4:H$200,"SANPC/SFF",'Monthly Activity Log'!I$4:I$200,"Incident/Bug Fix")),IF($B$3="All",COUNTIFS('Monthly Activity Log'!H$4:H$200,"SANPC/SFF",'Monthly Activity Log'!I$4:I$200,"Change Request"),COUNTIFS('Monthly Activity Log'!B$4:B$200,$B$3,'Monthly Activity Log'!H$4:H$200,"SANPC/SFF",'Monthly Activity Log'!I$4:I$200,"Change Request")),IF($B$3="All",COUNTIFS('Monthly Activity Log'!H$4:H$200,"SANPC/SFF",'Monthly Activity Log'!I$4:I$200,"User Support"),COUNTIFS('Monthly Activity Log'!B$4:B$200,$B$3,'Monthly Activity Log'!H$4:H$200,"SANPC/SFF",'Monthly Activity Log'!I$4:I$200,"User Support")),IF($B$3="All",COUNTIFS('Monthly Activity Log'!H$4:H$200,"SANPC/SFF",'Monthly Activity Log'!I$4:I$200,"Admin/Config"),COUNTIFS('Monthly Activity Log'!B$4:B$200,$B$3,'Monthly Activity Log'!H$4:H$200,"SANPC/SFF",'Monthly Activity Log'!I$4:I$200,"Admin/Config")),IF($B$3="All",COUNTIFS('Monthly Activity Log'!H$4:H$200,"SANPC/SFF",'Monthly Activity Log'!I$4:I$200,"Reporting"),COUNTIFS('Monthly Activity Log'!B$4:B$200,$B$3,'Monthly Activity Log'!H$4:H$200,"SANPC/SFF",'Monthly Activity Log'!I$4:I$200,"Reporting")),IF($B$3="All",COUNTIFS('Monthly Activity Log'!H$4:H$200,"SANPC/SFF",'Monthly Activity Log'!I$4:I$200,"Mentoring"),COUNTIFS('Monthly Activity Log'!B$4:B$200,$B$3,'Monthly Activity Log'!H$4:H$200,"SANPC/SFF",'Monthly Activity Log'!I$4:I$200,"Mentoring")),IF($B$3="All",COUNTIFS('Monthly Activity Log'!H$4:H$200,"SANPC/SFF",'Monthly Activity Log'!I$4:I$200,"Other"),COUNTIFS('Monthly Activity Log'!B$4:B$200,$B$3,'Monthly Activity Log'!H$4:H$200,"SANPC/SFF",'Monthly Activity Log'!I$4:I$200,"Other"))),"Project",IF(IF($B$3="All",COUNTIFS('Monthly Activity Log'!H$4:H$200,"SANPC/SFF",'Monthly Activity Log'!I$4:I$200,"Incident/Bug Fix"),COUNTIFS('Monthly Activity Log'!B$4:B$200,$B$3,'Monthly Activity Log'!H$4:H$200,"SANPC/SFF",'Monthly Activity Log'!I$4:I$200,"Incident/Bug Fix"))=MAX(IF($B$3="All",COUNTIFS('Monthly Activity Log'!H$4:H$200,"SANPC/SFF",'Monthly Activity Log'!I$4:I$200,"Project"),COUNTIFS('Monthly Activity Log'!B$4:B$200,$B$3,'Monthly Activity Log'!H$4:H$200,"SANPC/SFF",'Monthly Activity Log'!I$4:I$200,"Project")),IF($B$3="All",COUNTIFS('Monthly Activity Log'!H$4:H$200,"SANPC/SFF",'Monthly Activity Log'!I$4:I$200,"Incident/Bug Fix"),COUNTIFS('Monthly Activity Log'!B$4:B$200,$B$3,'Monthly Activity Log'!H$4:H$200,"SANPC/SFF",'Monthly Activity Log'!I$4:I$200,"Incident/Bug Fix")),IF($B$3="All",COUNTIFS('Monthly Activity Log'!H$4:H$200,"SANPC/SFF",'Monthly Activity Log'!I$4:I$200,"Change Request"),COUNTIFS('Monthly Activity Log'!B$4:B$200,$B$3,'Monthly Activity Log'!H$4:H$200,"SANPC/SFF",'Monthly Activity Log'!I$4:I$200,"Change Request")),IF($B$3="All",COUNTIFS('Monthly Activity Log'!H$4:H$200,"SANPC/SFF",'Monthly Activity Log'!I$4:I$200,"User Support"),COUNTIFS('Monthly Activity Log'!B$4:B$200,$B$3,'Monthly Activity Log'!H$4:H$200,"SANPC/SFF",'Monthly Activity Log'!I$4:I$200,"User Support")),IF($B$3="All",COUNTIFS('Monthly Activity Log'!H$4:H$200,"SANPC/SFF",'Monthly Activity Log'!I$4:I$200,"Admin/Config"),COUNTIFS('Monthly Activity Log'!B$4:B$200,$B$3,'Monthly Activity Log'!H$4:H$200,"SANPC/SFF",'Monthly Activity Log'!I$4:I$200,"Admin/Config")),IF($B$3="All",COUNTIFS('Monthly Activity Log'!H$4:H$200,"SANPC/SFF",'Monthly Activity Log'!I$4:I$200,"Reporting"),COUNTIFS('Monthly Activity Log'!B$4:B$200,$B$3,'Monthly Activity Log'!H$4:H$200,"SANPC/SFF",'Monthly Activity Log'!I$4:I$200,"Reporting")),IF($B$3="All",COUNTIFS('Monthly Activity Log'!H$4:H$200,"SANPC/SFF",'Monthly Activity Log'!I$4:I$200,"Mentoring"),COUNTIFS('Monthly Activity Log'!B$4:B$200,$B$3,'Monthly Activity Log'!H$4:H$200,"SANPC/SFF",'Monthly Activity Log'!I$4:I$200,"Mentoring")),IF($B$3="All",COUNTIFS('Monthly Activity Log'!H$4:H$200,"SANPC/SFF",'Monthly Activity Log'!I$4:I$200,"Other"),COUNTIFS('Monthly Activity Log'!B$4:B$200,$B$3,'Monthly Activity Log'!H$4:H$200,"SANPC/SFF",'Monthly Activity Log'!I$4:I$200,"Other"))),"Incident/Bug Fix",IF(IF($B$3="All",COUNTIFS('Monthly Activity Log'!H$4:H$200,"SANPC/SFF",'Monthly Activity Log'!I$4:I$200,"Change Request"),COUNTIFS('Monthly Activity Log'!B$4:B$200,$B$3,'Monthly Activity Log'!H$4:H$200,"SANPC/SFF",'Monthly Activity Log'!I$4:I$200,"Change Request"))=MAX(IF($B$3="All",COUNTIFS('Monthly Activity Log'!H$4:H$200,"SANPC/SFF",'Monthly Activity Log'!I$4:I$200,"Project"),COUNTIFS('Monthly Activity Log'!B$4:B$200,$B$3,'Monthly Activity Log'!H$4:H$200,"SANPC/SFF",'Monthly Activity Log'!I$4:I$200,"Project")),IF($B$3="All",COUNTIFS('Monthly Activity Log'!H$4:H$200,"SANPC/SFF",'Monthly Activity Log'!I$4:I$200,"Incident/Bug Fix"),COUNTIFS('Monthly Activity Log'!B$4:B$200,$B$3,'Monthly Activity Log'!H$4:H$200,"SANPC/SFF",'Monthly Activity Log'!I$4:I$200,"Incident/Bug Fix")),IF($B$3="All",COUNTIFS('Monthly Activity Log'!H$4:H$200,"SANPC/SFF",'Monthly Activity Log'!I$4:I$200,"Change Request"),COUNTIFS('Monthly Activity Log'!B$4:B$200,$B$3,'Monthly Activity Log'!H$4:H$200,"SANPC/SFF",'Monthly Activity Log'!I$4:I$200,"Change Request")),IF($B$3="All",COUNTIFS('Monthly Activity Log'!H$4:H$200,"SANPC/SFF",'Monthly Activity Log'!I$4:I$200,"User Support"),COUNTIFS('Monthly Activity Log'!B$4:B$200,$B$3,'Monthly Activity Log'!H$4:H$200,"SANPC/SFF",'Monthly Activity Log'!I$4:I$200,"User Support")),IF($B$3="All",COUNTIFS('Monthly Activity Log'!H$4:H$200,"SANPC/SFF",'Monthly Activity Log'!I$4:I$200,"Admin/Config"),COUNTIFS('Monthly Activity Log'!B$4:B$200,$B$3,'Monthly Activity Log'!H$4:H$200,"SANPC/SFF",'Monthly Activity Log'!I$4:I$200,"Admin/Config")),IF($B$3="All",COUNTIFS('Monthly Activity Log'!H$4:H$200,"SANPC/SFF",'Monthly Activity Log'!I$4:I$200,"Reporting"),COUNTIFS('Monthly Activity Log'!B$4:B$200,$B$3,'Monthly Activity Log'!H$4:H$200,"SANPC/SFF",'Monthly Activity Log'!I$4:I$200,"Reporting")),IF($B$3="All",COUNTIFS('Monthly Activity Log'!H$4:H$200,"SANPC/SFF",'Monthly Activity Log'!I$4:I$200,"Mentoring"),COUNTIFS('Monthly Activity Log'!B$4:B$200,$B$3,'Monthly Activity Log'!H$4:H$200,"SANPC/SFF",'Monthly Activity Log'!I$4:I$200,"Mentoring")),IF($B$3="All",COUNTIFS('Monthly Activity Log'!H$4:H$200,"SANPC/SFF",'Monthly Activity Log'!I$4:I$200,"Other"),COUNTIFS('Monthly Activity Log'!B$4:B$200,$B$3,'Monthly Activity Log'!H$4:H$200,"SANPC/SFF",'Monthly Activity Log'!I$4:I$200,"Other"))),"Change Request",IF(IF($B$3="All",COUNTIFS('Monthly Activity Log'!H$4:H$200,"SANPC/SFF",'Monthly Activity Log'!I$4:I$200,"User Support"),COUNTIFS('Monthly Activity Log'!B$4:B$200,$B$3,'Monthly Activity Log'!H$4:H$200,"SANPC/SFF",'Monthly Activity Log'!I$4:I$200,"User Support"))=MAX(IF($B$3="All",COUNTIFS('Monthly Activity Log'!H$4:H$200,"SANPC/SFF",'Monthly Activity Log'!I$4:I$200,"Project"),COUNTIFS('Monthly Activity Log'!B$4:B$200,$B$3,'Monthly Activity Log'!H$4:H$200,"SANPC/SFF",'Monthly Activity Log'!I$4:I$200,"Project")),IF($B$3="All",COUNTIFS('Monthly Activity Log'!H$4:H$200,"SANPC/SFF",'Monthly Activity Log'!I$4:I$200,"Incident/Bug Fix"),COUNTIFS('Monthly Activity Log'!B$4:B$200,$B$3,'Monthly Activity Log'!H$4:H$200,"SANPC/SFF",'Monthly Activity Log'!I$4:I$200,"Incident/Bug Fix")),IF($B$3="All",COUNTIFS('Monthly Activity Log'!H$4:H$200,"SANPC/SFF",'Monthly Activity Log'!I$4:I$200,"Change Request"),COUNTIFS('Monthly Activity Log'!B$4:B$200,$B$3,'Monthly Activity Log'!H$4:H$200,"SANPC/SFF",'Monthly Activity Log'!I$4:I$200,"Change Request")),IF($B$3="All",COUNTIFS('Monthly Activity Log'!H$4:H$200,"SANPC/SFF",'Monthly Activity Log'!I$4:I$200,"User Support"),COUNTIFS('Monthly Activity Log'!B$4:B$200,$B$3,'Monthly Activity Log'!H$4:H$200,"SANPC/SFF",'Monthly Activity Log'!I$4:I$200,"User Support")),IF($B$3="All",COUNTIFS('Monthly Activity Log'!H$4:H$200,"SANPC/SFF",'Monthly Activity Log'!I$4:I$200,"Admin/Config"),COUNTIFS('Monthly Activity Log'!B$4:B$200,$B$3,'Monthly Activity Log'!H$4:H$200,"SANPC/SFF",'Monthly Activity Log'!I$4:I$200,"Admin/Config")),IF($B$3="All",COUNTIFS('Monthly Activity Log'!H$4:H$200,"SANPC/SFF",'Monthly Activity Log'!I$4:I$200,"Reporting"),COUNTIFS('Monthly Activity Log'!B$4:B$200,$B$3,'Monthly Activity Log'!H$4:H$200,"SANPC/SFF",'Monthly Activity Log'!I$4:I$200,"Reporting")),IF($B$3="All",COUNTIFS('Monthly Activity Log'!H$4:H$200,"SANPC/SFF",'Monthly Activity Log'!I$4:I$200,"Mentoring"),COUNTIFS('Monthly Activity Log'!B$4:B$200,$B$3,'Monthly Activity Log'!H$4:H$200,"SANPC/SFF",'Monthly Activity Log'!I$4:I$200,"Mentoring")),IF($B$3="All",COUNTIFS('Monthly Activity Log'!H$4:H$200,"SANPC/SFF",'Monthly Activity Log'!I$4:I$200,"Other"),COUNTIFS('Monthly Activity Log'!B$4:B$200,$B$3,'Monthly Activity Log'!H$4:H$200,"SANPC/SFF",'Monthly Activity Log'!I$4:I$200,"Other"))),"User Support",IF(IF($B$3="All",COUNTIFS('Monthly Activity Log'!H$4:H$200,"SANPC/SFF",'Monthly Activity Log'!I$4:I$200,"Admin/Config"),COUNTIFS('Monthly Activity Log'!B$4:B$200,$B$3,'Monthly Activity Log'!H$4:H$200,"SANPC/SFF",'Monthly Activity Log'!I$4:I$200,"Admin/Config"))=MAX(IF($B$3="All",COUNTIFS('Monthly Activity Log'!H$4:H$200,"SANPC/SFF",'Monthly Activity Log'!I$4:I$200,"Project"),COUNTIFS('Monthly Activity Log'!B$4:B$200,$B$3,'Monthly Activity Log'!H$4:H$200,"SANPC/SFF",'Monthly Activity Log'!I$4:I$200,"Project")),IF($B$3="All",COUNTIFS('Monthly Activity Log'!H$4:H$200,"SANPC/SFF",'Monthly Activity Log'!I$4:I$200,"Incident/Bug Fix"),COUNTIFS('Monthly Activity Log'!B$4:B$200,$B$3,'Monthly Activity Log'!H$4:H$200,"SANPC/SFF",'Monthly Activity Log'!I$4:I$200,"Incident/Bug Fix")),IF($B$3="All",COUNTIFS('Monthly Activity Log'!H$4:H$200,"SANPC/SFF",'Monthly Activity Log'!I$4:I$200,"Change Request"),COUNTIFS('Monthly Activity Log'!B$4:B$200,$B$3,'Monthly Activity Log'!H$4:H$200,"SANPC/SFF",'Monthly Activity Log'!I$4:I$200,"Change Request")),IF($B$3="All",COUNTIFS('Monthly Activity Log'!H$4:H$200,"SANPC/SFF",'Monthly Activity Log'!I$4:I$200,"User Support"),COUNTIFS('Monthly Activity Log'!B$4:B$200,$B$3,'Monthly Activity Log'!H$4:H$200,"SANPC/SFF",'Monthly Activity Log'!I$4:I$200,"User Support")),IF($B$3="All",COUNTIFS('Monthly Activity Log'!H$4:H$200,"SANPC/SFF",'Monthly Activity Log'!I$4:I$200,"Admin/Config"),COUNTIFS('Monthly Activity Log'!B$4:B$200,$B$3,'Monthly Activity Log'!H$4:H$200,"SANPC/SFF",'Monthly Activity Log'!I$4:I$200,"Admin/Config")),IF($B$3="All",COUNTIFS('Monthly Activity Log'!H$4:H$200,"SANPC/SFF",'Monthly Activity Log'!I$4:I$200,"Reporting"),COUNTIFS('Monthly Activity Log'!B$4:B$200,$B$3,'Monthly Activity Log'!H$4:H$200,"SANPC/SFF",'Monthly Activity Log'!I$4:I$200,"Reporting")),IF($B$3="All",COUNTIFS('Monthly Activity Log'!H$4:H$200,"SANPC/SFF",'Monthly Activity Log'!I$4:I$200,"Mentoring"),COUNTIFS('Monthly Activity Log'!B$4:B$200,$B$3,'Monthly Activity Log'!H$4:H$200,"SANPC/SFF",'Monthly Activity Log'!I$4:I$200,"Mentoring")),IF($B$3="All",COUNTIFS('Monthly Activity Log'!H$4:H$200,"SANPC/SFF",'Monthly Activity Log'!I$4:I$200,"Other"),COUNTIFS('Monthly Activity Log'!B$4:B$200,$B$3,'Monthly Activity Log'!H$4:H$200,"SANPC/SFF",'Monthly Activity Log'!I$4:I$200,"Other"))),"Admin/Config",IF(IF($B$3="All",COUNTIFS('Monthly Activity Log'!H$4:H$200,"SANPC/SFF",'Monthly Activity Log'!I$4:I$200,"Reporting"),COUNTIFS('Monthly Activity Log'!B$4:B$200,$B$3,'Monthly Activity Log'!H$4:H$200,"SANPC/SFF",'Monthly Activity Log'!I$4:I$200,"Reporting"))=MAX(IF($B$3="All",COUNTIFS('Monthly Activity Log'!H$4:H$200,"SANPC/SFF",'Monthly Activity Log'!I$4:I$200,"Project"),COUNTIFS('Monthly Activity Log'!B$4:B$200,$B$3,'Monthly Activity Log'!H$4:H$200,"SANPC/SFF",'Monthly Activity Log'!I$4:I$200,"Project")),IF($B$3="All",COUNTIFS('Monthly Activity Log'!H$4:H$200,"SANPC/SFF",'Monthly Activity Log'!I$4:I$200,"Incident/Bug Fix"),COUNTIFS('Monthly Activity Log'!B$4:B$200,$B$3,'Monthly Activity Log'!H$4:H$200,"SANPC/SFF",'Monthly Activity Log'!I$4:I$200,"Incident/Bug Fix")),IF($B$3="All",COUNTIFS('Monthly Activity Log'!H$4:H$200,"SANPC/SFF",'Monthly Activity Log'!I$4:I$200,"Change Request"),COUNTIFS('Monthly Activity Log'!B$4:B$200,$B$3,'Monthly Activity Log'!H$4:H$200,"SANPC/SFF",'Monthly Activity Log'!I$4:I$200,"Change Request")),IF($B$3="All",COUNTIFS('Monthly Activity Log'!H$4:H$200,"SANPC/SFF",'Monthly Activity Log'!I$4:I$200,"User Support"),COUNTIFS('Monthly Activity Log'!B$4:B$200,$B$3,'Monthly Activity Log'!H$4:H$200,"SANPC/SFF",'Monthly Activity Log'!I$4:I$200,"User Support")),IF($B$3="All",COUNTIFS('Monthly Activity Log'!H$4:H$200,"SANPC/SFF",'Monthly Activity Log'!I$4:I$200,"Admin/Config"),COUNTIFS('Monthly Activity Log'!B$4:B$200,$B$3,'Monthly Activity Log'!H$4:H$200,"SANPC/SFF",'Monthly Activity Log'!I$4:I$200,"Admin/Config")),IF($B$3="All",COUNTIFS('Monthly Activity Log'!H$4:H$200,"SANPC/SFF",'Monthly Activity Log'!I$4:I$200,"Reporting"),COUNTIFS('Monthly Activity Log'!B$4:B$200,$B$3,'Monthly Activity Log'!H$4:H$200,"SANPC/SFF",'Monthly Activity Log'!I$4:I$200,"Reporting")),IF($B$3="All",COUNTIFS('Monthly Activity Log'!H$4:H$200,"SANPC/SFF",'Monthly Activity Log'!I$4:I$200,"Mentoring"),COUNTIFS('Monthly Activity Log'!B$4:B$200,$B$3,'Monthly Activity Log'!H$4:H$200,"SANPC/SFF",'Monthly Activity Log'!I$4:I$200,"Mentoring")),IF($B$3="All",COUNTIFS('Monthly Activity Log'!H$4:H$200,"SANPC/SFF",'Monthly Activity Log'!I$4:I$200,"Other"),COUNTIFS('Monthly Activity Log'!B$4:B$200,$B$3,'Monthly Activity Log'!H$4:H$200,"SANPC/SFF",'Monthly Activity Log'!I$4:I$200,"Other"))),"Reporting",IF(IF($B$3="All",COUNTIFS('Monthly Activity Log'!H$4:H$200,"SANPC/SFF",'Monthly Activity Log'!I$4:I$200,"Mentoring"),COUNTIFS('Monthly Activity Log'!B$4:B$200,$B$3,'Monthly Activity Log'!H$4:H$200,"SANPC/SFF",'Monthly Activity Log'!I$4:I$200,"Mentoring"))=MAX(IF($B$3="All",COUNTIFS('Monthly Activity Log'!H$4:H$200,"SANPC/SFF",'Monthly Activity Log'!I$4:I$200,"Project"),COUNTIFS('Monthly Activity Log'!B$4:B$200,$B$3,'Monthly Activity Log'!H$4:H$200,"SANPC/SFF",'Monthly Activity Log'!I$4:I$200,"Project")),IF($B$3="All",COUNTIFS('Monthly Activity Log'!H$4:H$200,"SANPC/SFF",'Monthly Activity Log'!I$4:I$200,"Incident/Bug Fix"),COUNTIFS('Monthly Activity Log'!B$4:B$200,$B$3,'Monthly Activity Log'!H$4:H$200,"SANPC/SFF",'Monthly Activity Log'!I$4:I$200,"Incident/Bug Fix")),IF($B$3="All",COUNTIFS('Monthly Activity Log'!H$4:H$200,"SANPC/SFF",'Monthly Activity Log'!I$4:I$200,"Change Request"),COUNTIFS('Monthly Activity Log'!B$4:B$200,$B$3,'Monthly Activity Log'!H$4:H$200,"SANPC/SFF",'Monthly Activity Log'!I$4:I$200,"Change Request")),IF($B$3="All",COUNTIFS('Monthly Activity Log'!H$4:H$200,"SANPC/SFF",'Monthly Activity Log'!I$4:I$200,"User Support"),COUNTIFS('Monthly Activity Log'!B$4:B$200,$B$3,'Monthly Activity Log'!H$4:H$200,"SANPC/SFF",'Monthly Activity Log'!I$4:I$200,"User Support")),IF($B$3="All",COUNTIFS('Monthly Activity Log'!H$4:H$200,"SANPC/SFF",'Monthly Activity Log'!I$4:I$200,"Admin/Config"),COUNTIFS('Monthly Activity Log'!B$4:B$200,$B$3,'Monthly Activity Log'!H$4:H$200,"SANPC/SFF",'Monthly Activity Log'!I$4:I$200,"Admin/Config")),IF($B$3="All",COUNTIFS('Monthly Activity Log'!H$4:H$200,"SANPC/SFF",'Monthly Activity Log'!I$4:I$200,"Reporting"),COUNTIFS('Monthly Activity Log'!B$4:B$200,$B$3,'Monthly Activity Log'!H$4:H$200,"SANPC/SFF",'Monthly Activity Log'!I$4:I$200,"Reporting")),IF($B$3="All",COUNTIFS('Monthly Activity Log'!H$4:H$200,"SANPC/SFF",'Monthly Activity Log'!I$4:I$200,"Mentoring"),COUNTIFS('Monthly Activity Log'!B$4:B$200,$B$3,'Monthly Activity Log'!H$4:H$200,"SANPC/SFF",'Monthly Activity Log'!I$4:I$200,"Mentoring")),IF($B$3="All",COUNTIFS('Monthly Activity Log'!H$4:H$200,"SANPC/SFF",'Monthly Activity Log'!I$4:I$200,"Other"),COUNTIFS('Monthly Activity Log'!B$4:B$200,$B$3,'Monthly Activity Log'!H$4:H$200,"SANPC/SFF",'Monthly Activity Log'!I$4:I$200,"Other"))),"Mentoring",IF(IF($B$3="All",COUNTIFS('Monthly Activity Log'!H$4:H$200,"SANPC/SFF",'Monthly Activity Log'!I$4:I$200,"Other"),COUNTIFS('Monthly Activity Log'!B$4:B$200,$B$3,'Monthly Activity Log'!H$4:H$200,"SANPC/SFF",'Monthly Activity Log'!I$4:I$200,"Other"))=MAX(IF($B$3="All",COUNTIFS('Monthly Activity Log'!H$4:H$200,"SANPC/SFF",'Monthly Activity Log'!I$4:I$200,"Project"),COUNTIFS('Monthly Activity Log'!B$4:B$200,$B$3,'Monthly Activity Log'!H$4:H$200,"SANPC/SFF",'Monthly Activity Log'!I$4:I$200,"Project")),IF($B$3="All",COUNTIFS('Monthly Activity Log'!H$4:H$200,"SANPC/SFF",'Monthly Activity Log'!I$4:I$200,"Incident/Bug Fix"),COUNTIFS('Monthly Activity Log'!B$4:B$200,$B$3,'Monthly Activity Log'!H$4:H$200,"SANPC/SFF",'Monthly Activity Log'!I$4:I$200,"Incident/Bug Fix")),IF($B$3="All",COUNTIFS('Monthly Activity Log'!H$4:H$200,"SANPC/SFF",'Monthly Activity Log'!I$4:I$200,"Change Request"),COUNTIFS('Monthly Activity Log'!B$4:B$200,$B$3,'Monthly Activity Log'!H$4:H$200,"SANPC/SFF",'Monthly Activity Log'!I$4:I$200,"Change Request")),IF($B$3="All",COUNTIFS('Monthly Activity Log'!H$4:H$200,"SANPC/SFF",'Monthly Activity Log'!I$4:I$200,"User Support"),COUNTIFS('Monthly Activity Log'!B$4:B$200,$B$3,'Monthly Activity Log'!H$4:H$200,"SANPC/SFF",'Monthly Activity Log'!I$4:I$200,"User Support")),IF($B$3="All",COUNTIFS('Monthly Activity Log'!H$4:H$200,"SANPC/SFF",'Monthly Activity Log'!I$4:I$200,"Admin/Config"),COUNTIFS('Monthly Activity Log'!B$4:B$200,$B$3,'Monthly Activity Log'!H$4:H$200,"SANPC/SFF",'Monthly Activity Log'!I$4:I$200,"Admin/Config")),IF($B$3="All",COUNTIFS('Monthly Activity Log'!H$4:H$200,"SANPC/SFF",'Monthly Activity Log'!I$4:I$200,"Reporting"),COUNTIFS('Monthly Activity Log'!B$4:B$200,$B$3,'Monthly Activity Log'!H$4:H$200,"SANPC/SFF",'Monthly Activity Log'!I$4:I$200,"Reporting")),IF($B$3="All",COUNTIFS('Monthly Activity Log'!H$4:H$200,"SANPC/SFF",'Monthly Activity Log'!I$4:I$200,"Mentoring"),COUNTIFS('Monthly Activity Log'!B$4:B$200,$B$3,'Monthly Activity Log'!H$4:H$200,"SANPC/SFF",'Monthly Activity Log'!I$4:I$200,"Mentoring")),IF($B$3="All",COUNTIFS('Monthly Activity Log'!H$4:H$200,"SANPC/SFF",'Monthly Activity Log'!I$4:I$200,"Other"),COUNTIFS('Monthly Activity Log'!B$4:B$200,$B$3,'Monthly Activity Log'!H$4:H$200,"SANPC/SFF",'Monthly Activity Log'!I$4:I$200,"Other"))),"Other","-"))))))))) | J9: =D9+E9
